Workbook

Sheet New Signups
P1: Wave 1 | AA1: Wave 2 | AO1: Wave 3
B2: PID | C2: Record ID | D2: First Name | E2: Last Name | F2: Gender | G2: Age | H2: Parent Name | I2: Guardian/Older Cohort Phone | J2: Child Phone | L2: Recruitment Source | M2: LONG TERM NOTES | N2: Next Contact Step | O2: Next date to contact | P2: Wave 1 initial contact | Q2: Schedule Screener | R2: Screener | S2: Schedule V1 | T2: v1 reminder | U2: Check for v1 completion | V2: Schedule V2 | W2: 4 days before v2 reminder | X2: 1 day before v2 reminder | Y2: Check for v2 completion | Z2: Wave 2 start month | AA2: Wave 2 initial contact | AB2: Schedule Screener | AC2: Screener | AD2: Schedule V1 | AE2: 3 day before V1 reminder | AF2: v1 reminder | AG2: Check for v1 completion | AH2: Check at Home survey completion | AI2: Schedule V2 | AJ2: 4 days before v2 reminder | AK2: 1 day before v2 reminder | AL2: Check for v2 completion | AM2: Travel Payments (send text and set auto email) | AN2: Wave 3 start month | AO2: Wave 3 initial contact | AP2: Schedule Screener | AQ2: Screener | AR2: Schedule V1 | AS2: v1 reminder | AT2: Check for v1 completion | AU2: V1 Payment | AV2: Schedule V2 | AW2: 4 days before v2 reminder | AX2: 1 day before v2 reminder | AY2: Check for v2 completion | AZ2: Travel Payments (send text and set auto email)
B3: {=ifna(iferror(xlookup(C:C,'1000'!A:A,'1000'!D:D),iferror(xlookup(C:C,'2000'!A:A,'2000'!D:D),xlookup(C:C,'3000'!A:A,'3000'!D:D))),"-")} -> 1114 | C3: 1609 | D3: nia | E3: brown | F3: Female (1) | G3: 12 | H3: Regina brown | I3: (215) 251-7688 | J3: (215) 551-7688 | K3: CLINICONTACT | L3: CLINICONTACT | N3: dont contact until avi clears - schedule screener - If no response, x. - AD 5/5/2026 | O3: 46167 | P3: TP | Q3: DZ | R3: MV | S3: MV | T3: MV | U3: DZ | V3: DZ | W3: MV | X3: MV | Y3: MV | Z3: {=IFERROR(xlookup(C:C,'Follow up.1'!A:A,'Follow up.1'!AF:AF),"-")} -> 05/26 | AA3: AC | AN3: {=IF(LEFT(B3,1)="3","x",IFNA(LET(raw,XLOOKUP(C3,'Follow up.2'!B:B,'Follow up.2'!AF:AF),IF(OR(raw="",raw=0),"-",TEXT(MIN(--raw,DATE(2027,6,1)),"mm/yyyy"))),"-"))} -> -
B4: {=ifna(iferror(xlookup(C:C,'1000'!A:A,'1000'!D:D),iferror(xlookup(C:C,'2000'!A:A,'2000'!D:D),xlookup(C:C,'3000'!A:A,'3000'!D:D))),"-")} -> 1124 | C4: 1703 | D4: Layala | E4: Dachs | F4: F | G4: 12 | H4: Avi Dachs | I4: (267) 285-3947 | L4: Avi's sister | M4: Text "Avi" to schedule | N4: w3 intial contact (ANDY SET DATE) | O4: 46167 | P4: AD | Q4: AD | R4: AD | S4: AD | T4: AD | U4: AD | V4: MV | W4: MV | X4: MV | Y4: CP | Z4: {=IFERROR(xlookup(C:C,'Follow up.1'!A:A,'Follow up.1'!AF:AF),"-")} -> 05/26 | AA4: AC | AB4: AD | AC4: AD | AD4: AD | AE4: X | AF4: X | AG4: X | AH4: KD | AI4: AD | AN4: {=IF(LEFT(B4,1)="3","x",IFNA(LET(raw,XLOOKUP(C4,'Follow up.2'!B:B,'Follow up.2'!AF:AF),IF(OR(raw="",raw=0),"-",TEXT(MIN(--raw,DATE(2027,6,1)),"mm/yyyy"))),"-"))} -> -
B5: {=ifna(iferror(xlookup(C:C,'1000'!A:A,'1000'!D:D),iferror(xlookup(C:C,'2000'!A:A,'2000'!D:D),xlookup(C:C,'3000'!A:A,'3000'!D:D))),"-")} -> 2098 | C5: 1859 | D5: Niang | E5: Dim Mang | F5: Female (1) | G5: 14 | H5: manu | I5: (260)702-5469 | J5: (215) 433-2036 | K5: niang.mang210@gmail.com | L5: CLINICONTACT | M5: her receipts got switched v2 reciept is actually v1 | N5: W3 initial contact (ANDY SET DATE) | O5: 46167 | P5: CP | Q5: MV | R5: MV | S5: MV | T5: TP | U5: MV | V5: MV | W5: IA | X5: CP | Y5: MV | Z5: {=IFERROR(xlookup(C:C,'Follow up.1'!A:A,'Follow up.1'!AF:AF),"-")} -> 05/26 | AA5: AC | AB5: AC | AC5: AC | AD5: AC | AE5: AC | AF5: AC | AG5: AC | AI5: AD | AJ5: AD | AL5: AC | AM5: AC | AN5: {=IF(LEFT(B5,1)="3","x",IFNA(LET(raw,XLOOKUP(C5,'Follow up.2'!B:B,'Follow up.2'!AF:AF),IF(OR(raw="",raw=0),"-",TEXT(MIN(--raw,DATE(2027,6,1)),"mm/yyyy"))),"-"))} -> -
B6: {=ifna(iferror(xlookup(C:C,'1000'!A:A,'1000'!D:D),iferror(xlookup(C:C,'2000'!A:A,'2000'!D:D),xlookup(C:C,'3000'!A:A,'3000'!D:D))),"-")} -> 2106 | C6: 1647 | D6: Ian | E6: Navarro | F6: Male (2) | G6: 15 | H6: Yalitza Perez | I6: (267) 319-4267 | J6: (267) 581-2238 | K6: CLINICONTACT | L6: CLINICONTACT | N6: Travel payments | O6: 46167 | P6: DZ | Q6: DZ | R6: BS | S6: BS | T6: MV | U6: MV | V6: MV | W6: MV | X6: DZ | Y6: DZ | Z6: {=IFERROR(xlookup(C:C,'Follow up.1'!A:A,'Follow up.1'!AF:AF),"-")} -> 05/26 | AA6: AC | AD6: AD | AE6: AN | AF6: AN | AG6: AP | AJ6: AC | AK6: AN | AL6: AP | AN6: {=IF(LEFT(B6,1)="3","x",IFNA(LET(raw,XLOOKUP(C6,'Follow up.2'!B:B,'Follow up.2'!AF:AF),IF(OR(raw="",raw=0),"-",TEXT(MIN(--raw,DATE(2027,6,1)),"mm/yyyy"))),"-"))} -> 06/2027
B7: {=ifna(iferror(xlookup(C:C,'1000'!A:A,'1000'!D:D),iferror(xlookup(C:C,'2000'!A:A,'2000'!D:D),xlookup(C:C,'3000'!A:A,'3000'!D:D))),"-")} -> 1117 | C7: 1614 | D7: Liam | E7: Galvez | F7: male | G7: 12 | H7: Dana Newsome | I7: (215) 510-6544 | J7: (215) 510-6544 | K7: CLINICONTACT | L7: CLINICONTACT | M7: saw they were called | N7: wait to contact again until Avi clears them (v2) | O7: 46171 | P7: TP | Q7: DZ | R7: DZ | S7: DZ | T7: DZ | U7: BS | V7: KL | W7: MV | X7: MV | Y7: AK | Z7: {=IFERROR(xlookup(C:C,'Follow up.1'!A:A,'Follow up.1'!AF:AF),"-")} -> 04/26 | AA7: BH | AB7: BH | AC7: AC | AE7: CP | AF7: MV | AG7: RY | AN7: {=IF(LEFT(B7,1)="3","x",IFNA(LET(raw,XLOOKUP(C7,'Follow up.2'!B:B,'Follow up.2'!AF:AF),IF(OR(raw="",raw=0),"-",TEXT(MIN(--raw,DATE(2027,6,1)),"mm/yyyy"))),"-"))} -> -
B8: 2112 | C8: 1830 | D8: Kristian | E8: Kilgore | F8: Male (2) | G8: 15 | H8: Dinah Jiles | I8: (267) 776-3612 | J8: (267) 579-8298 | L8: A family member who was also signing up | M8: needs to reschedule v1 (canceled x1 - add reason here) | N8: wait to contact again until Avi clears them (cut?) | O8: 46171 | P8: MV | Q8: MV | R8: MV | S8: MV | T8: MV | U8: MV | V8: MV | W8: AK | X8: AK | Y8: MV | Z8: {=IFERROR(xlookup(C:C,'Follow up.1'!A:A,'Follow up.1'!AF:AF),"-")} -> 04/26 | AA8: BH | AF8: CP | AN8: {=IF(LEFT(B8,1)="3","x",IFNA(LET(raw,XLOOKUP(C8,'Follow up.2'!B:B,'Follow up.2'!AF:AF),IF(OR(raw="",raw=0),"-",TEXT(MIN(--raw,DATE(2027,6,1)),"mm/yyyy"))),"-"))} -> -
B9: {=ifna(iferror(xlookup(C:C,'1000'!A:A,'1000'!D:D),iferror(xlookup(C:C,'2000'!A:A,'2000'!D:D),xlookup(C:C,'3000'!A:A,'3000'!D:D))),"-")} -> 1070 | C9: 1356 | D9: Chaniel | E9: Rackley | F9: male | G9: 9 | H9: Kimberly Rackley | I9: (864) 404-6545 | K9: Clinicontact | L9: Clinicontact | M9: 1172/1171 sibling | N9: dont contact until avi clears- Schedule V1 | O9: 46174 | P9: DZ | Q9: DZ | R9: DZ | S9: DZ | T9: AD | U9: AM | V9: DZ | W9: AD | X9: AD | Y9: DZ | Z9: {=IFERROR(xlookup(C:C,'Follow up.1'!A:A,'Follow up.1'!AF:AF),"-")} -> 12/25 | AA9: KL | AB9: - | AC9: IA | AD9: IA | AN9: {=IF(LEFT(B9,1)="3","x",IFNA(LET(raw,XLOOKUP(C9,'Follow up.2'!B:B,'Follow up.2'!AF:AF),IF(OR(raw="",raw=0),"-",TEXT(MIN(--raw,DATE(2027,6,1)),"mm/yyyy"))),"-"))} -> -
B10: {=ifna(iferror(xlookup(C:C,'1000'!A:A,'1000'!D:D),iferror(xlookup(C:C,'2000'!A:A,'2000'!D:D),xlookup(C:C,'3000'!A:A,'3000'!D:D))),"-")} -> 1058 | C10: 1129 | D10: Hendrix | E10: Carpenter | F10: Male (2) | G10: 10 | H10: Ashley Carpenter | I10: (609) 929-2222 | K10: CLINICONTACT | L10: CLINICONTACT | M10: Reach out in summer b/c they live in NJ and do sports | N10: dont contact until avi clears- screener | O10: 46174 | P10: DH | Q10: AD | R10: AD | S10: AD | T10: DZ | U10: BS | V10: DZ | W10: BS | X10: BS | Y10: AM | Z10: {=IFERROR(xlookup(C:C,'Follow up.1'!A:A,'Follow up.1'!AF:AF),"-")} -> 10/25 | AA10: AD | AB10: KL | AC10: CP | AN10: {=IF(LEFT(B10,1)="3","x",IFNA(LET(raw,XLOOKUP(C10,'Follow up.2'!B:B,'Follow up.2'!AF:AF),IF(OR(raw="",raw=0),"-",TEXT(MIN(--raw,DATE(2027,6,1)),"mm/yyyy"))),"-"))} -> -
B11: {=ifna(iferror(xlookup(C:C,'1000'!A:A,'1000'!D:D),iferror(xlookup(C:C,'2000'!A:A,'2000'!D:D),xlookup(C:C,'3000'!A:A,'3000'!D:D))),"-")} -> 1007 | C11: 127 | D11: Morgan | E11: Weaver | F11: M | G11: 9 | H11: Jessica Weaver | I11: (267) 928-7334 | N11: w3 schedule screener (cut?) | O11: 46176 | P11: DZ | Q11: BS | R11: BS | S11: BS | T11: BS | U11: BS | V11: MV | W11: DZ | X11: DZ | Y11: DZ | Z11: {=IFERROR(xlookup(C:C,'Follow up.1'!A:A,'Follow up.1'!AF:AF),"-")} -> 10/24 | AA11: AM | AB11: AD | AC11: AD | AD11: AD | AF11: DZ | AG11: DZ | AI11: DZ | AJ11: DZ | AK11: KL | AL11: CP | AM11: n/a | AN11: {=IF(LEFT(B11,1)="3","x",IFNA(LET(raw,XLOOKUP(C11,'Follow up.2'!B:B,'Follow up.2'!AF:AF),IF(OR(raw="",raw=0),"-",TEXT(MIN(--raw,DATE(2027,6,1)),"mm/yyyy"))),"-"))} -> 06/2026 | AO11: AN
B12: {=ifna(iferror(xlookup(C:C,'1000'!A:A,'1000'!D:D),iferror(xlookup(C:C,'2000'!A:A,'2000'!D:D),xlookup(C:C,'3000'!A:A,'3000'!D:D))),"-")} -> 1064 | C12: 1208 | D12: Isaiah | E12: Watts | F12: Male | G12: 8 | H12: Catrisha Watts | I12: (757) 651-6569 | K12: CLINICONTACT | L12: CLINICONTACT | N12: wait to schedule v1 until Avi clears them | O12: 46181 | P12: DZ | Q12: DZ | R12: DZ | S12: DZ | T12: DZ | U12: DZ | V12: DZ | W12: KL | X12: KL | Y12: MV | Z12: {=IFERROR(xlookup(C:C,'Follow up.1'!A:A,'Follow up.1'!AF:AF),"-")} -> 04/26 | AA12: AC | AB12: MS | AC12: MS | AD12: MS | AN12: {=IF(LEFT(B12,1)="3","x",IFNA(LET(raw,XLOOKUP(C12,'Follow up.2'!B:B,'Follow up.2'!AF:AF),IF(OR(raw="",raw=0),"-",TEXT(MIN(--raw,DATE(2027,6,1)),"mm/yyyy"))),"-"))} -> -
B13: {=ifna(iferror(xlookup(C:C,'1000'!A:A,'1000'!D:D),iferror(xlookup(C:C,'2000'!A:A,'2000'!D:D),xlookup(C:C,'3000'!A:A,'3000'!D:D))),"-")} -> 1063 | C13: 1207 | D13: Shiloh | E13: Watts | F13: Male | G13: 11 | H13: Catrisha Watts | I13: (757) 651-6569 | K13: CLINICONTACT | L13: CLINICONTACT | N13: wait to schedule v1 until Avi clears them | O13: 46181 | P13: DZ | Q13: DZ | R13: DZ | S13: DZ | T13: DZ | U13: DZ | V13: DZ | W13: KL | X13: KL | Y13: MV | Z13: {=IFERROR(xlookup(C:C,'Follow up.1'!A:A,'Follow up.1'!AF:AF),"-")} -> 04/26 | AA13: AC | AB13: MS | AC13: MS | AD13: MS | AN13: {=IF(LEFT(B13,1)="3","x",IFNA(LET(raw,XLOOKUP(C13,'Follow up.2'!B:B,'Follow up.2'!AF:AF),IF(OR(raw="",raw=0),"-",TEXT(MIN(--raw,DATE(2027,6,1)),"mm/yyyy"))),"-"))} -> -
B14: {=ifna(iferror(xlookup(C:C,'1000'!A:A,'1000'!D:D),iferror(xlookup(C:C,'2000'!A:A,'2000'!D:D),xlookup(C:C,'3000'!A:A,'3000'!D:D))),"-")} -> 2051 | C14: 1076 | D14: Judah | E14: Watts | F14: M | G14: M15 | H14: Catrisha Watts | I14: (757) 651-6569 | J14: (757) 470-6417 | K14: CLINICONTACT | L14: CLINICONTACT | M14: 1194 sibling | N14: Wait to schedule v2 until Avi clears them | O14: 46181 | P14: BS | Q14: DZ | R14: DZ | S14: DZ | T14: AD | U14: DZ | V14: DZ | W14: DZ | X14: DZ | Y14: DZ | Z14: {=IFERROR(xlookup(C:C,'Follow up.1'!A:A,'Follow up.1'!AF:AF),"-")} -> 10/25 | AA14: AK | AB14: AM | AC14: SM | AD14: AD | AF14: AC | AG14: AK | AI14: BH, CP | AJ14: AD,AD | AK14: AC, RY | AN14: {=IF(LEFT(B14,1)="3","x",IFNA(LET(raw,XLOOKUP(C14,'Follow up.2'!B:B,'Follow up.2'!AF:AF),IF(OR(raw="",raw=0),"-",TEXT(MIN(--raw,DATE(2027,6,1)),"mm/yyyy"))),"-"))} -> -
B15: {=ifna(iferror(xlookup(C:C,'1000'!A:A,'1000'!D:D),iferror(xlookup(C:C,'2000'!A:A,'2000'!D:D),xlookup(C:C,'3000'!A:A,'3000'!D:D))),"-")} -> 2005 | C15: 13 | D15: Elliott | E15: Clair | H15: Orli Gal | I15: (267) 265-8456 | J15: 267-909-6200 | M15: waiting for flights to get scheduled | N15: dont contact until avi clears- Schedule v1/ child living in west coast | O15: 46181 | P15: DZ | Q15: DZ | R15: DZ | S15: DZ | T15: DZ | U15: DZ | V15: DZ | W15: DZ | X15: DZ | Y15: DZ | Z15: {=IFERROR(xlookup(C:C,'Follow up.1'!A:A,'Follow up.1'!AF:AF),"-")} -> 10/24 | AA15: MV | AB15: MV | AC15: MV | AD15: MV | AF15: MV | AG15: AK | AI15: MV | AJ15: DZ | AK15: DZ | AL15: DZ | AM15: n/a | AN15: {=IF(LEFT(B15,1)="3","x",IFNA(LET(raw,XLOOKUP(C15,'Follow up.2'!B:B,'Follow up.2'!AF:AF),IF(OR(raw="",raw=0),"-",TEXT(MIN(--raw,DATE(2027,6,1)),"mm/yyyy"))),"-"))} -> 03/2026 | AO15: CP
B16: {=ifna(iferror(xlookup(C:C,'1000'!A:A,'1000'!D:D),iferror(xlookup(C:C,'2000'!A:A,'2000'!D:D),xlookup(C:C,'3000'!A:A,'3000'!D:D))),"-")} -> 1127 | C16: 1754 | D16: Noelle | E16: Ferguson | F16: Female (1) | G16: 12 | H16: Christina Danielle Turner | I16: (267) 648-3537 | J16: (267) 438-9939 | L16: CLINICONTACT | N16: reschedule w2 Screener - called no answer 6/15/26 | O16: 46195 | P16: MV | Q16: KL | R16: KL | S16: KL | T16: KL | U16: MV | V16: KL | W16: MV | X16: CP | Y16: MV | Z16: {=IFERROR(xlookup(C:C,'Follow up.1'!A:A,'Follow up.1'!AF:AF),"-")} -> 05/26 | AA16: AC | AB16: AC | AJ16: AC | AN16: {=IF(LEFT(B16,1)="3","x",IFNA(LET(raw,XLOOKUP(C16,'Follow up.2'!B:B,'Follow up.2'!AF:AF),IF(OR(raw="",raw=0),"-",TEXT(MIN(--raw,DATE(2027,6,1)),"mm/yyyy"))),"-"))} -> -
B17: {=ifna(iferror(xlookup(C:C,'1000'!A:A,'1000'!D:D),iferror(xlookup(C:C,'2000'!A:A,'2000'!D:D),xlookup(C:C,'3000'!A:A,'3000'!D:D))),"-")} -> 2055 | C17: 1088 | D17: Gilpatrick | E17: Ben-Yaacov | F17: M | G17: M14 | H17: Kate Dugan | I17: (609) 744-1033 | J17: (215) 514-0531 | K17: (Awbury Arboretum summer camp) | L17: (Awbury Arboretum summer camp) | N17: w3 intital | O17: 46545 | P17: AM | Q17: DZ | R17: DZ | S17: DZ | T17: BS | U17: BS | V17: KL | W17: DZ | X17: DZ | Y17: MV | Z17: {=IFERROR(xlookup(C:C,'Follow up.1'!A:A,'Follow up.1'!AF:AF),"-")} -> 02/26 | AA17: MV | AB17: - | AC17: BH | AD17: BH | AF17: AC | AG17: RY | AI17: AP | AJ17: AC | AK17: AN | AL17: AP | AN17: {=IF(LEFT(B17,1)="3","x",IFNA(LET(raw,XLOOKUP(C17,'Follow up.2'!B:B,'Follow up.2'!AF:AF),IF(OR(raw="",raw=0),"-",TEXT(MIN(--raw,DATE(2027,6,1)),"mm/yyyy"))),"-"))} -> 06/2027
B18: {=ifna(iferror(xlookup(C:C,'1000'!A:A,'1000'!D:D),iferror(xlookup(C:C,'2000'!A:A,'2000'!D:D),xlookup(C:C,'3000'!A:A,'3000'!D:D))),"-")} -> 1105 | C18: 1574 | D18: Tyler | E18: Romanelli | F18: Male | G18: 9 | H18: Saki Sono Romanelli | I18: (203) 464-1205 | J18: (508) 808-2411 | K18: Mr. Naoya Tani | L18: Mr. Naoya Tani | M18: Maybe don't schedule v2, did not want to do v1 and notes show he quit v2 halfway through pat last year | N18: v2 schedule | O18: 46196 | P18: MV | Q18: AM | R18: AM | S18: AM | T18: DZ | U18: SB | V18: SB | W18: TP | X18: TP | Y18: MV | Z18: {=IFERROR(xlookup(C:C,'Follow up.1'!A:A,'Follow up.1'!AF:AF),"-")} -> 05/26 | AA18: AC | AD18: AC | AE18: AC | AF18: AP | AG18: RY | AN18: {=IF(LEFT(B18,1)="3","x",IFNA(LET(raw,XLOOKUP(C18,'Follow up.2'!B:B,'Follow up.2'!AF:AF),IF(OR(raw="",raw=0),"-",TEXT(MIN(--raw,DATE(2027,6,1)),"mm/yyyy"))),"-"))} -> -
B19: {=ifna(iferror(xlookup(C:C,'1000'!A:A,'1000'!D:D),iferror(xlookup(C:C,'2000'!A:A,'2000'!D:D),xlookup(C:C,'3000'!A:A,'3000'!D:D))),"-")} -> 2100 | C19: 1575 | D19: Allisa | E19: Romanelli | F19: Female | G19: 15 | H19: Saki Sono Romanelli | I19: (203) 464-1205 | J19: (508) 808-2411 | K19: Mr. Naoya Tani | L19: Mr. Naoya Tani | N19: v2 schedule | O19: 46196 | P19: MV | Q19: AM | R19: AM | S19: AM | T19: DZ | U19: SB | V19: SB | W19: TP | X19: TP | Y19: MV | Z19: {=IFERROR(xlookup(C:C,'Follow up.1'!A:A,'Follow up.1'!AF:AF),"-")} -> - | AA19: AC | AD19: AC | AE19: AC | AF19: AP | AG19: RY | AN19: {=IF(LEFT(B19,1)="3","x",IFNA(LET(raw,XLOOKUP(C19,'Follow up.2'!B:B,'Follow up.2'!AF:AF),IF(OR(raw="",raw=0),"-",TEXT(MIN(--raw,DATE(2027,6,1)),"mm/yyyy"))),"-"))} -> -
B20: {=ifna(iferror(xlookup(C:C,'1000'!A:A,'1000'!D:D),iferror(xlookup(C:C,'2000'!A:A,'2000'!D:D),xlookup(C:C,'3000'!A:A,'3000'!D:D))),"-")} -> 2087 | C20: 1531 | D20: Layla | E20: Young | F20: Female | G20: 12 | H20: Sheliah Yuille | I20: (215) 201-8965 | K20: parent | L20: parent | N20: v2 schedule | O20: 46196 | P20: AM | Q20: DZ | R20: DZ | S20: DZ | T20: AM | U20: AM | V20: TP | W20: MV | X20: AM | Y20: AM | Z20: {=IFERROR(xlookup(C:C,'Follow up.1'!A:A,'Follow up.1'!AF:AF),"-")} -> 05/26 | AA20: AC | AB20: AD | AC20: AD | AD20: AP | AE20: AN | AF20: RY | AG20: RY | AN20: {=IF(LEFT(B20,1)="3","x",IFNA(LET(raw,XLOOKUP(C20,'Follow up.2'!B:B,'Follow up.2'!AF:AF),IF(OR(raw="",raw=0),"-",TEXT(MIN(--raw,DATE(2027,6,1)),"mm/yyyy"))),"-"))} -> -
B21: {=ifna(iferror(xlookup(C:C,'1000'!A:A,'1000'!D:D),iferror(xlookup(C:C,'2000'!A:A,'2000'!D:D),xlookup(C:C,'3000'!A:A,'3000'!D:D))),"-")} -> 2113 | C21: 1810 | D21: Chelsea | E21: George | F21: Female (1) | G21: 16 | H21: Chelsea G | I21: (267) 366-7176 | J21: (610) 803-6519 | L21: CLINICONTACT | M21: try and finish w2 no w3 | N21: reschedule v1/ghosting/ if no response cut them | O21: 46196 | P21: MV | Q21: MV | R21: MV | S21: MV | T21: KL | U21: MV | V21: KL | W21: AK | X21: AK | Y21: MV | Z21: {=IFERROR(xlookup(C:C,'Follow up.1'!A:A,'Follow up.1'!AF:AF),"-")} -> 05/26 | AA21: AC | AB21: AD | AC21: AD | AD21: AC | AE21: RY | AN21: {=IF(LEFT(B21,1)="3","x",IFNA(LET(raw,XLOOKUP(C21,'Follow up.2'!B:B,'Follow up.2'!AF:AF),IF(OR(raw="",raw=0),"-",TEXT(MIN(--raw,DATE(2027,6,1)),"mm/yyyy"))),"-"))} -> -
B22: {=ifna(iferror(xlookup(C:C,'1000'!A:A,'1000'!D:D),iferror(xlookup(C:C,'2000'!A:A,'2000'!D:D),xlookup(C:C,'3000'!A:A,'3000'!D:D))),"-")} -> 1128 | C22: 1806 | D22: Haylee | E22: Jones | F22: Female (1) | G22: 10 | H22: Joanne Carrasquillo | I22: (267) 761-6115 | J22: (484) 788-7075 | L22: CLINICONTACT | N22: v2 reminder 1 day | O22: 46196 | P22: MV | Q22: KL | R22: KL | S22: KL | T22: MV | U22: KL | V22: KL | W22: MV | X22: MV | Y22: KL | Z22: {=IFERROR(xlookup(C:C,'Follow up.1'!A:A,'Follow up.1'!AF:AF),"-")} -> 05/26 | AA22: AC | AB22: AD | AC22: MS | AD22: MS | AE22: AC | AF22: AC | AG22: AD | AH22: AD | AJ22: AP | AN22: {=IF(LEFT(B22,1)="3","x",IFNA(LET(raw,XLOOKUP(C22,'Follow up.2'!B:B,'Follow up.2'!AF:AF),IF(OR(raw="",raw=0),"-",TEXT(MIN(--raw,DATE(2027,6,1)),"mm/yyyy"))),"-"))} -> -
B23: {=ifna(iferror(xlookup(C:C,'1000'!A:A,'1000'!D:D),iferror(xlookup(C:C,'2000'!A:A,'2000'!D:D),xlookup(C:C,'3000'!A:A,'3000'!D:D))),"-")} -> 1089 | C23: 1538 | D23: Sebastien | E23: Mason | F23: Male | G23: 10 | H23: Emily Mason | I23: (917) 698-9694 | K23: email | L23: email | M23: siblings with 2086 no w3 | N23: Follow-Up About V1 Scheduling | O23: 46196 | P23: MV | Q23: DZ | R23: DZ | S23: DZ | T23: DZ | U23: TP | V23: KL | W23: DZ | X23: DZ | Y23: DZ | Z23: {=IFERROR(xlookup(C:C,'Follow up.1'!A:A,'Follow up.1'!AF:AF),"-")} -> 04/26 | AA23: BH | AB23: MS | AC23: EB | AD23: EB | AN23: {=IF(LEFT(B23,1)="3","x",IFNA(LET(raw,XLOOKUP(C23,'Follow up.2'!B:B,'Follow up.2'!AF:AF),IF(OR(raw="",raw=0),"-",TEXT(MIN(--raw,DATE(2027,6,1)),"mm/yyyy"))),"-"))} -> -
B24: {=ifna(iferror(xlookup(C:C,'1000'!A:A,'1000'!D:D),iferror(xlookup(C:C,'2000'!A:A,'2000'!D:D),xlookup(C:C,'3000'!A:A,'3000'!D:D))),"-")} -> 2086 | C24: 1537 | D24: Oliver | E24: Mason | F24: Male | G24: 14 | H24: Emily Mason | I24: (917) 698-9694 | J24: (856) 631-4323 | K24: email | L24: email | M24: siblings with 1089 | N24: Follow-Up About V1 Scheduling | O24: 46196 | P24: MV | Q24: DZ | R24: DZ | S24: DZ | T24: DZ | U24: DZ | V24: DZ | W24: AD | X24: AD | Y24: DZ | Z24: {=IFERROR(xlookup(C:C,'Follow up.1'!A:A,'Follow up.1'!AF:AF),"-")} -> 04/26 | AA24: BH | AB24: MS | AC24: EB | AD24: EB | AN24: {=IF(LEFT(B24,1)="3","x",IFNA(LET(raw,XLOOKUP(C24,'Follow up.2'!B:B,'Follow up.2'!AF:AF),IF(OR(raw="",raw=0),"-",TEXT(MIN(--raw,DATE(2027,6,1)),"mm/yyyy"))),"-"))} -> -
B25: {=ifna(iferror(xlookup(C:C,'1000'!A:A,'1000'!D:D),iferror(xlookup(C:C,'2000'!A:A,'2000'!D:D),xlookup(C:C,'3000'!A:A,'3000'!D:D))),"-")} -> 1113 | C25: 1468 | D25: Lincoln she/her | E25: Monahan | F25: Female | G25: 7 | H25: Megan Monahan | I25: (610) 763-6696 | K25: Email | L25: Email | M25: Sibling is 1005 - delayed w2 contact date by month so siblings can come together- already completed screener? | N25: schedule WAVE2 v1- july date she wants | O25: 46196 | P25: MV | Q25: MV | R25: DZ | S25: DZ | T25: AD | U25: DZ | V25: DZ | W25: DZ | X25: DZ | Y25: DZ | Z25: {=IFERROR(xlookup(C:C,'Follow up.1'!A:A,'Follow up.1'!AF:AF),"-")} -> - | AA25: EB | AB25: EB | AC25: EB | AD25: EB | AF25: AP | AI25: EB | AN25: {=IF(LEFT(B25,1)="3","x",IFNA(LET(raw,XLOOKUP(C25,'Follow up.2'!B:B,'Follow up.2'!AF:AF),IF(OR(raw="",raw=0),"-",TEXT(MIN(--raw,DATE(2027,6,1)),"mm/yyyy"))),"-"))} -> -
B26: {=ifna(iferror(xlookup(C:C,'1000'!A:A,'1000'!D:D),iferror(xlookup(C:C,'2000'!A:A,'2000'!D:D),xlookup(C:C,'3000'!A:A,'3000'!D:D))),"-")} -> 1005 | C26: 57 | D26: Laughlin she/her | E26: Monahan | F26: Female | G26: 8 | H26: Megan Monahan | I26: (530) 263-7370 | J26: (530) 263-7370 | M26: Sibling is 1113 | N26: schedule WAVE3 v1- july date she wants | O26: 46196 | P26: DZ | Q26: DZ | R26: DZ | S26: DZ | T26: DZ | U26: DZ | V26: DZ | W26: DZ | X26: DZ | Y26: DZ | Z26: {=IFERROR(xlookup(C:C,'Follow up.1'!A:A,'Follow up.1'!AF:AF),"-")} -> 10/24 | AA26: SB | AB26: DZ | AC26: DZ | AD26: DZ | AF26: DZ | AG26: AD | AI26: DZ | AJ26: DZ | AK26: DZ | AL26: DZ | AM26: n/a | AN26: {=IF(LEFT(B26,1)="3","x",IFNA(LET(raw,XLOOKUP(C26,'Follow up.2'!B:B,'Follow up.2'!AF:AF),IF(OR(raw="",raw=0),"-",TEXT(MIN(--raw,DATE(2027,6,1)),"mm/yyyy"))),"-"))} -> 03/2026 | AO26: EB | AP26: EB | AQ26: EB
B27: {=ifna(iferror(xlookup(C:C,'1000'!A:A,'1000'!D:D),iferror(xlookup(C:C,'2000'!A:A,'2000'!D:D),xlookup(C:C,'3000'!A:A,'3000'!D:D))),"-")} -> 1130 | C27: 1927 | D27: Zarriah | E27: Williams | F27: Female (1) | G27: 11 | H27: Cherele washington | I27: (267) 628-8662 | L27: redcap - sibling in study | N27: Wave 2 initial contact | O27: 46197 | P27: MV | Q27: MV | R27: AK | S27: AK | T27: CP | U27: CP | V27: AD | W27: AK | X27: MV | Y27: CP | Z27: {=IFERROR(xlookup(C:C,'Follow up.1'!A:A,'Follow up.1'!AF:AF),"-")} -> 07/26 | AN27: {=IF(LEFT(B27,1)="3","x",IFNA(LET(raw,XLOOKUP(C27,'Follow up.2'!B:B,'Follow up.2'!AF:AF),IF(OR(raw="",raw=0),"-",TEXT(MIN(--raw,DATE(2027,6,1)),"mm/yyyy"))),"-"))} -> -
B28: {=ifna(iferror(xlookup(C:C,'1000'!A:A,'1000'!D:D),iferror(xlookup(C:C,'2000'!A:A,'2000'!D:D),xlookup(C:C,'3000'!A:A,'3000'!D:D))),"-")} -> 1002 | C28: 47 | D28: Vihaan | E28: Kaushik | G28: 10 | I28: (919) 428-0818 | J28: (919) 428-0818 | N28: Wave 3 schedule screener (travelling til end of july) | O28: 46202 | P28: AM | Q28: AM | R28: AM | S28: AM | T28: AM | U28: AM | V28: DZ | W28: BS | X28: BS | Y28: MV | Z28: {=IFERROR(xlookup(C:C,'Follow up.1'!A:A,'Follow up.1'!AF:AF),"-")} -> 10/24 | AA28: MV | AB28: MV | AC28: BS | AD28: BS | AF28: TP | AG28: MV | AI28: TP | AJ28: MV | AK28: Mv | AL28: MV | AM28: n/a | AN28: {=IF(LEFT(B28,1)="3","x",IFNA(LET(raw,XLOOKUP(C28,'Follow up.2'!B:B,'Follow up.2'!AF:AF),IF(OR(raw="",raw=0),"-",TEXT(MIN(--raw,DATE(2027,6,1)),"mm/yyyy"))),"-"))} -> 05/2026
B29: {=ifna(iferror(xlookup(C:C,'1000'!A:A,'1000'!D:D),iferror(xlookup(C:C,'2000'!A:A,'2000'!D:D),xlookup(C:C,'3000'!A:A,'3000'!D:D))),"-")} -> 2006 | C29: 48 | D29: Vrishab | E29: Kaushik | G29: 13 | H29: Dhivya Kaushik | I29: dhivyac@gmail.com | J29: (919) 428-0818 | N29: Wave 3 schedule screener (travelling til end of july) | O29: 46202 | P29: DZ | Q29: DZ | R29: DZ | S29: DZ | T29: DZ | U29: DZ | V29: DZ | W29: DZ | X29: DZ | Y29: DZ | Z29: {=IFERROR(xlookup(C:C,'Follow up.1'!A:A,'Follow up.1'!AF:AF),"-")} -> 10/24 | AA29: MV | AB29: MV | AC29: BS | AD29: BS | AF29: KL | AG29: MV | AI29: TP | AJ29: MV | AK29: MV | AL29: MV | AM29: n/a | AN29: {=IF(LEFT(B29,1)="3","x",IFNA(LET(raw,XLOOKUP(C29,'Follow up.2'!B:B,'Follow up.2'!AF:AF),IF(OR(raw="",raw=0),"-",TEXT(MIN(--raw,DATE(2027,6,1)),"mm/yyyy"))),"-"))} -> 04/2026 | AO29: CP
B30: {=ifna(iferror(xlookup(C:C,'1000'!A:A,'1000'!D:D),iferror(xlookup(C:C,'2000'!A:A,'2000'!D:D),xlookup(C:C,'3000'!A:A,'3000'!D:D))),"-")} -> 2111 | C30: 1765 | D30: Emani | E30: wooden | F30: Female (1) | G30: 15 | I30: (267) 699-1405 | J30: (267) 560-6952 | L30: CLINICONTACT | N30: schedule screener - called mom but she couldn't hear- ghosting? | O30: 46202 | P30: KL | Q30: MV | R30: MV | S30: MV | T30: MV | U30: MV | V30: MV | W30: AK | X30: AK | Y30: MV | Z30: {=IFERROR(xlookup(C:C,'Follow up.1'!A:A,'Follow up.1'!AF:AF),"-")} -> 04/26 | AA30: BH | AN30: {=IF(LEFT(B30,1)="3","x",IFNA(LET(raw,XLOOKUP(C30,'Follow up.2'!B:B,'Follow up.2'!AF:AF),IF(OR(raw="",raw=0),"-",TEXT(MIN(--raw,DATE(2027,6,1)),"mm/yyyy"))),"-"))} -> -
B31: {=ifna(iferror(xlookup(C:C,'1000'!A:A,'1000'!D:D),iferror(xlookup(C:C,'2000'!A:A,'2000'!D:D),xlookup(C:C,'3000'!A:A,'3000'!D:D))),"-")} -> 1129 | C31: 1781 | D31: Za'Haad | E31: Covington-Walley | F31: Male (2) | G31: 10 | H31: Erica Covington | I31: (215) 397-7672 | J31: (215) 397-7672 | L31: CLINICONTACT | N31: Wave 2 intial content (if no scan no w3) | O31: 46204 | P31: KL | Q31: MV | R31: KL | S31: KL | T31: MV | U31: MV | V31: KL | W31: KL | X31: IA | Y31: AMo | Z31: {=IFERROR(xlookup(C:C,'Follow up.1'!A:A,'Follow up.1'!AF:AF),"-")} -> 07/26 | AN31: {=IF(LEFT(B31,1)="3","x",IFNA(LET(raw,XLOOKUP(C31,'Follow up.2'!B:B,'Follow up.2'!AF:AF),IF(OR(raw="",raw=0),"-",TEXT(MIN(--raw,DATE(2027,6,1)),"mm/yyyy"))),"-"))} -> -
B32: {=ifna(iferror(xlookup(C:C,'1000'!A:A,'1000'!D:D),iferror(xlookup(C:C,'2000'!A:A,'2000'!D:D),xlookup(C:C,'3000'!A:A,'3000'!D:D))),"-")} -> 1011 | C32: 76 | D32: Caleb | E32: Davis | F32: M | G32: 12 | H32: Rebecca davis | I32: (215) 498-6017 | N32: Wave 3 intial contact (not on a team list but good contact and age?) | O32: 46204 | P32: DZ | Q32: BS | R32: BS | S32: BS | T32: BS | U32: BS | V32: MV | W32: DZ | X32: DZ | Y32: DZ | Z32: {=IFERROR(xlookup(C:C,'Follow up.1'!A:A,'Follow up.1'!AF:AF),"-")} -> 10/24 | AA32: TP | AB32: CP | AC32: DZ | AD32: DZ | AF32: KL | AG32: TP | AI32: CP | AJ32: TP | AK32: KL | AL32: CP | AM32: n/a | AN32: {=IF(LEFT(B32,1)="3","x",IFNA(LET(raw,XLOOKUP(C32,'Follow up.2'!B:B,'Follow up.2'!AF:AF),IF(OR(raw="",raw=0),"-",TEXT(MIN(--raw,DATE(2027,6,1)),"mm/yyyy"))),"-"))} -> 07/2026 | AO32: 46204
B33: {=ifna(iferror(xlookup(C:C,'1000'!A:A,'1000'!D:D),iferror(xlookup(C:C,'2000'!A:A,'2000'!D:D),xlookup(C:C,'3000'!A:A,'3000'!D:D))),"-")} -> 2126 | C33: 1883 | D33: Makynzi | E33: jones | F33: Female (1) | G33: 13 | H33: Brittani Jones | I33: 2154105186 | J33: 2677098301 | L33: CLINICONTACT | N33: Wave 2 Initial Contact- if issues with scanner no w3 | O33: 46204 | P33: MV | Q33: MV | R33: DZ | S33: CP | T33: CP | U33: MV | V33: CP | W33: CP | X33: IA | Y33: CP | Z33: {=IFERROR(xlookup(C:C,'Follow up.1'!A:A,'Follow up.1'!AF:AF),"-")} -> 07/26 | AN33: {=IF(LEFT(B33,1)="3","x",IFNA(LET(raw,XLOOKUP(C33,'Follow up.2'!B:B,'Follow up.2'!AF:AF),IF(OR(raw="",raw=0),"-",TEXT(MIN(--raw,DATE(2027,6,1)),"mm/yyyy"))),"-"))} -> -
B34: {=ifna(iferror(xlookup(C:C,'1000'!A:A,'1000'!D:D),iferror(xlookup(C:C,'2000'!A:A,'2000'!D:D),xlookup(C:C,'3000'!A:A,'3000'!D:D))),"-")} -> 2127 | C34: 1862 | D34: Isaiah | E34: Scott | F34: Male (2) | G34: 14 | H34: Felicia Wrice-Scott | I34: (267) 738-1138 | J34: (267) 586-7726 | K34: fwrice76@gmail.com | L34: CLINICONTACT | N34: Wave 2 Initial Contact | O34: 46204 | P34: CP | Q34: MV | R34: DZ | S34: MV | T34: AM | U34: MV | V34: CP | W34: IA | X34: MV | Y34: IA | Z34: {=IFERROR(xlookup(C:C,'Follow up.1'!A:A,'Follow up.1'!AF:AF),"-")} -> 07/26 | AN34: {=IF(LEFT(B34,1)="3","x",IFNA(LET(raw,XLOOKUP(C34,'Follow up.2'!B:B,'Follow up.2'!AF:AF),IF(OR(raw="",raw=0),"-",TEXT(MIN(--raw,DATE(2027,6,1)),"mm/yyyy"))),"-"))} -> -
B35: {=ifna(iferror(xlookup(C:C,'1000'!A:A,'1000'!D:D),iferror(xlookup(C:C,'2000'!A:A,'2000'!D:D),xlookup(C:C,'3000'!A:A,'3000'!D:D))),"-")} -> 2119 | C35: 1867 | D35: Maia | E35: LaMonte | F35: Female (1) | G35: 15 | H35: April LaMonte | I35: (484) 888-6718 | J35: (484) 888-6718 | K35: thelamontefamily@gmail.com | L35: CLINICONTACT | N35: Wave 2 Initial contact | O35: 46204 | P35: CP | Q35: MS | R35: AD | S35: AD | T35: Kl | U35: KL | V35: AM | W35: CP | X35: IA | Y35: MV | Z35: {=IFERROR(xlookup(C:C,'Follow up.1'!A:A,'Follow up.1'!AF:AF),"-")} -> 07/26 | AN35: {=IF(LEFT(B35,1)="3","x",IFNA(LET(raw,XLOOKUP(C35,'Follow up.2'!B:B,'Follow up.2'!AF:AF),IF(OR(raw="",raw=0),"-",TEXT(MIN(--raw,DATE(2027,6,1)),"mm/yyyy"))),"-"))} -> -
B36: {=ifna(iferror(xlookup(C:C,'1000'!A:A,'1000'!D:D),iferror(xlookup(C:C,'2000'!A:A,'2000'!D:D),xlookup(C:C,'3000'!A:A,'3000'!D:D))),"-")} -> 2125 | C36: 1884 | D36: Kyrah | E36: Ferguson | F36: Female (1) | G36: 15 | H36: Safiyyah Carter Pack | I36: (267) 648-6297 | J36: 2159173433 | L36: CLINICONTACT | N36: Wave 2 intial contact | O36: 46204 | P36: IA | Q36: MV | R36: IA | S36: IA | T36: CP | U36: MV | V36: MV | W36: MV | X36: KL | Y36: MV | Z36: {=IFERROR(xlookup(C:C,'Follow up.1'!A:A,'Follow up.1'!AF:AF),"-")} -> 07/26 | AN36: {=IF(LEFT(B36,1)="3","x",IFNA(LET(raw,XLOOKUP(C36,'Follow up.2'!B:B,'Follow up.2'!AF:AF),IF(OR(raw="",raw=0),"-",TEXT(MIN(--raw,DATE(2027,6,1)),"mm/yyyy"))),"-"))} -> -
B37: {=ifna(iferror(xlookup(C:C,'1000'!A:A,'1000'!D:D),iferror(xlookup(C:C,'2000'!A:A,'2000'!D:D),xlookup(C:C,'3000'!A:A,'3000'!D:D))),"-")} -> 2117 | C37: 1855 | D37: Beniris | E37: Cumbe-Gonzalez | F37: Female (1) | G37: 16 | H37: Beniris C-G | I37: 787-549-0402 | J37: (215) 209-9982 | K37: beniriscristal@gmail.com | L37: CLINICONTACT | N37: dont contact until avi clears - w2 initial | O37: 46204 | P37: MV | Q37: MV | R37: MV | S37: MV | T37: CP | U37: KL | V37: MV | W37: CP | X37: KL | Y37: MV | Z37: {=IFERROR(xlookup(C:C,'Follow up.1'!A:A,'Follow up.1'!AF:AF),"-")} -> 07/26 | AN37: {=IF(LEFT(B37,1)="3","x",IFNA(LET(raw,XLOOKUP(C37,'Follow up.2'!B:B,'Follow up.2'!AF:AF),IF(OR(raw="",raw=0),"-",TEXT(MIN(--raw,DATE(2027,6,1)),"mm/yyyy"))),"-"))} -> -
B38: {=ifna(iferror(xlookup(C:C,'1000'!A:A,'1000'!D:D),iferror(xlookup(C:C,'2000'!A:A,'2000'!D:D),xlookup(C:C,'3000'!A:A,'3000'!D:D))),"-")} -> 2130 | C38: 1835 | D38: Zariyah | E38: Covington | F38: Female (1) | G38: 16 | H38: Erica Covington | I38: (215) 397-7672 | L38: Sibling is 1781 | N38: Wave 2 inital contact | O38: 46204 | P38: KL | Q38: KL | R38: KL | S38: AK | T38: KL | U38: AD | V38: KL | W38: KL | X38: IA | Y38: MV | Z38: {=IFERROR(xlookup(C:C,'Follow up.1'!A:A,'Follow up.1'!AF:AF),"-")} -> 07/26 | AN38: {=IF(LEFT(B38,1)="3","x",IFNA(LET(raw,XLOOKUP(C38,'Follow up.2'!B:B,'Follow up.2'!AF:AF),IF(OR(raw="",raw=0),"-",TEXT(MIN(--raw,DATE(2027,6,1)),"mm/yyyy"))),"-"))} -> -
B39: {=ifna(iferror(xlookup(C:C,'1000'!A:A,'1000'!D:D),iferror(xlookup(C:C,'2000'!A:A,'2000'!D:D),xlookup(C:C,'3000'!A:A,'3000'!D:D))),"-")} -> 1012 | C39: 169 | D39: Magnolia (Maggie) | E39: Becker | F39: F | H39: Justin Becker (dad) Sarah becker (mom) | N39: Wave 3 initial contact | O39: 46204 | P39: MV | Q39: MV | R39: MV | S39: MV | T39: MV | U39: MV | V39: MV | W39: MV | X39: MV | Y39: MV | Z39: {=IFERROR(xlookup(C:C,'Follow up.1'!A:A,'Follow up.1'!AF:AF),"-")} -> 10/24 | AA39: AM | AB39: AM | AC39: AM | AD39: AM | AF39: KL | AG39: CP | AI39: KL | AJ39: CP | AK39: CP | AL39: KL | AM39: n/a | AN39: {=IF(LEFT(B39,1)="3","x",IFNA(LET(raw,XLOOKUP(C39,'Follow up.2'!B:B,'Follow up.2'!AF:AF),IF(OR(raw="",raw=0),"-",TEXT(MIN(--raw,DATE(2027,6,1)),"mm/yyyy"))),"-"))} -> 06/2026 | AO39: 46204
B40: {=ifna(iferror(xlookup(C:C,'1000'!A:A,'1000'!D:D),iferror(xlookup(C:C,'2000'!A:A,'2000'!D:D),xlookup(C:C,'3000'!A:A,'3000'!D:D))),"-")} -> 1017 | C40: 115 | D40: Iyannah | E40: Marshall* | I40: (609) 929-2222 | J40: (609) 929-2222 | N40: Wave 3 Initial Contact | O40: 46204 | P40: DZ | Q40: BS | R40: BS | S40: BS | T40: BS | U40: BS | V40: MV | W40: MV | X40: MV | Y40: MV | Z40: {=IFERROR(xlookup(C:C,'Follow up.1'!A:A,'Follow up.1'!AF:AF),"-")} -> 2/25 | AA40: MV | AB40: MV | AC40: MV | AD40: MV | AF40: CP | AG40: KL | AI40: DZ | AJ40: DZ | AK40: DZ | AL40: DZ | AM40: n/a | AN40: {=IF(LEFT(B40,1)="3","x",IFNA(LET(raw,XLOOKUP(C40,'Follow up.2'!B:B,'Follow up.2'!AF:AF),IF(OR(raw="",raw=0),"-",TEXT(MIN(--raw,DATE(2027,6,1)),"mm/yyyy"))),"-"))} -> 07/2026 | AO40: 46204
B41: {=ifna(iferror(xlookup(C:C,'1000'!A:A,'1000'!D:D),iferror(xlookup(C:C,'2000'!A:A,'2000'!D:D),xlookup(C:C,'3000'!A:A,'3000'!D:D))),"-")} -> 1132 | C41: 1880 | D41: Harmony | E41: Hall | F41: Female (1) | G41: 10 | H41: brieanna hall | I41: (267) 276-5451 | J41: (215) 913-2635 | L41: Sister to 1851 | N41: wave 2 initial contact (sibling - 1851) - No w3 if no scan | O41: 46207 | P41: MV | Q41: MV | R41: MV | S41: MV | T41: MV | U41: KL | V41: MS | W41: MV | X41: CP | Y41: MV | Z41: {=IFERROR(xlookup(C:C,'Follow up.1'!A:A,'Follow up.1'!AF:AF),"-")} -> 07/26 | AN41: {=IF(LEFT(B41,1)="3","x",IFNA(LET(raw,XLOOKUP(C41,'Follow up.2'!B:B,'Follow up.2'!AF:AF),IF(OR(raw="",raw=0),"-",TEXT(MIN(--raw,DATE(2027,6,1)),"mm/yyyy"))),"-"))} -> -
B42: {=ifna(iferror(xlookup(C:C,'1000'!A:A,'1000'!D:D),iferror(xlookup(C:C,'2000'!A:A,'2000'!D:D),xlookup(C:C,'3000'!A:A,'3000'!D:D))),"-")} -> 2129 | C42: 1851 | D42: Katelynn | E42: kirtz | F42: Female (1) | G42: 13 | H42: Brieanna Hall | I42: (267) 276-5451 | J42: (267) 276-5451 | K42: hall.brieanna@yahoo.com | L42: CLINICONTACT | N42: wave 2 initial contact (sibling - 1880) | O42: 46207 | P42: AM | Q42: AM | R42: MV | S42: MV | T42: MV | U42: KL | V42: MS | W42: MV | X42: CP | Y42: MV | Z42: {=IFERROR(xlookup(C:C,'Follow up.1'!A:A,'Follow up.1'!AF:AF),"-")} -> 07/26 | AN42: {=IF(LEFT(B42,1)="3","x",IFNA(LET(raw,XLOOKUP(C42,'Follow up.2'!B:B,'Follow up.2'!AF:AF),IF(OR(raw="",raw=0),"-",TEXT(MIN(--raw,DATE(2027,6,1)),"mm/yyyy"))),"-"))} -> -
B43: {=ifna(iferror(xlookup(C:C,'1000'!A:A,'1000'!D:D),iferror(xlookup(C:C,'2000'!A:A,'2000'!D:D),xlookup(C:C,'3000'!A:A,'3000'!D:D))),"-")} -> 2122 | C43: 1764 | D43: Noemi | E43: Wanaselja | F43: Female (1) | G43: 16 | H43: Allison Van Wyk Wanaselja | I43: (215) 704-2253 | J43: (267) 568-9169 | L43: CLINICONTACT | N43: Wave2 Initial Contact | O43: 46208 | P43: KL | Q43: KL | R43: TP | S43: TP | T43: CP | U43: MV | V43: CP | W43: DZ | X43: CP | Y43: AD | Z43: {=IFERROR(xlookup(C:C,'Follow up.1'!A:A,'Follow up.1'!AF:AF),"-")} -> 07/26 | AN43: {=IF(LEFT(B43,1)="3","x",IFNA(LET(raw,XLOOKUP(C43,'Follow up.2'!B:B,'Follow up.2'!AF:AF),IF(OR(raw="",raw=0),"-",TEXT(MIN(--raw,DATE(2027,6,1)),"mm/yyyy"))),"-"))} -> -
B44: {=ifna(iferror(xlookup(C:C,'1000'!A:A,'1000'!D:D),iferror(xlookup(C:C,'2000'!A:A,'2000'!D:D),xlookup(C:C,'3000'!A:A,'3000'!D:D))),"-")} -> 1123 | C44: 1553 | D44: Samantha | E44: Aleman | F44: Female (1) | G44: 11 | H44: Herlinda Tlaxcaltecatl | I44: (267) 760-6682 | K44: They reached me via email | L44: They reached me via email | M44: ghosting sts - texted mom - never recieved them | N44: Wave 3 initial contact | O44: 46213 | P44: DZ | Q44: DZ | R44: DZ | S44: DZ | T44: AM | U44: AM | V44: AD | W44: MV | X44: MV | Y44: AD | Z44: {=IFERROR(xlookup(C:C,'Follow up.1'!A:A,'Follow up.1'!AF:AF),"-")} -> - | AA44: CP | AB44: CP | AC44: CP | AD44: CP | AF44: AC | AG44: AC | AI44: RY | AJ44: CP | AK44: BH | AL44: RY | AM44: AD | AN44: {=IF(LEFT(B44,1)="3","x",IFNA(LET(raw,XLOOKUP(C44,'Follow up.2'!B:B,'Follow up.2'!AF:AF),IF(OR(raw="",raw=0),"-",TEXT(MIN(--raw,DATE(2027,6,1)),"mm/yyyy"))),"-"))} -> 06/2027
B45: {=ifna(iferror(xlookup(C:C,'1000'!A:A,'1000'!D:D),iferror(xlookup(C:C,'2000'!A:A,'2000'!D:D),xlookup(C:C,'3000'!A:A,'3000'!D:D))),"-")} -> 1081 | C45: 1498 | D45: Kai | E45: Tran | F45: Male (2) | G45: 9 | H45: Delaina Tran | I45: (215) 237-8966 | K45: Email | L45: Email | M45: out of the country in June/July | N45: wave2 v2 reminder | O45: 46216 | P45: TP | Q45: MV | R45: TP | S45: TP | T45: DZ | U45: AD | V45: DZ | W45: MV | X45: MV | Y45: MV | Z45: {=IFERROR(xlookup(C:C,'Follow up.1'!A:A,'Follow up.1'!AF:AF),"-")} -> 02/26 | AA45: MV | AB45: EB | AC45: EB | AD45: EB | AF45: - | AG45: CP | AI45: CP | AN45: {=IF(LEFT(B45,1)="3","x",IFNA(LET(raw,XLOOKUP(C45,'Follow up.2'!B:B,'Follow up.2'!AF:AF),IF(OR(raw="",raw=0),"-",TEXT(MIN(--raw,DATE(2027,6,1)),"mm/yyyy"))),"-"))} -> -
B46: {=ifna(iferror(xlookup(C:C,'1000'!A:A,'1000'!D:D),iferror(xlookup(C:C,'2000'!A:A,'2000'!D:D),xlookup(C:C,'3000'!A:A,'3000'!D:D))),"-")} -> 1014 | C46: 132 | D46: Joshua | E46: Gerecht | F46: M | G46: 9 | H46: Miyuki Hashimoto | I46: 0 | J46: (215) 316-2915 | N46: Wave 3 iniitial contact | O46: 46226 | P46: DZ | Q46: BS | R46: BS | S46: BS | T46: BS | U46: BS | V46: MV | W46: DZ | X46: DZ | Y46: DZ | Z46: {=IFERROR(xlookup(C:C,'Follow up.1'!A:A,'Follow up.1'!AF:AF),"-")} -> 12/24 | AA46: AD | AB46: AD | AC46: AD | AD46: AD | AF46: MV | AG46: AD | AI46: KL | AJ46: CP | AK46: CP | AL46: CP | AM46: n/a | AN46: {=IF(LEFT(B46,1)="3","x",IFNA(LET(raw,XLOOKUP(C46,'Follow up.2'!B:B,'Follow up.2'!AF:AF),IF(OR(raw="",raw=0),"-",TEXT(MIN(--raw,DATE(2027,6,1)),"mm/yyyy"))),"-"))} -> 07/2026 | AO46: 46226
B47: {=ifna(iferror(xlookup(C:C,'1000'!A:A,'1000'!D:D),iferror(xlookup(C:C,'2000'!A:A,'2000'!D:D),xlookup(C:C,'3000'!A:A,'3000'!D:D))),"-")} -> 2114 | C47: 1782 | D47: Olivia | E47: Garrett | F47: Female (1) | G47: 16 | H47: Samantha | I47: 267-442-8673 | J47: (215) 778-2672 | L47: CLINICONTACT | N47: dont contact until avi clears-Wave 2 iniitial contact | O47: 46231 | P47: TP | Q47: KL | R47: KL | S47: TP | T47: KL | U47: AK | V47: TP | W47: CP | X47: Kl | Y47: MV | Z47: {=IFERROR(xlookup(C:C,'Follow up.1'!A:A,'Follow up.1'!AF:AF),"-")} -> 07/26 | AN47: {=IF(LEFT(B47,1)="3","x",IFNA(LET(raw,XLOOKUP(C47,'Follow up.2'!B:B,'Follow up.2'!AF:AF),IF(OR(raw="",raw=0),"-",TEXT(MIN(--raw,DATE(2027,6,1)),"mm/yyyy"))),"-"))} -> - | AO47: 46231
B48: {=ifna(iferror(xlookup(C:C,'1000'!A:A,'1000'!D:D),iferror(xlookup(C:C,'2000'!A:A,'2000'!D:D),xlookup(C:C,'3000'!A:A,'3000'!D:D))),"-")} -> 1131 | C48: 1926 | D48: Nylae | E48: Edwards-Williams | F48: Female (1) | G48: 12 | H48: Cherele Washington | I48: (267) 628-8662 | L48: redcap - sibling in study | N48: Wave 2 initial contact | O48: 46234 | P48: MV | Q48: MV | R48: AK | S48: AK | T48: CP | U48: CP | V48: AD | W48: AK | X48: AK | Y48: CP | Z48: {=IFERROR(xlookup(C:C,'Follow up.1'!A:A,'Follow up.1'!AF:AF),"-")} -> 07/26 | AN48: {=IF(LEFT(B48,1)="3","x",IFNA(LET(raw,XLOOKUP(C48,'Follow up.2'!B:B,'Follow up.2'!AF:AF),IF(OR(raw="",raw=0),"-",TEXT(MIN(--raw,DATE(2027,6,1)),"mm/yyyy"))),"-"))} -> -
B49: {=ifna(iferror(xlookup(C:C,'1000'!A:A,'1000'!D:D),iferror(xlookup(C:C,'2000'!A:A,'2000'!D:D),xlookup(C:C,'3000'!A:A,'3000'!D:D))),"-")} -> 2121 | C49: 1870 | D49: Eric | E49: Wu | F49: Male (2) | G49: 16 | H49: Eric Wu | I49: (267) 506-9460 | J49: 267 239 6088 | K49: gigarunner123@gmail.com | L49: CLINICONTACT | N49: dont contact until avi clears-Wave 2 initial contact | O49: 46234 | P49: CP | Q49: MV | R49: AD | S49: AD | T49: MV | U49: MV | V49: MV | W49: CP | X49: CP | Y49: CP | Z49: {=IFERROR(xlookup(C:C,'Follow up.1'!A:A,'Follow up.1'!AF:AF),"-")} -> 07/26 | AN49: {=IF(LEFT(B49,1)="3","x",IFNA(LET(raw,XLOOKUP(C49,'Follow up.2'!B:B,'Follow up.2'!AF:AF),IF(OR(raw="",raw=0),"-",TEXT(MIN(--raw,DATE(2027,6,1)),"mm/yyyy"))),"-"))} -> - | AO49: 46234
B50: {=ifna(iferror(xlookup(C:C,'1000'!A:A,'1000'!D:D),iferror(xlookup(C:C,'2000'!A:A,'2000'!D:D),xlookup(C:C,'3000'!A:A,'3000'!D:D))),"-")} -> 2128 | C50: 1908 | D50: Kaleah | E50: Y Calloway | F50: Female (1) | G50: 13 | H50: K.b | I50: 8479603911 | J50: 3523568378 | L50: CLINICONTACT | N50: w2 inital contact | O50: 46235 | P50: IA | Q50: DZ | R50: DZ | S50: DZ | T50: MV | U50: MV | V50: CP | W50: CP | X50: KL | Y50: MV | Z50: {=IFERROR(xlookup(C:C,'Follow up.1'!A:A,'Follow up.1'!AF:AF),"-")} -> 08/26 | AN50: {=IF(LEFT(B50,1)="3","x",IFNA(LET(raw,XLOOKUP(C50,'Follow up.2'!B:B,'Follow up.2'!AF:AF),IF(OR(raw="",raw=0),"-",TEXT(MIN(--raw,DATE(2027,6,1)),"mm/yyyy"))),"-"))} -> -
B51: {=ifna(iferror(xlookup(C:C,'1000'!A:A,'1000'!D:D),iferror(xlookup(C:C,'2000'!A:A,'2000'!D:D),xlookup(C:C,'3000'!A:A,'3000'!D:D))),"-")} -> 1008 | C51: 133 | D51: JJ (Jensen) | E51: Cressman | F51: M | N51: w3 initial contact | O51: 46235 | P51: DZ | Q51: BS | R51: BS | S51: BS | T51: BS | U51: BS | V51: MV | W51: BS | X51: BS | Y51: BS | Z51: {=IFERROR(xlookup(C:C,'Follow up.1'!A:A,'Follow up.1'!AF:AF),"-")} -> 10/24 | AA51: AM | AB51: KL | AC51: MV | AD51: AD | AF51: CP | AG51: KL | AI51: KL | AJ51: CP | AK51: CP | AL51: MV | AM51: n/a | AN51: {=IF(LEFT(B51,1)="3","x",IFNA(LET(raw,XLOOKUP(C51,'Follow up.2'!B:B,'Follow up.2'!AF:AF),IF(OR(raw="",raw=0),"-",TEXT(MIN(--raw,DATE(2027,6,1)),"mm/yyyy"))),"-"))} -> 08/2026
B52: {=ifna(iferror(xlookup(C:C,'1000'!A:A,'1000'!D:D),iferror(xlookup(C:C,'2000'!A:A,'2000'!D:D),xlookup(C:C,'3000'!A:A,'3000'!D:D))),"-")} -> 2120 | C52: 1853 | D52: Laila�Isabella | E52: Nelson | F52: Female (1) | G52: 13 | H52: Nasirrah Pratt | I52: (215) 445-9942 | J52: (215) 445-9942 | K52: naspratt0602@gmail.com | L52: CLINICONTACT | N52: Wave 2 intial contact | O52: 46237 | P52: AM | Q52: TP | R52: TP | S52: TP | T52: MS | U52: MV | V52: MV | W52: AMo | X52: AN | Y52: CP | Z52: {=IFERROR(xlookup(C:C,'Follow up.1'!A:A,'Follow up.1'!AF:AF),"-")} -> 08/26 | AN52: {=IF(LEFT(B52,1)="3","x",IFNA(LET(raw,XLOOKUP(C52,'Follow up.2'!B:B,'Follow up.2'!AF:AF),IF(OR(raw="",raw=0),"-",TEXT(MIN(--raw,DATE(2027,6,1)),"mm/yyyy"))),"-"))} -> - | AO52: 46237
B53: {=ifna(iferror(xlookup(C:C,'1000'!A:A,'1000'!D:D),iferror(xlookup(C:C,'2000'!A:A,'2000'!D:D),xlookup(C:C,'3000'!A:A,'3000'!D:D))),"-")} -> 2124 | C53: 1845 | D53: Alexandria | E53: Awong | F53: Female (1) | G53: 17 | H53: Michael Wong | I53: 267-872-9148 | J53: (610) 564-0597 | K53: againraptor@gmail.com | L53: CLINICONTACT | N53: Wave 2 initial contact | O53: 46248 | P53: TP | Q53: AK | R53: MV | S53: MV | T53: CP | U53: MV | V53: IA | W53: KL | X53: CP | Y53: CP | Z53: {=IFERROR(xlookup(C:C,'Follow up.1'!A:A,'Follow up.1'!AF:AF),"-")} -> 08/26 | AN53: {=IF(LEFT(B53,1)="3","x",IFNA(LET(raw,XLOOKUP(C53,'Follow up.2'!B:B,'Follow up.2'!AF:AF),IF(OR(raw="",raw=0),"-",TEXT(MIN(--raw,DATE(2027,6,1)),"mm/yyyy"))),"-"))} -> - | AO53: 46247
B54: {=ifna(iferror(xlookup(C:C,'1000'!A:A,'1000'!D:D),iferror(xlookup(C:C,'2000'!A:A,'2000'!D:D),xlookup(C:C,'3000'!A:A,'3000'!D:D))),"-")} -> 1085 | C54: 1489 | D54: Joshua | E54: Rubincan | F54: Male | G54: 9 | H54: Lauren Rubincan | I54: (302) 521-4438 | K54: Previous study | L54: Previous study | M54: 2085 sibling, expander pinged in the metal detector follow up in aug reach back out early fall | N54: reschedule wave2 v2 ( expander ) | O54: 46266 | P54: MV | Q54: AD | R54: AD | S54: AD | T54: MV | U54: DZ | V54: DZ | W54: MV | X54: MV | Y54: BH | Z54: {=IFERROR(xlookup(C:C,'Follow up.1'!A:A,'Follow up.1'!AF:AF),"-")} -> 1/26 | AA54: MG | AB54: BH | AC54: MV | AD54: MS | AF54: AD | AG54: MS | AI54: AD, EB | AJ54: AC | AL54: AC | AN54: {=IF(LEFT(B54,1)="3","x",IFNA(LET(raw,XLOOKUP(C54,'Follow up.2'!B:B,'Follow up.2'!AF:AF),IF(OR(raw="",raw=0),"-",TEXT(MIN(--raw,DATE(2027,6,1)),"mm/yyyy"))),"-"))} -> -
B55: {=ifna(iferror(xlookup(C:C,'1000'!A:A,'1000'!D:D),iferror(xlookup(C:C,'2000'!A:A,'2000'!D:D),xlookup(C:C,'3000'!A:A,'3000'!D:D))),"-")} -> 2123 | C55: 1780 | D55: Aryn | E55: Clark | F55: Female (1) | G55: 16 | H55: Nuh Tah Shuh Lloyd | I55: (267) 353-7829 | J55: (267) 466-7255 | L55: CLINICONTACT | N55: dont contact until avi clears- Wave 2 Initial Contact | O55: 46266 | P55: TP | Q55: MV | R55: MV | S55: MV | T55: CP | U55: MV | V55: KL, CP | W55: KL | X55: RY | Y55: IA | Z55: {=IFERROR(xlookup(C:C,'Follow up.1'!A:A,'Follow up.1'!AF:AF),"-")} -> 09/26 | AN55: {=IF(LEFT(B55,1)="3","x",IFNA(LET(raw,XLOOKUP(C55,'Follow up.2'!B:B,'Follow up.2'!AF:AF),IF(OR(raw="",raw=0),"-",TEXT(MIN(--raw,DATE(2027,6,1)),"mm/yyyy"))),"-"))} -> -
B56: {=ifna(iferror(xlookup(C:C,'1000'!A:A,'1000'!D:D),iferror(xlookup(C:C,'2000'!A:A,'2000'!D:D),xlookup(C:C,'3000'!A:A,'3000'!D:D))),"-")} -> 1015 | C56: 155 | D56: Jacob | E56: Gibbons | F56: M | G56: 9 | H56: Courtney Gibbons | I56: (215) 429-5541 | N56: wave 3 initial contact | O56: 46267 | P56: DZ | Q56: DZ | R56: DZ | S56: DZ | T56: DZ | U56: DZ | V56: DZ | W56: DZ | X56: DZ | Y56: DZ | Z56: {=IFERROR(xlookup(C:C,'Follow up.1'!A:A,'Follow up.1'!AF:AF),"-")} -> 11/24 | AA56: AD | AB56: AD | AC56: AD | AD56: AD | AF56: AD | AG56: KL | AI56: CP | AJ56: KL | AK56: KL | AL56: CP | AM56: n/a | AN56: {=IF(LEFT(B56,1)="3","x",IFNA(LET(raw,XLOOKUP(C56,'Follow up.2'!B:B,'Follow up.2'!AF:AF),IF(OR(raw="",raw=0),"-",TEXT(MIN(--raw,DATE(2027,6,1)),"mm/yyyy"))),"-"))} -> 09/2026 | AO56: 46267
B57: {=ifna(iferror(xlookup(C:C,'1000'!A:A,'1000'!D:D),iferror(xlookup(C:C,'2000'!A:A,'2000'!D:D),xlookup(C:C,'3000'!A:A,'3000'!D:D))),"-")} -> 2118 | C57: 1821 | D57: Jason | E57: Serrano | F57: Male (2) | G57: 14 | H57: Lisa Borrelli-Serrano | I57: (215) 768-1389 | J57: (215) 768-1389 | L57: CLINICONTACT | N57: Wave 2 initial contact | O57: 46282 | P57: MV | Q57: TP | R57: TP | S57: AD | T57: AD | U57: KL | V57: AD | W57: AN | X57: IA | Y57: CP | Z57: {=IFERROR(xlookup(C:C,'Follow up.1'!A:A,'Follow up.1'!AF:AF),"-")} -> 09/26 | AN57: {=IF(LEFT(B57,1)="3","x",IFNA(LET(raw,XLOOKUP(C57,'Follow up.2'!B:B,'Follow up.2'!AF:AF),IF(OR(raw="",raw=0),"-",TEXT(MIN(--raw,DATE(2027,6,1)),"mm/yyyy"))),"-"))} -> -
B58: {=ifna(iferror(xlookup(C:C,'1000'!A:A,'1000'!D:D),iferror(xlookup(C:C,'2000'!A:A,'2000'!D:D),xlookup(C:C,'3000'!A:A,'3000'!D:D))),"-")} -> 1016 | C58: 180 | D58: Connor | E58: Fitzpatrick | F58: M | G58: 10 | M58: Paid 70 at V1 wave 2 (7/13/2025) - had no cards | N58: Wave 3 Initial Contact | O58: 46296 | P58: MV | Q58: MV | R58: MV | S58: MV | T58: MV | U58: BS | V58: BS | W58: BS | X58: BS | Y58: BS | Z58: {=IFERROR(xlookup(C:C,'Follow up.1'!A:A,'Follow up.1'!AF:AF),"-")} -> 2/25 | AA58: IA | AB58: MV | AC58: MV | AD58: MV | AF58: AD | AG58: IA | AI58: MV | AJ58: AD | AK58: AN | AL58: IA | AM58: n/a | AN58: {=IF(LEFT(B58,1)="3","x",IFNA(LET(raw,XLOOKUP(C58,'Follow up.2'!B:B,'Follow up.2'!AF:AF),IF(OR(raw="",raw=0),"-",TEXT(MIN(--raw,DATE(2027,6,1)),"mm/yyyy"))),"-"))} -> 10/2026 | AO58: 46296
B59: {=ifna(iferror(xlookup(C:C,'1000'!A:A,'1000'!D:D),iferror(xlookup(C:C,'2000'!A:A,'2000'!D:D),xlookup(C:C,'3000'!A:A,'3000'!D:D))),"-")} -> 2012 | C59: 527 | D59: Rika | E59: Iijima | F59: F | G59: F16 | H59: Nobuko Iijima | I59: (267) 595-2755 | J59: (267) 992-0083 | K59: Friend | L59: Friend | N59: Wave 3 Initial Contact | O59: 46296 | P59: DZ | Q59: DZ | R59: DZ | S59: DZ | T59: DZ | U59: DZ | V59: DZ | W59: DZ | X59: DZ | Y59: DZ | Z59: {=IFERROR(xlookup(C:C,'Follow up.1'!A:A,'Follow up.1'!AF:AF),"-")} -> 5/25 | AA59: AN | AB59: IA, CP | AC59: MV | AD59: AD | AF59: IA | AG59: AN | AI59: AD | AJ59: AD | AK59: AN | AL59: IA | AM59: n/a | AN59: {=IF(LEFT(B59,1)="3","x",IFNA(LET(raw,XLOOKUP(C59,'Follow up.2'!B:B,'Follow up.2'!AF:AF),IF(OR(raw="",raw=0),"-",TEXT(MIN(--raw,DATE(2027,6,1)),"mm/yyyy"))),"-"))} -> 10/2026 | AO59: 46296
B60: {=ifna(iferror(xlookup(C:C,'1000'!A:A,'1000'!D:D),iferror(xlookup(C:C,'2000'!A:A,'2000'!D:D),xlookup(C:C,'3000'!A:A,'3000'!D:D))),"-")} -> 2009 | C60: 170 | D60: Jude | E60: Becker | H60: Justin Becker | I60: 0 | J60: (215) 888-6714 | M60: NEEDS 70 + 30 for V2 - did not get paid!!!! | N60: w3 initial contact | O60: 46311 | P60: DZ | Q60: DZ | R60: DZ | S60: DZ | T60: DZ | U60: DZ | V60: DZ | W60: DZ | X60: DZ | Y60: DZ | Z60: {=IFERROR(xlookup(C:C,'Follow up.1'!A:A,'Follow up.1'!AF:AF),"-")} -> 4/25 | AA60: MV | AB60: KL | AC60: KL | AD60: KL | AF60: CP | AG60: AN | AI60: MV | AJ60: IA | AK60: CP | AL60: IA | AM60: n/a | AN60: {=IF(LEFT(B60,1)="3","x",IFNA(LET(raw,XLOOKUP(C60,'Follow up.2'!B:B,'Follow up.2'!AF:AF),IF(OR(raw="",raw=0),"-",TEXT(MIN(--raw,DATE(2027,6,1)),"mm/yyyy"))),"-"))} -> 10/2026
B61: {=ifna(iferror(xlookup(C:C,'1000'!A:A,'1000'!D:D),iferror(xlookup(C:C,'2000'!A:A,'2000'!D:D),xlookup(C:C,'3000'!A:A,'3000'!D:D))),"-")} -> 1019 | C61: 393 | D61: Hai-Dinh | E61: Ballock | N61: Wave 3 initial contact | O61: 46312 | P61: AD | Q61: AD | R61: AD | S61: AD | T61: AD | U61: AD | V61: AD | W61: AD | X61: AD | Y61: AD | Z61: {=IFERROR(xlookup(C:C,'Follow up.1'!A:A,'Follow up.1'!AF:AF),"-")} -> 3/25 | AA61: AM | AB61: CP | AC61: DZ | AD61: DZ, CP | AF61: AD | AG61: AC | AI61: CP | AJ61: AN | AK61: CP | AL61: CP | AM61: n/a | AN61: {=IF(LEFT(B61,1)="3","x",IFNA(LET(raw,XLOOKUP(C61,'Follow up.2'!B:B,'Follow up.2'!AF:AF),IF(OR(raw="",raw=0),"-",TEXT(MIN(--raw,DATE(2027,6,1)),"mm/yyyy"))),"-"))} -> 10/2026 | AO61: 46312
B62: {=ifna(iferror(xlookup(C:C,'1000'!A:A,'1000'!D:D),iferror(xlookup(C:C,'2000'!A:A,'2000'!D:D),xlookup(C:C,'3000'!A:A,'3000'!D:D))),"-")} -> 1032 | C62: 774 | D62: Khyjair | E62: Tripline Reed | F62: M | G62: M12 | H62: Kamilah Reed | I62: 0 | J62: (267) 928-0049 | K62: CLINICONTACT | L62: CLINICONTACT | N62: dont contact until avi clears- Wave 3 initial contact | O62: 46315 | P62: MV | Q62: MV | R62: MV | S62: MV | T62: MV | U62: MV | V62: DZ | W62: MV | X62: MV | Y62: MV | Z62: {=IFERROR(xlookup(C:C,'Follow up.1'!A:A,'Follow up.1'!AF:AF),"-")} -> 7/25 | AA62: CP | AB62: CP | AC62: CP | AD62: CP | AF62: CP | AG62: CP | AI62: MV | AJ62: MV | AK62: MV | AL62: CP | AM62: n/a | AN62: {=IF(LEFT(B62,1)="3","x",IFNA(LET(raw,XLOOKUP(C62,'Follow up.2'!B:B,'Follow up.2'!AF:AF),IF(OR(raw="",raw=0),"-",TEXT(MIN(--raw,DATE(2027,6,1)),"mm/yyyy"))),"-"))} -> 10/2026 | AO62: 46315
B63: {=ifna(iferror(xlookup(C:C,'1000'!A:A,'1000'!D:D),iferror(xlookup(C:C,'2000'!A:A,'2000'!D:D),xlookup(C:C,'3000'!A:A,'3000'!D:D))),"-")} -> 2020 | C63: 738 | D63: Myesha | E63: Gardner | F63: F | G63: F16 | H63: Dakettia Cook | I63: (267) 402-8110 | J63: 8562713698 | K63: CLINICONTACT | L63: CLINICONTACT | N63: Wave 3 initial contact | O63: 46317 | P63: MV | Q63: MV | R63: MV | S63: MV | T63: MV | U63: MV | V63: DZ | W63: MV | X63: MV | Y63: MV | Z63: {=IFERROR(xlookup(C:C,'Follow up.1'!A:A,'Follow up.1'!AF:AF),"-")} -> 7/25 | AA63: CP | AB63: CP | AC63: CP | AD63: CP | AF63: CP | AG63: CP | AI63: CP | AJ63: MV | AK63: KL | AL63: KL | AM63: n/a | AN63: {=IF(LEFT(B63,1)="3","x",IFNA(LET(raw,XLOOKUP(C63,'Follow up.2'!B:B,'Follow up.2'!AF:AF),IF(OR(raw="",raw=0),"-",TEXT(MIN(--raw,DATE(2027,6,1)),"mm/yyyy"))),"-"))} -> 10/2026 | AO63: 46317
B64: {=ifna(iferror(xlookup(C:C,'1000'!A:A,'1000'!D:D),iferror(xlookup(C:C,'2000'!A:A,'2000'!D:D),xlookup(C:C,'3000'!A:A,'3000'!D:D))),"-")} -> 2046 | C64: 1078 | D64: Dominic | E64: Fuhs | F64: M | G64: M13 | H64: Anita Fuhs | I64: 215-820-5802 | J64: (215) 820-5802 | K64: CLINICONTACT | L64: CLINICONTACT | N64: Wave 3 initital contact | O64: 46318 | P64: BS | Q64: AD | R64: AD | S64: AD | T64: AM | U64: DZ | V64: DZ | W64: DZ | X64: DZ | Y64: DZ | Z64: {=IFERROR(xlookup(C:C,'Follow up.1'!A:A,'Follow up.1'!AF:AF),"-")} -> 10/25 | AA64: AM | AB64: AD | AC64: AD | AD64: AD | AF64: IA | AG64: CP | AI64: AK | AJ64: MV | AK64: IA | AL64: CP | AM64: n/a | AN64: {=IF(LEFT(B64,1)="3","x",IFNA(LET(raw,XLOOKUP(C64,'Follow up.2'!B:B,'Follow up.2'!AF:AF),IF(OR(raw="",raw=0),"-",TEXT(MIN(--raw,DATE(2027,6,1)),"mm/yyyy"))),"-"))} -> 10/2026 | AO64: 46318
B65: {=ifna(iferror(xlookup(C:C,'1000'!A:A,'1000'!D:D),iferror(xlookup(C:C,'2000'!A:A,'2000'!D:D),xlookup(C:C,'3000'!A:A,'3000'!D:D))),"-")} -> 2016 | C65: 679 | D65: Chelsea | E65: Painter | F65: F | G65: F15 | H65: Arthur Painter | I65: (215) 350-2809 | J65: (215) 470-1212 | K65: Referred to by a family member | L65: Referred to by a family member | N65: Wave 3 iniitial contact | O65: 46320 | P65: MV | Q65: MV | R65: MV | S65: MV | T65: MV | U65: MV | V65: DZ | W65: MV | X65: MV | Y65: MV | Z65: {=IFERROR(xlookup(C:C,'Follow up.1'!A:A,'Follow up.1'!AF:AF),"-")} -> 6/25 | AA65: CP | AB65: KL | AC65: KL | AD65: KL | AF65: CP | AG65: IA | AI65: IA | AJ65: IA | AK65: CP | AL65: CP | AM65: n/a | AN65: {=IF(LEFT(B65,1)="3","x",IFNA(LET(raw,XLOOKUP(C65,'Follow up.2'!B:B,'Follow up.2'!AF:AF),IF(OR(raw="",raw=0),"-",TEXT(MIN(--raw,DATE(2027,6,1)),"mm/yyyy"))),"-"))} -> 10/2026 | AO65: 46320
B66: {=ifna(iferror(xlookup(C:C,'1000'!A:A,'1000'!D:D),iferror(xlookup(C:C,'2000'!A:A,'2000'!D:D),xlookup(C:C,'3000'!A:A,'3000'!D:D))),"-")} -> 2013 | C66: 529 | D66: Tina | E66: Zheng | F66: F | G66: F15 | H66: Xiu Yun Qiu | I66: 267-331-1656 | J66: (215) 500-4868 | K66: Friend | L66: Friend | M66: only child texts | N66: Wave 3 initial contact | O66: 46320 | P66: DZ | Q66: DZ | R66: DZ | S66: DZ | T66: DZ | U66: DZ | V66: DZ | W66: DZ | X66: DZ | Y66: DZ | Z66: {=IFERROR(xlookup(C:C,'Follow up.1'!A:A,'Follow up.1'!AF:AF),"-")} -> 5/25 | AA66: CP | AB66: KL | AC66: KL | AD66: KL | AF66: AD | AG66: AN | AI66: CP | AJ66: MV | AK66: CP | AL66: CP | AM66: n/a | AN66: {=IF(LEFT(B66,1)="3","x",IFNA(LET(raw,XLOOKUP(C66,'Follow up.2'!B:B,'Follow up.2'!AF:AF),IF(OR(raw="",raw=0),"-",TEXT(MIN(--raw,DATE(2027,6,1)),"mm/yyyy"))),"-"))} -> 10/2026 | AO66: 46320
B67: {=ifna(iferror(xlookup(C:C,'1000'!A:A,'1000'!D:D),iferror(xlookup(C:C,'2000'!A:A,'2000'!D:D),xlookup(C:C,'3000'!A:A,'3000'!D:D))),"-")} -> 1036 | C67: 773 | D67: Suhaylah | E67: Andino | F67: F | G67: F8 | H67: Sharde Walker | I67: 0 | J67: (215) 954-3526 | K67: CLINICONTACT | L67: CLINICONTACT | N67: Wave 3 initial contact | O67: 46320 | P67: MV | Q67: MV | R67: MV | S67: MV | T67: MV | U67: MV | V67: DZ | W67: MV | X67: MV | Y67: MV | Z67: {=IFERROR(xlookup(C:C,'Follow up.1'!A:A,'Follow up.1'!AF:AF),"-")} -> 7/25 | AA67: CP | AB67: KL | AC67: KL | AD67: KL | AF67: AN | AG67: CP | AI67: CP | AJ67: KL | AK67: IA | AL67: CP | AM67: n/a | AN67: {=IF(LEFT(B67,1)="3","x",IFNA(LET(raw,XLOOKUP(C67,'Follow up.2'!B:B,'Follow up.2'!AF:AF),IF(OR(raw="",raw=0),"-",TEXT(MIN(--raw,DATE(2027,6,1)),"mm/yyyy"))),"-"))} -> 10/2026 | AO67: 46320
B68: {=ifna(iferror(xlookup(C:C,'1000'!A:A,'1000'!D:D),iferror(xlookup(C:C,'2000'!A:A,'2000'!D:D),xlookup(C:C,'3000'!A:A,'3000'!D:D))),"-")} -> 2011 | C68: 520 | D68: Nayeli | E68: Padilla | F68: F | G68: F15 | H68: Monica Hankins | I68: (267) 269-2081 | J68: (215) 669-4765 | K68: gaurdian sent it to me' | L68: gaurdian sent it to me' | M68: Messages are going undelivered - AD 6/27/2025 | N68: Wave 3 initial contact | O68: 46324 | P68: DZ | Q68: DZ | R68: DZ | S68: DZ | T68: DZ | U68: DZ | V68: DZ | W68: DZ | X68: DZ | Y68: DZ | Z68: {=IFERROR(xlookup(C:C,'Follow up.1'!A:A,'Follow up.1'!AF:AF),"-")} -> 5/25 | AA68: MV | AB68: CP | AC68: BH | AD68: KL | AF68: BH | AG68: kl | AI68: KL | AJ68: CP | AK68: KL | AL68: CP | AM68: n/a | AN68: {=IF(LEFT(B68,1)="3","x",IFNA(LET(raw,XLOOKUP(C68,'Follow up.2'!B:B,'Follow up.2'!AF:AF),IF(OR(raw="",raw=0),"-",TEXT(MIN(--raw,DATE(2027,6,1)),"mm/yyyy"))),"-"))} -> 10/2026 | AO68: 46324
B69: {=ifna(iferror(xlookup(C:C,'1000'!A:A,'1000'!D:D),iferror(xlookup(C:C,'2000'!A:A,'2000'!D:D),xlookup(C:C,'3000'!A:A,'3000'!D:D))),"-")} -> 2131 | C69: 737 | D69: Quadir | E69: Gardner | F69: M | G69: M17 | H69: Dakettia Cook | I69: (267) 606-7628 | J69: (267) 606-7628 | K69: CLINICONTACT | L69: CLINICONTACT | N69: Wave 3 initial contact | O69: 46331 | P69: MV | Q69: MV | R69: MV | S69: MV | T69: MV | U69: MV | V69: DZ | W69: MV | X69: MV | Y69: MV | Z69: {=IFERROR(xlookup(C:C,'Follow up.1'!A:A,'Follow up.1'!AF:AF),"-")} -> 7/25 | AA69: CP | AB69: CP | AC69: CP | AD69: CP | AF69: CP | AG69: CP | AI69: CP | AJ69: AN | AK69: CP | AL69: CP | AM69: n/a | AN69: {=IF(LEFT(B69,1)="3","x",IFNA(LET(raw,XLOOKUP(C69,'Follow up.2'!B:B,'Follow up.2'!AF:AF),IF(OR(raw="",raw=0),"-",TEXT(MIN(--raw,DATE(2027,6,1)),"mm/yyyy"))),"-"))} -> 11/2026 | AO69: 46331
B70: {=ifna(iferror(xlookup(C:C,'1000'!A:A,'1000'!D:D),iferror(xlookup(C:C,'2000'!A:A,'2000'!D:D),xlookup(C:C,'3000'!A:A,'3000'!D:D))),"-")} -> 1035 | C70: 772 | D70: Kennedy | E70: Player | F70: F | G70: F12 | H70: Johnetta Gay | I70: 0 | J70: (267) 624-5836 | K70: CLINICONTACT | L70: CLINICONTACT | N70: wave 3 initial contact | O70: 46333 | P70: MV | Q70: MV | R70: MV | S70: MV | T70: MV | U70: MV | V70: DZ | W70: MV | X70: MV | Y70: MV | Z70: {=IFERROR(xlookup(C:C,'Follow up.1'!A:A,'Follow up.1'!AF:AF),"-")} -> 7/25 | AA70: CP | AB70: KL | AC70: AC | AD70: AC | AF70: CP | AG70: CP | AI70: CP | AJ70: CP | AK70: CP | AL70: CP | AM70: n/a | AN70: {=IF(LEFT(B70,1)="3","x",IFNA(LET(raw,XLOOKUP(C70,'Follow up.2'!B:B,'Follow up.2'!AF:AF),IF(OR(raw="",raw=0),"-",TEXT(MIN(--raw,DATE(2027,6,1)),"mm/yyyy"))),"-"))} -> 11/2026 | AO70: 46333
B71: {=ifna(iferror(xlookup(C:C,'1000'!A:A,'1000'!D:D),iferror(xlookup(C:C,'2000'!A:A,'2000'!D:D),xlookup(C:C,'3000'!A:A,'3000'!D:D))),"-")} -> 2018 | C71: 701 | D71: Karma | E71: Davis | F71: F | G71: F13 | H71: Kendria Davis | I71: (267) 290-0188 | J71: (267) 582-2499 | K71: Philly Free School | L71: Philly Free School | N71: Wave 3 initial contact | O71: 46333 | P71: MV | Q71: MV | R71: MV | S71: MV | T71: MV | U71: MV | V71: DZ | W71: MV | X71: MV | Y71: MV | Z71: {=IFERROR(xlookup(C:C,'Follow up.1'!A:A,'Follow up.1'!AF:AF),"-")} -> 6/25 | AA71: CP | AB71: AD | AC71: AD | AD71: AD | AF71: CP | AG71: CP | AI71: CP | AJ71: Bh | AK71: KL, CP | AL71: CP | AM71: n/a | AN71: {=IF(LEFT(B71,1)="3","x",IFNA(LET(raw,XLOOKUP(C71,'Follow up.2'!B:B,'Follow up.2'!AF:AF),IF(OR(raw="",raw=0),"-",TEXT(MIN(--raw,DATE(2027,6,1)),"mm/yyyy"))),"-"))} -> 11/2026 | AO71: 46333
B72: {=ifna(iferror(xlookup(C:C,'1000'!A:A,'1000'!D:D),iferror(xlookup(C:C,'2000'!A:A,'2000'!D:D),xlookup(C:C,'3000'!A:A,'3000'!D:D))),"-")} -> 2024 | C72: 779 | D72: Emira | E72: Cheeks | F72: F | G72: F14 | H72: Laylah Wilson | I72: (835) 226-7473 | J72: (302) 685-7891 | K72: CLINICONTACT | L72: CLINICONTACT | N72: dont contact until avi clears/ if they have braces still cut them - Wave 3 initial contact | O72: 46336 | P72: MV | Q72: MV | R72: MV | S72: MV | T72: MV | U72: MV | V72: DZ | W72: MV | X72: MV | Y72: MV | Z72: {=IFERROR(xlookup(C:C,'Follow up.1'!A:A,'Follow up.1'!AF:AF),"-")} -> 7/25 | AA72: MV | AB72: KL | AC72: KL | AD72: KL | AF72: IA | AG72: IA | AI72: IA | AJ72: IA | AK72: CP | AL72: CP | AM72: n/a | AN72: {=IF(LEFT(B72,1)="3","x",IFNA(LET(raw,XLOOKUP(C72,'Follow up.2'!B:B,'Follow up.2'!AF:AF),IF(OR(raw="",raw=0),"-",TEXT(MIN(--raw,DATE(2027,6,1)),"mm/yyyy"))),"-"))} -> 11/2026 | AO72: 46336
B73: {=ifna(iferror(xlookup(C:C,'1000'!A:A,'1000'!D:D),iferror(xlookup(C:C,'2000'!A:A,'2000'!D:D),xlookup(C:C,'3000'!A:A,'3000'!D:D))),"-")} -> 2022 | C73: 658 | D73: Thomas | E73: Hylan | F73: M | G73: M15 | H73: Mia Hylan | I73: (215) 617-7111 | J73: (215) 888-1243 | K73: PennHD | L73: PennHD | N73: Wave 3 initital contact | O73: 46345 | P73: MV | Q73: MV | R73: MV | S73: MV | T73: MV | U73: MV | V73: DZ | W73: MV | X73: MV | Y73: MV | Z73: {=IFERROR(xlookup(C:C,'Follow up.1'!A:A,'Follow up.1'!AF:AF),"-")} -> 7/25 | AA73: CP | AB73: KL | AC73: KL | AD73: KL, CP | AF73: IA | AG73: AN | AI73: - | AJ73: CP | AK73: - | AL73: CP | AM73: n/a | AN73: {=IF(LEFT(B73,1)="3","x",IFNA(LET(raw,XLOOKUP(C73,'Follow up.2'!B:B,'Follow up.2'!AF:AF),IF(OR(raw="",raw=0),"-",TEXT(MIN(--raw,DATE(2027,6,1)),"mm/yyyy"))),"-"))} -> - | AO73: 46345
B74: {=ifna(iferror(xlookup(C:C,'1000'!A:A,'1000'!D:D),iferror(xlookup(C:C,'2000'!A:A,'2000'!D:D),xlookup(C:C,'3000'!A:A,'3000'!D:D))),"-")} -> 2029 | C74: 819 | D74: Ishmael | E74: Savadogo | F74: M | G74: M17 | H74: Nzinga Jackson | I74: (267) 210-1987 | J74: (267) 210-1987 | K74: Drexel Dornsife Center | L74: Drexel Dornsife Center | N74: Wave 3 initial contact | O74: 46348 | P74: MV | Q74: MV | R74: MV | S74: MV | T74: MV | U74: MV | V74: DZ | W74: MV | X74: MV | Y74: MV | Z74: {=IFERROR(xlookup(C:C,'Follow up.1'!A:A,'Follow up.1'!AF:AF),"-")} -> 7/25 | AA74: MV | AB74: IA | AC74: AD | AD74: MV | AF74: MV | AG74: CP | AI74: CP, CP | AJ74: - | AK74: IA | AL74: CP | AM74: n/a | AN74: {=IF(LEFT(B74,1)="3","x",IFNA(LET(raw,XLOOKUP(C74,'Follow up.2'!B:B,'Follow up.2'!AF:AF),IF(OR(raw="",raw=0),"-",TEXT(MIN(--raw,DATE(2027,6,1)),"mm/yyyy"))),"-"))} -> 11/2026 | AO74: 46348
B75: {=ifna(iferror(xlookup(C:C,'1000'!A:A,'1000'!D:D),iferror(xlookup(C:C,'2000'!A:A,'2000'!D:D),xlookup(C:C,'3000'!A:A,'3000'!D:D))),"-")} -> 1038 | C75: 887 | D75: Sydney | E75: Hollaway | F75: F | G75: F12 | H75: Brandi Hollaway | I75: (215) 954-5340 | J75: ??? | K75: CLINICONTACT | L75: CLINICONTACT | N75: w3 initital contact | O75: 46356 | P75: DZ | Q75: DZ | R75: DZ | S75: DZ | T75: DZ | U75: DZ | V75: DZ | W75: DZ | X75: DZ | Y75: DZ | Z75: {=IFERROR(xlookup(C:C,'Follow up.1'!A:A,'Follow up.1'!AF:AF),"-")} -> 8/25 | AA75: RY | AB75: CP | AC75: BH | AD75: BH | AF75: MV | AG75: CP | AI75: AD | AJ75: KL | AK75: MV | AL75: CP | AM75: n/a | AN75: {=IF(LEFT(B75,1)="3","x",IFNA(LET(raw,XLOOKUP(C75,'Follow up.2'!B:B,'Follow up.2'!AF:AF),IF(OR(raw="",raw=0),"-",TEXT(MIN(--raw,DATE(2027,6,1)),"mm/yyyy"))),"-"))} -> 11/2026
B76: {=ifna(iferror(xlookup(C:C,'1000'!A:A,'1000'!D:D),iferror(xlookup(C:C,'2000'!A:A,'2000'!D:D),xlookup(C:C,'3000'!A:A,'3000'!D:D))),"-")} -> 2032 | C76: 884 | D76: Micah | E76: Hollaway | F76: F | G76: F14 | H76: Brandi Hollaway | I76: (445) 226-3286 | J76: (215) 954-5340 | K76: CLINICONTACT | L76: CLINICONTACT | N76: w3 intital contact | O76: 46356 | P76: DZ | Q76: DZ | R76: DZ | S76: DZ | T76: DZ | U76: DZ | V76: DZ | W76: DZ | X76: DZ | Y76: DZ | Z76: {=IFERROR(xlookup(C:C,'Follow up.1'!A:A,'Follow up.1'!AF:AF),"-")} -> 8/25 | AA76: RY | AB76: CP | AC76: BH | AD76: BH | AF76: MV | AG76: CP | AI76: KL | AJ76: AD | AK76: MV | AL76: CP | AM76: n/a | AN76: {=IF(LEFT(B76,1)="3","x",IFNA(LET(raw,XLOOKUP(C76,'Follow up.2'!B:B,'Follow up.2'!AF:AF),IF(OR(raw="",raw=0),"-",TEXT(MIN(--raw,DATE(2027,6,1)),"mm/yyyy"))),"-"))} -> 11/2026
B77: {=ifna(iferror(xlookup(C:C,'1000'!A:A,'1000'!D:D),iferror(xlookup(C:C,'2000'!A:A,'2000'!D:D),xlookup(C:C,'3000'!A:A,'3000'!D:D))),"-")} -> 1037 | C77: 851 | D77: Kiley | E77: Strauss | F77: F | G77: F12 | H77: Melissa A Strauss | I77: (267) 213-6658 | J77: ??? | K77: CLINICONTACT | L77: CLINICONTACT | N77: Wave 3 Initial Contact | O77: 46357 | P77: DZ | Q77: DZ | R77: DZ | S77: DZ | T77: DZ | U77: DZ | V77: DZ | W77: DZ | X77: DZ | Y77: DZ | Z77: {=IFERROR(xlookup(C:C,'Follow up.1'!A:A,'Follow up.1'!AF:AF),"-")} -> 8/25 | AA77: RY | AB77: CP | AC77: AD | AD77: AD | AF77: CP | AG77: AK | AI77: AK | AJ77: AN | AK77: AK | AL77: AK | AM77: n/a | AN77: {=IF(LEFT(B77,1)="3","x",IFNA(LET(raw,XLOOKUP(C77,'Follow up.2'!B:B,'Follow up.2'!AF:AF),IF(OR(raw="",raw=0),"-",TEXT(MIN(--raw,DATE(2027,6,1)),"mm/yyyy"))),"-"))} -> 12/2026 | AO77: 46357
B78: {=ifna(iferror(xlookup(C:C,'1000'!A:A,'1000'!D:D),iferror(xlookup(C:C,'2000'!A:A,'2000'!D:D),xlookup(C:C,'3000'!A:A,'3000'!D:D))),"-")} -> 1039 | C78: 888 | D78: Kendall | E78: Hollaway | F78: F | G78: F12 | H78: Brandi Hollaway | I78: (215) 954-5340 | J78: ??? | K78: CLINICONTACT | L78: CLINICONTACT | N78: Wave 3 initial contact | O78: 46357 | P78: DZ | Q78: DZ | R78: DZ | S78: DZ | T78: DZ | U78: DZ | V78: DZ | W78: DZ | X78: DZ | Y78: DZ | Z78: {=IFERROR(xlookup(C:C,'Follow up.1'!A:A,'Follow up.1'!AF:AF),"-")} -> 8/25 | AA78: RY | AB78: CP | AC78: BH | AD78: BH | AF78: - | AG78: CP | AI78: KL | AJ78: CP | AK78: KL | AL78: CP | AM78: n/a | AN78: {=IF(LEFT(B78,1)="3","x",IFNA(LET(raw,XLOOKUP(C78,'Follow up.2'!B:B,'Follow up.2'!AF:AF),IF(OR(raw="",raw=0),"-",TEXT(MIN(--raw,DATE(2027,6,1)),"mm/yyyy"))),"-"))} -> 12/2026 | AO78: 46357
B79: {=ifna(iferror(xlookup(C:C,'1000'!A:A,'1000'!D:D),iferror(xlookup(C:C,'2000'!A:A,'2000'!D:D),xlookup(C:C,'3000'!A:A,'3000'!D:D))),"-")} -> 2026 | C79: 807 | D79: Sayir | E79: Taylor | F79: M | G79: M15 | H79: Crystal Brown | I79: (267) 679-9194 | J79: (267) 610-9388 | K79: CLINICONTACT | L79: CLINICONTACT | N79: dont contact until avi clears them-Wave 3 initial contact | O79: 46357 | P79: MV | Q79: MV | R79: MV | S79: MV | T79: MV | U79: MV | V79: DZ | W79: MV | X79: MV | Y79: MV | Z79: {=IFERROR(xlookup(C:C,'Follow up.1'!A:A,'Follow up.1'!AF:AF),"-")} -> 7/25 | AA79: MV | AB79: KL | AC79: KL | AD79: KL | AF79: CP | AG79: CP | AI79: CP | AJ79: - | AK79: CP | AL79: KL | AM79: n/a | AN79: {=IF(LEFT(B79,1)="3","x",IFNA(LET(raw,XLOOKUP(C79,'Follow up.2'!B:B,'Follow up.2'!AF:AF),IF(OR(raw="",raw=0),"-",TEXT(MIN(--raw,DATE(2027,6,1)),"mm/yyyy"))),"-"))} -> 12/2026 | AO79: 46357
B80: {=ifna(iferror(xlookup(C:C,'1000'!A:A,'1000'!D:D),iferror(xlookup(C:C,'2000'!A:A,'2000'!D:D),xlookup(C:C,'3000'!A:A,'3000'!D:D))),"-")} -> 2033 | C80: 867 | D80: Wren | E80: RuiFang Palombaro Lanza | F80: F | G80: F17 | H80: Kerstin Palombaro | I80: (215) 813-3008 | J80: (215) 817-6430 | K80: CLINICONTACT | L80: CLINICONTACT | N80: Wave 3 initial contact | O80: 46379 | P80: DZ | Q80: DZ | R80: DZ | S80: DZ | T80: DZ | U80: DZ | V80: DZ | W80: DZ | X80: DZ | Y80: DZ | Z80: {=IFERROR(xlookup(C:C,'Follow up.1'!A:A,'Follow up.1'!AF:AF),"-")} -> 8/25 | AA80: RY | AB80: n/a | AC80: n/a | AD80: AD | AF80: CP | AG80: - | AI80: - | AJ80: AMo | AK80: AK | AL80: CP | AM80: n/a | AN80: {=IF(LEFT(B80,1)="3","x",IFNA(LET(raw,XLOOKUP(C80,'Follow up.2'!B:B,'Follow up.2'!AF:AF),IF(OR(raw="",raw=0),"-",TEXT(MIN(--raw,DATE(2027,6,1)),"mm/yyyy"))),"-"))} -> 12/2026 | AO80: 46379
B81: {=ifna(iferror(xlookup(C:C,'1000'!A:A,'1000'!D:D),iferror(xlookup(C:C,'2000'!A:A,'2000'!D:D),xlookup(C:C,'3000'!A:A,'3000'!D:D))),"-")} -> 1024 | C81: 509 | D81: Noemi | E81: Ortiz-Rivera | F81: F | G81: F11 | H81: Samiha Ortiz-Rivera | I81: (267) 997-4412 | J81: (267) 997-4412 | K81: Temple | L81: Temple | N81: Wave 3 Initial Contact | O81: 46392 | P81: DZ | Q81: DZ | R81: DZ | S81: DZ | T81: DZ | U81: DZ | V81: DZ | W81: DZ | X81: DZ | Y81: DZ | Z81: {=IFERROR(xlookup(C:C,'Follow up.1'!A:A,'Follow up.1'!AF:AF),"-")} -> 5/25 | AA81: DZ | AB81: DZ | AC81: DZ | AD81: AM | AF81: CP | AG81: MV | AI81: CP | AJ81: AK | AK81: AN | AL81: AK | AM81: n/a | AN81: {=IF(LEFT(B81,1)="3","x",IFNA(LET(raw,XLOOKUP(C81,'Follow up.2'!B:B,'Follow up.2'!AF:AF),IF(OR(raw="",raw=0),"-",TEXT(MIN(--raw,DATE(2027,6,1)),"mm/yyyy"))),"-"))} -> 01/2027 | AO81: 46392
B82: {=ifna(iferror(xlookup(C:C,'1000'!A:A,'1000'!D:D),iferror(xlookup(C:C,'2000'!A:A,'2000'!D:D),xlookup(C:C,'3000'!A:A,'3000'!D:D))),"-")} -> 1023 | C82: 508 | D82: Anthony | E82: Ortiz-Rivera Jr | F82: M | G82: M11 | H82: Samiha Ortiz-Rivera | I82: (267) 997-4412 | J82: (267) 997-4412 | K82: Temple | L82: Temple | N82: Wave 3 initial contact | O82: 46398 | P82: DZ | Q82: DZ | R82: DZ | S82: DZ | T82: DZ | U82: DZ | V82: DZ | W82: DZ | X82: DZ | Y82: DZ | Z82: {=IFERROR(xlookup(C:C,'Follow up.1'!A:A,'Follow up.1'!AF:AF),"-")} -> 5/25 | AA82: DZ | AB82: DZ | AC82: DZ | AD82: AMo | AF82: CP | AG82: MV | AI82: AK | AJ82: AK | AN82: {=IF(LEFT(B82,1)="3","x",IFNA(LET(raw,XLOOKUP(C82,'Follow up.2'!B:B,'Follow up.2'!AF:AF),IF(OR(raw="",raw=0),"-",TEXT(MIN(--raw,DATE(2027,6,1)),"mm/yyyy"))),"-"))} -> 01/2027 | AO82: 46398
B83: {=ifna(iferror(xlookup(C:C,'1000'!A:A,'1000'!D:D),iferror(xlookup(C:C,'2000'!A:A,'2000'!D:D),xlookup(C:C,'3000'!A:A,'3000'!D:D))),"-")} -> 2039 | C83: 963 | D83: Enrique | E83: Hernandez | F83: M | G83: M14 | H83: Robin Hernandez-Mekonnen | I83: (267) 283-8787 | J83: (267) 987-4689 | K83: CLINICONTACT | L83: CLINICONTACT | M83: use parent & child gc | N83: wave 3 initial contact | O83: 46419 | P83: MV | Q83: MV | R83: MV | S83: MV | T83: MV | U83: MV | V83: DZ | W83: MV | X83: MV | Y83: MV | Z83: {=IFERROR(xlookup(C:C,'Follow up.1'!A:A,'Follow up.1'!AF:AF),"-")} -> 9/25 | AA83: AC | AB83: KL | AC83: KL | AD83: BH | AF83: AD | AG83: RY | AI83: AK | AJ83: AD | AK83: AD | AL83: AN | AM83: n/a | AN83: {=IF(LEFT(B83,1)="3","x",IFNA(LET(raw,XLOOKUP(C83,'Follow up.2'!B:B,'Follow up.2'!AF:AF),IF(OR(raw="",raw=0),"-",TEXT(MIN(--raw,DATE(2027,6,1)),"mm/yyyy"))),"-"))} -> 03/2027 | AO83: 46419
B84: {=ifna(iferror(xlookup(C:C,'1000'!A:A,'1000'!D:D),iferror(xlookup(C:C,'2000'!A:A,'2000'!D:D),xlookup(C:C,'3000'!A:A,'3000'!D:D))),"-")} -> 1057 | C84: 1147 | D84: Aashir | E84: Nelson | F84: M | G84: 10 | H84: Lakia Taylor | I84: (484) 566-0529 | K84: sibling of Jaziah Taylor | L84: cousin of Jaziah & christian Taylor | N84: wave 3 initial contact | O84: 46420 | P84: DZ | Q84: DZ | R84: AM | S84: AM | T84: AD | U84: DZ | V84: DZ | W84: DZ | X84: DZ | Y84: DZ | Z84: {=IFERROR(xlookup(C:C,'Follow up.1'!A:A,'Follow up.1'!AF:AF),"-")} -> 10/25 | AA84: AK | AB84: CP | AC84: CP | AD84: CP | AF84: AK | AG84: MV | AJ84: AN | AK84: AC | AL84: AN | AM84: n/a | AN84: {=IF(LEFT(B84,1)="3","x",IFNA(LET(raw,XLOOKUP(C84,'Follow up.2'!B:B,'Follow up.2'!AF:AF),IF(OR(raw="",raw=0),"-",TEXT(MIN(--raw,DATE(2027,6,1)),"mm/yyyy"))),"-"))} -> 02/2027 | AO84: 46420
B85: {=ifna(iferror(xlookup(C:C,'1000'!A:A,'1000'!D:D),iferror(xlookup(C:C,'2000'!A:A,'2000'!D:D),xlookup(C:C,'3000'!A:A,'3000'!D:D))),"-")} -> 1051 | C85: 876 | D85: Anabel | E85: Robinson-Posey | F85: F | G85: F12 | H85: Sierra Robinson | I85: (570) 396-0338 | J85: (570) 396-0338 | K85: CLINICONTACT | L85: CLINICONTACT | M85: Only text parent | N85: Wave 3 initial contact | O85: 46424 | P85: MV | Q85: MV | R85: BS | S85: MV | T85: MV | U85: BS | V85: DZ | W85: BS | X85: BS | Y85: AD | Z85: {=IFERROR(xlookup(C:C,'Follow up.1'!A:A,'Follow up.1'!AF:AF),"-")} -> 9/25 | AA85: AC | AB85: AD | AC85: AK | AD85: AK | AF85: AK | AG85: IA | AI85: ? | AJ85: KL | AK85: ? | AL85: AD | AM85: n/a | AN85: {=IF(LEFT(B85,1)="3","x",IFNA(LET(raw,XLOOKUP(C85,'Follow up.2'!B:B,'Follow up.2'!AF:AF),IF(OR(raw="",raw=0),"-",TEXT(MIN(--raw,DATE(2027,6,1)),"mm/yyyy"))),"-"))} -> 02/2027 | AO85: 46424
B86: {=ifna(iferror(xlookup(C:C,'1000'!A:A,'1000'!D:D),iferror(xlookup(C:C,'2000'!A:A,'2000'!D:D),xlookup(C:C,'3000'!A:A,'3000'!D:D))),"-")} -> 2048 | C86: 1110 | D86: Arman Jonathan (AJ) | E86: Froggatt | F86: M | G86: M17 | H86: Cindy Froggatt | I86: (267) 785-4092 | J86: (917) 734-2568 | K86: CLINICONTACT | L86: CLINICONTACT | N86: Wave 3 Initial Contact | O86: 46426 | P86: AD | Q86: DZ | R86: AM | S86: AM | T86: DZ | U86: DZ | V86: DZ | W86: BS | X86: BS | Y86: DZ | Z86: {=IFERROR(xlookup(C:C,'Follow up.1'!A:A,'Follow up.1'!AF:AF),"-")} -> 10/25 | AA86: AK | AB86: KL | AC86: MV | AD86: MV | AF86: MV | AG86: ac | AI86: MV | AJ86: KL | AK86: - | AL86: EB | AM86: n/a | AN86: {=IF(LEFT(B86,1)="3","x",IFNA(LET(raw,XLOOKUP(C86,'Follow up.2'!B:B,'Follow up.2'!AF:AF),IF(OR(raw="",raw=0),"-",TEXT(MIN(--raw,DATE(2027,6,1)),"mm/yyyy"))),"-"))} -> 02/2027 | AO86: 46426
B87: {=ifna(iferror(xlookup(C:C,'1000'!A:A,'1000'!D:D),iferror(xlookup(C:C,'2000'!A:A,'2000'!D:D),xlookup(C:C,'3000'!A:A,'3000'!D:D))),"-")} -> 1080 | C87: 1457 | D87: Oliver | E87: Nguyen | F87: Male | G87: 11 | H87: Linh Doan | I87: (215) 917-0135 | J87: (610) 425-7152 | K87: Email | L87: Email | N87: Wave 3 intial contact | O87: 46428 | P87: MV | Q87: MV | R87: AM | S87: AM | T87: AM | U87: TP | V87: DZ | W87: TP | X87: TP | Y87: TP | Z87: {=IFERROR(xlookup(C:C,'Follow up.1'!A:A,'Follow up.1'!AF:AF),"-")} -> 12/25 | AA87: N/A | AB87: IA | AC87: KL | AD87: KL | AF87: AN | AG87: ? | AI87: KL | AJ87: AN | AK87: ?? | AL87: EB | AM87: n/a | AN87: {=IF(LEFT(B87,1)="3","x",IFNA(LET(raw,XLOOKUP(C87,'Follow up.2'!B:B,'Follow up.2'!AF:AF),IF(OR(raw="",raw=0),"-",TEXT(MIN(--raw,DATE(2027,6,1)),"mm/yyyy"))),"-"))} -> 02/2027 | AO87: 46428
B88: {=ifna(iferror(xlookup(C:C,'1000'!A:A,'1000'!D:D),iferror(xlookup(C:C,'2000'!A:A,'2000'!D:D),xlookup(C:C,'3000'!A:A,'3000'!D:D))),"-")} -> 1022 | C88: 507 | D88: Nashali | E88: Ortiz-Rivera | F88: F | G88: F12 | H88: Samiha Ortiz-Rivera | I88: (267) 997-4412 | J88: (267) 997-4412 | K88: Temple | L88: Temple | N88: wave 3 initial contact | O88: 46428 | P88: DZ | Q88: DZ | R88: DZ | S88: DZ | T88: DZ | U88: DZ | V88: DZ | W88: DZ | X88: DZ | Y88: DZ | Z88: {=IFERROR(xlookup(C:C,'Follow up.1'!A:A,'Follow up.1'!AF:AF),"-")} -> 9/25 | AA88: MV | AB88: MV | AC88: MV | AD88: MV | AF88: MV | AG88: MV | AI88: CP | AJ88: AK | AK88: AK | AL88: AN | AM88: n/a | AN88: {=IF(LEFT(B88,1)="3","x",IFNA(LET(raw,XLOOKUP(C88,'Follow up.2'!B:B,'Follow up.2'!AF:AF),IF(OR(raw="",raw=0),"-",TEXT(MIN(--raw,DATE(2027,6,1)),"mm/yyyy"))),"-"))} -> 02/2027 | AO88: 46428
B89: {=ifna(iferror(xlookup(C:C,'1000'!A:A,'1000'!D:D),iferror(xlookup(C:C,'2000'!A:A,'2000'!D:D),xlookup(C:C,'3000'!A:A,'3000'!D:D))),"-")} -> 2040 | C89: 981 | D89: Eliza | E89: Scott | F89: F | G89: F13 | H89: Jennifer Scott | I89: (610) 621-9974 | J89: (610) 781-1828 | K89: CLINICONTACT | L89: CLINICONTACT | N89: wave 3 initial contact | O89: 46428 | P89: DZ | Q89: DZ | R89: DZ | S89: DZ | T89: DZ | U89: DZ | V89: DZ | W89: DZ | X89: DZ | Y89: MV | Z89: {=IFERROR(xlookup(C:C,'Follow up.1'!A:A,'Follow up.1'!AF:AF),"-")} -> 9/25 | AA89: AC | AB89: CP | AC89: MV | AD89: MV | AF89: AK | AG89: IA | AI89: BH | AK89: CP | AL89: RY | AM89: n/a | AN89: {=IF(LEFT(B89,1)="3","x",IFNA(LET(raw,XLOOKUP(C89,'Follow up.2'!B:B,'Follow up.2'!AF:AF),IF(OR(raw="",raw=0),"-",TEXT(MIN(--raw,DATE(2027,6,1)),"mm/yyyy"))),"-"))} -> 02/2027 | AO89: 46428
B90: {=ifna(iferror(xlookup(C:C,'1000'!A:A,'1000'!D:D),iferror(xlookup(C:C,'2000'!A:A,'2000'!D:D),xlookup(C:C,'3000'!A:A,'3000'!D:D))),"-")} -> 1053 | C90: 1116 | D90: Zahon | E90: McDonald | F90: M | G90: M11 | H90: Chenoa McDonald | I90: (215) 410-8259 | J90: (215) 410-8259 | K90: CLINICONTACT | L90: CLINICONTACT | M90: answered - said she would do them but it passed to sts that were missed... still interested in participating | N90: wave 3 initial contact | O90: 46428 | P90: SJ | Q90: DZ | R90: DZ | S90: DZ | T90: DH | U90: MV | V90: DZ | W90: AM | X90: AM | Y90: DZ | Z90: {=IFERROR(xlookup(C:C,'Follow up.1'!A:A,'Follow up.1'!AF:AF),"-")} -> 10/25 | AA90: AK | AB90: CP | AC90: AK | AD90: AK | AF90: AK | AG90: IA | AI90: AD | AJ90: CP | AL90: AN | AM90: n/a | AN90: {=IF(LEFT(B90,1)="3","x",IFNA(LET(raw,XLOOKUP(C90,'Follow up.2'!B:B,'Follow up.2'!AF:AF),IF(OR(raw="",raw=0),"-",TEXT(MIN(--raw,DATE(2027,6,1)),"mm/yyyy"))),"-"))} -> 02/2027 | AO90: 46428
B91: {=ifna(iferror(xlookup(C:C,'1000'!A:A,'1000'!D:D),iferror(xlookup(C:C,'2000'!A:A,'2000'!D:D),xlookup(C:C,'3000'!A:A,'3000'!D:D))),"-")} -> 1054 | C91: 1117 | D91: Zaaka | E91: McDonald | F91: M | G91: M9 | H91: Chenoa McDonald | I91: 0 | J91: (215) 410-8259 | K91: CLINICONTACT | L91: CLINICONTACT | M91: answered - said she would do them but it passed to sts that were missed... still interested in participating | N91: Wave 3 initial contact | O91: 46428 | P91: DZ | Q91: DZ | R91: DZ | S91: DZ | T91: DH | U91: MV | V91: DZ | W91: AM | X91: AM | Y91: DZ | Z91: {=IFERROR(xlookup(C:C,'Follow up.1'!A:A,'Follow up.1'!AF:AF),"-")} -> 10/25 | AA91: AK | AB91: CP | AC91: AK | AD91: AK | AF91: AK | AG91: IA | AI91: AD | AJ91: CP | AL91: AN | AM91: n/a | AN91: {=IF(LEFT(B91,1)="3","x",IFNA(LET(raw,XLOOKUP(C91,'Follow up.2'!B:B,'Follow up.2'!AF:AF),IF(OR(raw="",raw=0),"-",TEXT(MIN(--raw,DATE(2027,6,1)),"mm/yyyy"))),"-"))} -> 02/2027 | AO91: 46428
B92: {=ifna(iferror(xlookup(C:C,'1000'!A:A,'1000'!D:D),iferror(xlookup(C:C,'2000'!A:A,'2000'!D:D),xlookup(C:C,'3000'!A:A,'3000'!D:D))),"-")} -> 1065 | C92: 1210 | D92: Ciana | E92: White | F92: Female (1) | G92: F12 | H92: Krystal Anyair | I92: (267) 357-2527 | J92: (267) 321-0242 | K92: CLINICONTACT | L92: CLINICONTACT | N92: wave 3 initial contact | O92: 46430 | P92: AM | Q92: DZ | R92: DZ | S92: DZ | T92: DZ | U92: DZ | V92: DZ | W92: AM | X92: AM | Y92: AM | Z92: {=IFERROR(xlookup(C:C,'Follow up.1'!A:A,'Follow up.1'!AF:AF),"-")} -> 10/25 | AA92: AK | AB92: CP | AC92: KL | AD92: KL | AF92: AD | AG92: CP | AI92: N/A | AJ92: N/A | AK92: AK | AL92: EB | AM92: n/a | AN92: {=IF(LEFT(B92,1)="3","x",IFNA(LET(raw,XLOOKUP(C92,'Follow up.2'!B:B,'Follow up.2'!AF:AF),IF(OR(raw="",raw=0),"-",TEXT(MIN(--raw,DATE(2027,6,1)),"mm/yyyy"))),"-"))} -> - | AO92: 46430
B93: {=ifna(iferror(xlookup(C:C,'1000'!A:A,'1000'!D:D),iferror(xlookup(C:C,'2000'!A:A,'2000'!D:D),xlookup(C:C,'3000'!A:A,'3000'!D:D))),"-")} -> 2049 | C93: 1165 | D93: Juhlai | E93: Dixon | F93: Female | G93: 16 | H93: Jamie Dixon | I93: (267) 303-7437 | J93: (267) 546-8234 | K93: Lighthouse | L93: Lighthouse | N93: wave 3 initial contact | O93: 46431 | P93: DZ | Q93: DZ | R93: DZ | S93: DZ | T93: DZ | U93: DZ | V93: DZ | W93: DZ | X93: DZ | Y93: DZ | Z93: {=IFERROR(xlookup(C:C,'Follow up.1'!A:A,'Follow up.1'!AF:AF),"-")} -> 10/25 | AA93: AK | AB93: KL | AC93: KL | AD93: KL | AF93: ? | AG93: AN,CP | AI93: KL | AJ93: RY | AK93: EB | AL93: AD | AM93: n/a | AN93: {=IF(LEFT(B93,1)="3","x",IFNA(LET(raw,XLOOKUP(C93,'Follow up.2'!B:B,'Follow up.2'!AF:AF),IF(OR(raw="",raw=0),"-",TEXT(MIN(--raw,DATE(2027,6,1)),"mm/yyyy"))),"-"))} -> 02/2027 | AO93: 46431
B94: {=ifna(iferror(xlookup(C:C,'1000'!A:A,'1000'!D:D),iferror(xlookup(C:C,'2000'!A:A,'2000'!D:D),xlookup(C:C,'3000'!A:A,'3000'!D:D))),"-")} -> 1056 | C94: 1107 | D94: Jeremiah | E94: Conner | F94: M | G94: M11 | H94: Shardai Jenkins | I94: (215) 594-0212 | K94: CLINICONTACT | L94: CLINICONTACT | M94: needs payment checked no scan has braces | N94: braces - 11/13/2025. Check if he has them off for wave 3 | O94: 46431 | P94: DZ | Q94: DZ | R94: DZ | S94: DZ | T94: DZ | U94: DH | V94: DZ | W94: DZ | X94: DZ | Y94: DZ | Z94: {=IFERROR(xlookup(C:C,'Follow up.1'!A:A,'Follow up.1'!AF:AF),"-")} -> 10/25 | AA94: AD | AB94: AD | AC94: AD | AD94: AD | AF94: MV | AG94: AN | AN94: {=IF(LEFT(B94,1)="3","x",IFNA(LET(raw,XLOOKUP(C94,'Follow up.2'!B:B,'Follow up.2'!AF:AF),IF(OR(raw="",raw=0),"-",TEXT(MIN(--raw,DATE(2027,6,1)),"mm/yyyy"))),"-"))} -> 02/2027
B95: {=ifna(iferror(xlookup(C:C,'1000'!A:A,'1000'!D:D),iferror(xlookup(C:C,'2000'!A:A,'2000'!D:D),xlookup(C:C,'3000'!A:A,'3000'!D:D))),"-")} -> 2052 | C95: 1211 | D95: Sye | E95: Mirsky | F95: Female (1) | G95: F17 | H95: Ani maitin | I95: 2672409964 | J95: (267) 615-5394 | K95: CLINICONTACT | L95: CLINICONTACT | N95: wave 3 initial contact | O95: 46435 | P95: AM | Q95: AM | R95: DZ | S95: DZ | T95: BS | U95: DZ | V95: DZ | W95: DZ | X95: DZ | Y95: DZ | Z95: {=IFERROR(xlookup(C:C,'Follow up.1'!A:A,'Follow up.1'!AF:AF),"-")} -> 10/25 | AA95: AK | AB95: CP | AC95: MV | AD95: CP | AF95: KL | AG95: EB | AI95: CP | AJ95: AD | AK95: KL | AL95: EB | AM95: n/a | AN95: {=IF(LEFT(B95,1)="3","x",IFNA(LET(raw,XLOOKUP(C95,'Follow up.2'!B:B,'Follow up.2'!AF:AF),IF(OR(raw="",raw=0),"-",TEXT(MIN(--raw,DATE(2027,6,1)),"mm/yyyy"))),"-"))} -> 02/2027 | AO95: 46435
B96: {=ifna(iferror(xlookup(C:C,'1000'!A:A,'1000'!D:D),iferror(xlookup(C:C,'2000'!A:A,'2000'!D:D),xlookup(C:C,'3000'!A:A,'3000'!D:D))),"-")} -> 2047 | C96: 1109 | D96: Jahbril | E96: Jenkins | F96: M | G96: M17 | H96: Shardai Jenkins | I96: (215) 594-0212 | K96: CLINICONTACT | L96: CLINICONTACT | M96: for megan; amazon issue | N96: Wave 3 initial contact | O96: 46447 | P96: DZ | Q96: DZ | R96: DZ | S96: DZ | T96: DZ | U96: DH | V96: DZ | W96: AM | X96: AM | Y96: DZ | Z96: {=IFERROR(xlookup(C:C,'Follow up.1'!A:A,'Follow up.1'!AF:AF),"-")} -> 10/25 | AA96: AD | AB96: AD | AC96: KL | AD96: KL | AF96: ?? | AG96: CP | AI96: MV | AJ96: ?? | AK96: AN | AL96: KL | AM96: n/a | AN96: {=IF(LEFT(B96,1)="3","x",IFNA(LET(raw,XLOOKUP(C96,'Follow up.2'!B:B,'Follow up.2'!AF:AF),IF(OR(raw="",raw=0),"-",TEXT(MIN(--raw,DATE(2027,6,1)),"mm/yyyy"))),"-"))} -> 03/2027 | AO96: 46447
B97: {=ifna(iferror(xlookup(C:C,'1000'!A:A,'1000'!D:D),iferror(xlookup(C:C,'2000'!A:A,'2000'!D:D),xlookup(C:C,'3000'!A:A,'3000'!D:D))),"-")} -> 2035 | C97: 869 | D97: Sherie | E97: Clark | F97: F | G97: F14 | H97: Dawn Keith | I97: (215) 307-9363 | J97: (215) 307-9363 | K97: CLINICONTACT | L97: CLINICONTACT | M97: has nose piercing but removable and healed now! - two months past their visit from last year | N97: w3 initial contact | O97: 46478 | P97: DZ | Q97: DZ | R97: DZ | S97: DZ | T97: DZ | U97: DZ | V97: DZ | W97: DZ | X97: DZ | Y97: DZ | Z97: {=IFERROR(xlookup(C:C,'Follow up.1'!A:A,'Follow up.1'!AF:AF),"-")} -> 8/25 | AA97: RY | AB97: MS | AC97: MV | AD97: MV | AF97: AMo | AG97: AMo | AI97: AMo | AJ97: MV | AK97: MV | AL97: MV | AM97: n/a | AN97: {=IF(LEFT(B97,1)="3","x",IFNA(LET(raw,XLOOKUP(C97,'Follow up.2'!B:B,'Follow up.2'!AF:AF),IF(OR(raw="",raw=0),"-",TEXT(MIN(--raw,DATE(2027,6,1)),"mm/yyyy"))),"-"))} -> 04/2027
B98: {=ifna(iferror(xlookup(C:C,'1000'!A:A,'1000'!D:D),iferror(xlookup(C:C,'2000'!A:A,'2000'!D:D),xlookup(C:C,'3000'!A:A,'3000'!D:D))),"-")} -> 2045 | C98: 1093 | D98: Dirk | E98: Spaeth | F98: M | G98: M17 | H98: Jules Spaeth | I98: (484) 434-9714 | J98: (215) 356-4314 | K98: CLINICONTACT | L98: CLINICONTACT | N98: Wave 3 Initial contact | O98: 46478 | P98: AM | Q98: DZ | R98: DZ | S98: DZ | T98: AM | U98: BS | V98: DZ | W98: BS | X98: BS | Y98: DZ | Z98: {=IFERROR(xlookup(C:C,'Follow up.1'!A:A,'Follow up.1'!AF:AF),"-")} -> 10/25 | AA98: AK | AB98: KL | AC98: Kl | AD98: AN | AF98: AM | AG98: CP | AI98: AN | AJ98: AN | AK98: CP | AL98: MS | AM98: MS | AN98: {=IF(LEFT(B98,1)="3","x",IFNA(LET(raw,XLOOKUP(C98,'Follow up.2'!B:B,'Follow up.2'!AF:AF),IF(OR(raw="",raw=0),"-",TEXT(MIN(--raw,DATE(2027,6,1)),"mm/yyyy"))),"-"))} -> 04/2027 | AO98: 46478
B99: {=ifna(iferror(xlookup(C:C,'1000'!A:A,'1000'!D:D),iferror(xlookup(C:C,'2000'!A:A,'2000'!D:D),xlookup(C:C,'3000'!A:A,'3000'!D:D))),"-")} -> 1077 | C99: 1442 | D99: Khamari | E99: Almodovar | F99: M | G99: 10 | H99: Shavon Patrice | I99: (267) 303-2082 | J99: 267 444 1242 | K99: CLINICONTACT (2nd refferal) | L99: CLINICONTACT (2nd refferal) | N99: Wave 3 initital contact | O99: 46492 | P99: DZ | Q99: DZ | R99: DZ | S99: DZ | T99: AM | U99: AM | V99: DZ | W99: TP | X99: TP | Y99: TP | Z99: {=IFERROR(xlookup(C:C,'Follow up.1'!A:A,'Follow up.1'!AF:AF),"-")} -> 12/25 | AA99: AMo | AB99: CP | AC99: CP | AD99: AD | AF99: AD | AG99: AN | AI99: KL | AJ99: ? | AK99: ? | AL99: AD | AM99: n/a | AN99: {=IF(LEFT(B99,1)="3","x",IFNA(LET(raw,XLOOKUP(C99,'Follow up.2'!B:B,'Follow up.2'!AF:AF),IF(OR(raw="",raw=0),"-",TEXT(MIN(--raw,DATE(2027,6,1)),"mm/yyyy"))),"-"))} -> 04/2027 | AO99: 46492
B100: {=ifna(iferror(xlookup(C:C,'1000'!A:A,'1000'!D:D),iferror(xlookup(C:C,'2000'!A:A,'2000'!D:D),xlookup(C:C,'3000'!A:A,'3000'!D:D))),"-")} -> 2062 | C100: 1280 | D100: Owen | E100: Ganley | F100: Male (2) | G100: 16 | H100: Maria Crespo | I100: (267) 254-6966 | J100: (267) 559-0613 | K100: CLINICONTACT | L100: CLINICONTACT | N100: Wave 3 initial contact | O100: 46503 | P100: AM | Q100: AM | R100: DZ | S100: DZ | T100: AD | U100: AM | V100: DZ | W100: DZ | X100: DZ | Y100: DZ | Z100: {=IFERROR(xlookup(C:C,'Follow up.1'!A:A,'Follow up.1'!AF:AF),"-")} -> 11/25 | AA100: KL | AB100: AN | AC100: AK | AD100: AK | AF100: CP | AG100: RY | AJ100: CP | AL100: CP | AN100: {=IF(LEFT(B100,1)="3","x",IFNA(LET(raw,XLOOKUP(C100,'Follow up.2'!B:B,'Follow up.2'!AF:AF),IF(OR(raw="",raw=0),"-",TEXT(MIN(--raw,DATE(2027,6,1)),"mm/yyyy"))),"-"))} -> 04/2027 | AO100: 46503
...

Sheet Scheduling Eligibility
C1: When editing this sheet DO NOT use copy/paste
I2: Scan | K2: Scan shadow MUST BE ACCOMPANIED BY L3 and L2 | M2: V1 | P2: Signups - do not count for marks
B3: Initials | C3: Researchers | D3: Visit Tally since 1/1/2025 | I3: L3 | J3: L2 | K3: L3 | L3: L2 | M3: V1 | N3: V1 Shadow (must be with someone who can do V1) | P3: Screeners | V3: 3/20/2025 to 5/31/2025 Scanning Tally | X3: 6/1/2025 to 1/19/2026 Scanning Tally | AI3: 2
B4: AP | C4: Anushka | D4: 15 | I4: =if('Scheduling Code'!N3="x","",'Scheduling Code'!N3) -> Shenghan | J4: =if('Scheduling Code'!O3="x","",'Scheduling Code'!O3) -> Isabel | K4: =if('Scheduling Code'!P3="x","",'Scheduling Code'!P3) -> Camilla | L4: =if('Scheduling Code'!Q3="x","",'Scheduling Code'!Q3) -> Aashna | M4: =if('Scheduling Code'!R3="x","",'Scheduling Code'!R3) -> Aashna | N4: =if('Scheduling Code'!S3="x","",'Scheduling Code'!S3) -> Kiara | P4: Megan | V4: Avi | W4: 30 | X4: Avi Dachs | Y4: 42 | AI4: 1
B5: AD | C5: Avi | D5: 20 | I5: =if('Scheduling Code'!N4="x","",'Scheduling Code'!N4) -> Danny | J5: =if('Scheduling Code'!O4="x","",'Scheduling Code'!O4) -> Maia | K5: =if('Scheduling Code'!P4="x","",'Scheduling Code'!P4) -> Sophie | L5: =if('Scheduling Code'!Q4="x","",'Scheduling Code'!Q4) -> Shenghan | M5: =if('Scheduling Code'!R4="x","",'Scheduling Code'!R4) -> Alicia | N5: =if('Scheduling Code'!S4="x","",'Scheduling Code'!S4) | P5: Emily | V5: Danny | W5: 29 | X5: Megan Vince | Y5: 36 | AI5: 35
B6: MV | C6: Megan | D6: 17 | I6: =if('Scheduling Code'!N5="x","",'Scheduling Code'!N5) -> Lina | J6: =if('Scheduling Code'!O5="x","",'Scheduling Code'!O5) -> Camilla | K6: =if('Scheduling Code'!P5="x","",'Scheduling Code'!P5) -> Anushka | L6: =if('Scheduling Code'!Q5="x","",'Scheduling Code'!Q5) -> Alicia | M6: =if('Scheduling Code'!R5="x","",'Scheduling Code'!R5) -> Emily | N6: =if('Scheduling Code'!S5="x","",'Scheduling Code'!S5) | P6: Avi | V6: Megan | W6: 28 | X6: Abby Kennedy | Y6: 4 | AI6: 11
B7: AK | C7: Abby | D7: 8 | I7: =if('Scheduling Code'!N6="x","",'Scheduling Code'!N6) -> Isabel | J7: =if('Scheduling Code'!O6="x","",'Scheduling Code'!O6) -> Abby | K7: =if('Scheduling Code'!P6="x","",'Scheduling Code'!P6) | L7: =if('Scheduling Code'!Q6="x","",'Scheduling Code'!Q6) -> Emily | M7: =if('Scheduling Code'!R6="x","",'Scheduling Code'!R6) -> Sophie | N7: =if('Scheduling Code'!S6="x","",'Scheduling Code'!S6) | P7: Abby | V7: Maia | W7: 8 | X7: Andrew Cardona | Y7: 16 | AI7: 347
B8: AC | C8: Andrew | D8: 17 | I8: =if('Scheduling Code'!N7="x","",'Scheduling Code'!N7) -> Andrew | J8: =if('Scheduling Code'!O7="x","",'Scheduling Code'!O7) -> Anushka | K8: =if('Scheduling Code'!P7="x","",'Scheduling Code'!P7) | L8: =if('Scheduling Code'!Q7="x","",'Scheduling Code'!Q7) -> Kiara | M8: =if('Scheduling Code'!R7="x","",'Scheduling Code'!R7) -> Rae | N8: =if('Scheduling Code'!S7="x","",'Scheduling Code'!S7) | P8: Andrew | V8: Isabel | W8: 7 | X8: Kirsten | Y8: 33 | AI8: 388
B9: KD | C9: Kiara | D9: 4 | I9: =if('Scheduling Code'!N8="x","",'Scheduling Code'!N8) -> Megan | J9: =if('Scheduling Code'!O8="x","",'Scheduling Code'!O8) -> Andrew | L9: =if('Scheduling Code'!Q8="x","",'Scheduling Code'!Q8) -> Sophie | M9: =if('Scheduling Code'!R8="x","",'Scheduling Code'!R8) -> Maia | N9: =if('Scheduling Code'!S8="x","",'Scheduling Code'!S8) | P9: Rae - training | V9: Kirsten | W9: 6 | X9: Binh | Y9: 25 | AI9: 1220
B10: DZ | C10: Danny | D10: 8 | I10: =if('Scheduling Code'!N9="x","",'Scheduling Code'!N9) -> Avi | J10: =if('Scheduling Code'!O9="x","",'Scheduling Code'!O9) -> Megan | K10: =if('Scheduling Code'!P9="x","",'Scheduling Code'!P9) | L10: =if('Scheduling Code'!Q9="x","",'Scheduling Code'!Q9) -> Rae | M10: =if('Scheduling Code'!R9="x","",'Scheduling Code'!R9) -> Camilla | N10: =if('Scheduling Code'!S9="x","",'Scheduling Code'!S9) | P10: Maia | V10: Binh | W10: 5 | X10: Ife | Y10: 5 | AI10: 2483
B11: AH | C11: Alicia | D11: 3 | I11: =if('Scheduling Code'!N10="x","",'Scheduling Code'!N10) | J11: =if('Scheduling Code'!O10="x","",'Scheduling Code'!O10) -> Avi | K11: =if('Scheduling Code'!P10="x","",'Scheduling Code'!P10) | L11: =if('Scheduling Code'!Q10="x","",'Scheduling Code'!Q10) | M11: =if('Scheduling Code'!R10="x","",'Scheduling Code'!R10) -> Abby | N11: =if('Scheduling Code'!S10="x","",'Scheduling Code'!S10) | P11: Binh | V11: Aashna | W11: 5 | X11: Camilla | Y11: 5 | AI11: 0
B12: CP | C12: Camilla | D12: 7 | I12: =if('Scheduling Code'!N11="x","",'Scheduling Code'!N11) | J12: =if('Scheduling Code'!O11="x","",'Scheduling Code'!O11) | K12: =if('Scheduling Code'!P11="x","",'Scheduling Code'!P11) | L12: =if('Scheduling Code'!Q11="x","",'Scheduling Code'!Q11) | M12: =if('Scheduling Code'!R11="x","",'Scheduling Code'!R11) -> Anushka | N12: =if('Scheduling Code'!S11="x","",'Scheduling Code'!S11) | P12: Sophie | V12: Sophie | W12: 4 | X12: Maia | Y12: 4 | AI12: 62
B13: MS | C13: Maia | D13: 7 | I13: =if('Scheduling Code'!N12="x","",'Scheduling Code'!N12) | J13: =if('Scheduling Code'!O12="x","",'Scheduling Code'!O12) | K13: =if('Scheduling Code'!P12="x","",'Scheduling Code'!P12) | M13: =if('Scheduling Code'!R12="x","",'Scheduling Code'!R12) -> Andrew | N13: =if('Scheduling Code'!S12="x","",'Scheduling Code'!S12) | P13: Camilla | V13: Harry | W13: 4 | X13: Aashna | Y13: 3 | AI13: 572
B14: AM | C14: Aashna | D14: 2 | I14: =if('Scheduling Code'!N13="x","",'Scheduling Code'!N13) | J14: =if('Scheduling Code'!O13="x","",'Scheduling Code'!O13) | K14: =if('Scheduling Code'!P13="x","",'Scheduling Code'!P13) | L14: =if('Scheduling Code'!Q13="x","",'Scheduling Code'!Q13) | M14: =if('Scheduling Code'!R13="x","",'Scheduling Code'!R13) -> Megan | N14: =if('Scheduling Code'!S13="x","",'Scheduling Code'!S13) | V14: Brooke | W14: 4 | X14: Isabel | Y14: 8 | AI14: 22
B15: IL | C15: Isabel | D15: 6 | I15: =if('Scheduling Code'!N14="x","",'Scheduling Code'!N14) | J15: =if('Scheduling Code'!O14="x","",'Scheduling Code'!O14) | K15: =if('Scheduling Code'!P14="x","",'Scheduling Code'!P14) | L15: =if('Scheduling Code'!Q14="x","",'Scheduling Code'!Q14) | M15: =if('Scheduling Code'!R14="x","",'Scheduling Code'!R14) -> Avi | N15: =if('Scheduling Code'!S14="x","",'Scheduling Code'!S14) | V15: Ife | W15: 3 | X15: Lina | Y15: 2 | AI15: 149
B16: LH | C16: Lina | D16: 4 | I16: =if('Scheduling Code'!N15="x","",'Scheduling Code'!N15) | J16: =if('Scheduling Code'!O15="x","",'Scheduling Code'!O15) | K16: =if('Scheduling Code'!P15="x","",'Scheduling Code'!P15) | L16: =if('Scheduling Code'!Q15="x","",'Scheduling Code'!Q15) | M16: =if('Scheduling Code'!R15="x","",'Scheduling Code'!R15) | N16: =if('Scheduling Code'!S15="x","",'Scheduling Code'!S15) | V16: Rae | W16: 2 | X16: Shenghan | Y16: 4 | AI16: 109
B17: SW | C17: Shenghan | D17: 3 | I17: =if('Scheduling Code'!N16="x","",'Scheduling Code'!N16) | J17: =if('Scheduling Code'!O16="x","",'Scheduling Code'!O16) | K17: =if('Scheduling Code'!P16="x","",'Scheduling Code'!P16) | L17: =if('Scheduling Code'!Q16="x","",'Scheduling Code'!Q16) | M17: =if('Scheduling Code'!R16="x","",'Scheduling Code'!R16) | N17: =if('Scheduling Code'!S16="x","",'Scheduling Code'!S16) | V17: Titiksha | W17: 1 | X17: Rae | Y17: 4 | AI17: 405
B18: RY | C18: Rae | D18: 7 | I18: =if('Scheduling Code'!N17="x","",'Scheduling Code'!N17) | J18: =if('Scheduling Code'!O17="x","",'Scheduling Code'!O17) | K18: =if('Scheduling Code'!P17="x","",'Scheduling Code'!P17) | L18: =if('Scheduling Code'!Q17="x","",'Scheduling Code'!Q17) | M18: =if('Scheduling Code'!R17="x","",'Scheduling Code'!R17) | N18: =if('Scheduling Code'!S17="x","",'Scheduling Code'!S17) | V18: Shenghan | W18: 1 | X18: Sophie | Y18: 4 | AI18: 34
B19: SM | C19: Sophie | D19: 5 | I19: =if('Scheduling Code'!N18="x","",'Scheduling Code'!N18) | J19: =if('Scheduling Code'!O18="x","",'Scheduling Code'!O18) | K19: =if('Scheduling Code'!P18="x","",'Scheduling Code'!P18) | L19: =if('Scheduling Code'!Q18="x","",'Scheduling Code'!Q18) | M19: =if('Scheduling Code'!R18="x","",'Scheduling Code'!R18) | N19: =if('Scheduling Code'!S18="x","",'Scheduling Code'!S18) | V19: Samra | W19: 1 | X19: Emily | Y19: 2 | AI19: 1
B20: EB | C20: Emily | D20: 4 | I20: =if('Scheduling Code'!N19="x","",'Scheduling Code'!N19) | J20: =if('Scheduling Code'!O19="x","",'Scheduling Code'!O19) | K20: =if('Scheduling Code'!P19="x","",'Scheduling Code'!P19) | L20: =if('Scheduling Code'!Q19="x","",'Scheduling Code'!Q19) | M20: =if('Scheduling Code'!R19="x","",'Scheduling Code'!R19) | N20: =if('Scheduling Code'!S19="x","",'Scheduling Code'!S19) | V20: Jay | W20: 1 | AI20: 35
B21: SB | C21: Samra | D21: 3 | I21: =if('Scheduling Code'!N20="x","",'Scheduling Code'!N20) | J21: =if('Scheduling Code'!O20="x","",'Scheduling Code'!O20) | K21: =if('Scheduling Code'!P20="x","",'Scheduling Code'!P20) | L21: =if('Scheduling Code'!Q20="x","",'Scheduling Code'!Q20) | M21: =if('Scheduling Code'!R20="x","",'Scheduling Code'!R20) | N21: =if('Scheduling Code'!S20="x","",'Scheduling Code'!S20) | V21: Cooper (???) | W21: 1 | AI21: 83
B22: NM | C22: Natalie | I22: =if('Scheduling Code'!N21="x","",'Scheduling Code'!N21) | V22: Lina | W22: 0 | AI22: 3
V23: Camilla | W23: 0
V24: Abby | W24: 0

Sheet 1000
B2: participant dropped out of the study or stopped responding
B3: unsusable data
B4: Excused no-show/partial visit | G4: VISIT 1 | M4: VISIT 2 | U4: Wave 2 Visit 1 | AC4: Wave 2 Visit 2 | AN4: Wave 3 Visit 1 | AV4: Wave 3 Visit 2
B5: Completed visit
B6: No Mri Moving Forward
A7: Record ID | B7: First name | C7: Last name | D7: PID | G7: Date | H7: RAs | I7: Notes | J7: Data transferred? | M7: Date | N7: RAs | O7: Notes | P7: X-NAT data | Q7: Behavioral data | R7: Compensation? | U7: Date | V7: RA | W7: Shadow RA | X7: Notes | Y7: Behavioral data | Z7: Compensation? | AC7: Date | AD7: L3 RA | AE7: L2 RA | AF7: Shadow 1 | AG7: Shadow 2 | AH7: Notes | AI7: X-NAT data | AJ7: Behavioral data | AK7: Compensation? | AN7: Date | AO7: RA | AP7: Shadow RA | AQ7: Notes | AR7: Behavioral data | AS7: Compensation? | AV7: Date | AW7: L3 | AX7: L2 | AY7: Shadow 1 | AZ7: Shadow 2 | BA7: Notes | BB7: X-NAT data | BC7: Behavioral data | BD7: Compensation?
A8: 46 | B8: {=IFNA(XLOOKUP(A8,'New Signups'!C:C,'New Signups'!D:D),"-")} -> Naylah | C8: {=IFNA(XLOOKUP(A8,'New Signups'!C:C,'New Signups'!E:E),"-")} -> Hopkins | D8: 1001 | G8: 45029 | H8: King | I8: Long session, ran half hour over; good participant | J8: Y | M8: 45019 | N8: Skalaban/Murray/King | O8: Visit ran long; participant didn't understand Chatroom very well. Kept falling asleep but tried her best. | P8: Y | Q8: Y | R8: Y
A9: 47 | B9: {=IFNA(XLOOKUP(A9,'New Signups'!C:C,'New Signups'!D:D),"-")} -> Vihaan | C9: {=IFNA(XLOOKUP(A9,'New Signups'!C:C,'New Signups'!E:E),"-")} -> Kaushik | D9: 1002 | E9: 1 | F9: 1 | G9: 45037 | H9: Murray | I9: No notes; good session | J9: Y | M9: 45065 | N9: Skalaban/King | O9: Did very well, got a little frustrated during GNG (button presses). | P9: Y | Q9: Y | R9: Y | U9: 45675 | V9: Megan | X9: for pat icons put 1002.2 not 10022 but not for peers. Also, he was like spamming keys for shortant | Y9: y | Z9: y | AC9: 45701 | AD9: Danny | AE9: Megan | AH9: good session - localizer and fieldmaps again after 2nd round of gng | AI9: Y | AJ9: Y | AK9: Y
A10: 57 | B10: {=IFNA(XLOOKUP(A10,'New Signups'!C:C,'New Signups'!D:D),"-")} -> Laughlin she/her | C10: {=IFNA(XLOOKUP(A10,'New Signups'!C:C,'New Signups'!E:E),"-")} -> Monahan | D10: 1005 | E10: 1 | F10: 1 | G10: 45118 | H10: Murray/Shulski | I10: great session; would like to see an image of her brain | J10: Y | M10: 45126 | N10: Murray/King | O10: did not get to DTI | P10: Y | Q10: Y | R10: Y | U10: 45657 | V10: Danny | X10: answered MTES questions regaruding IPAD | Y10: Y | Z10: Y | AC10: 45634 | AD10: Danny | AE10: Megan | AH10: good session no notes | AI10: Y | AJ10: Y | AK10: Y
A11: 63 | B11: {=IFNA(XLOOKUP(A11,'New Signups'!C:C,'New Signups'!D:D),"-")} -> Elizabeth | C11: {=IFNA(XLOOKUP(A11,'New Signups'!C:C,'New Signups'!E:E),"-")} -> Lem | D11: 1006 | E11: 1 | F11: 1 | G11: 45118 | H11: Wyatt | I11: Great session and participant! Session ran about a half an hour over time, but completed everything after moving to 841. Data for gameofdice and stoplight was not transferred (done in 844 and room was occupied). Would like to see an image of her brain | J11: Y | M11: 45126 | N11: Murray/King | O11: did not get to DTI | P11: Y | Q11: Y | R11: Y | U11: 45761 | V11: Sophie | X11: good session, no notes | Y11: Y | Z11: Y | AC11: 45817 | AD11: Megan | AE11: Binh | AH11: didn't run dd social, participant had braces | AI11: Y | AJ11: Y
A12: 75 | B12: {=IFNA(XLOOKUP(A12,'New Signups'!C:C,'New Signups'!D:D),"-")} -> Sadie | C12: {=IFNA(XLOOKUP(A12,'New Signups'!C:C,'New Signups'!E:E),"-")} -> Davis | D12: 1018 | E12: 1 | F12: 1 | G12: 45216 | H12: Zweben/Neil | I12: good session | J12: Y | M12: 45233 | N12: Murray/King/Zweben | O12: She did awesome, struggled a bit eith PAT at first but got it, had a hard time with planet gonogo but did her best - she is very young | P12: Y | Q12: Y | R12: Y | U12: 45744 | V12: Rae | W12: Megan | X12: No notes, good session | Y12: y | Z12: y | AC12: 45778 | AD12: Danny | AE12: Avi | AH12: No notes good session | AI12: y | AJ12: y | AK12: y
A13: 76 | B13: {=IFNA(XLOOKUP(A13,'New Signups'!C:C,'New Signups'!D:D),"-")} -> Caleb | C13: {=IFNA(XLOOKUP(A13,'New Signups'!C:C,'New Signups'!E:E),"-")} -> Davis | D13: 1011 | E13: 1 | F13: 1 | G13: 45105 | H13: King | I13: Great session; finished in an hour. Seemed attentive | J13: Y | M13: 45118 | N13: King | O13: good session went well | P13: Y | Q13: Y | R13: Y | U13: 45744 | V13: Sophie | X13: put 2 instead of 1 for group number | Y13: Y | Z13: Y | AC13: 45769 | AD13: Isabel | AE13: Samra | AF13: Danny | AH13: No 2nd round of PAT - had to skip | AI13: Y | AJ13: Y | AK13: Y
A14: 96 | B14: {=IFNA(XLOOKUP(A14,'New Signups'!C:C,'New Signups'!D:D),"-")} -> Ari | C14: {=IFNA(XLOOKUP(A14,'New Signups'!C:C,'New Signups'!E:E),"-")} -> Woodward | D14: 1009 | E14: 1 | F14: 1 | G14: 45097 | H14: Wyatt | I14: Bored often, coversational, couldn't complete short ant or uberball due to time - ANSWERED MTES/SAS/OBJ about IPAD | J14: Y | M14: 45127 | N14: King/Murray | O14: After the scan was tired and didn't want to be here anymore. Had to take him upstairs for uberball and short ANT that was not completed in his v1, but our inquisit license expired so I could not run either of the two tasks. For foraging task - lost him in this game- was very uninterested. Was tired from the scan. | P14: Y | Q14: Y | R14: Y
A15: 115 | B15: {=IFNA(XLOOKUP(A15,'New Signups'!C:C,'New Signups'!D:D),"-")} -> Iyannah | C15: {=IFNA(XLOOKUP(A15,'New Signups'!C:C,'New Signups'!E:E),"-")} -> Marshall* | D15: 1017 | E15: 1 | F15: 1 | G15: 45209 | H15: Zweben/King | I15: UberBall and Short Ans. not complete | J15: Y | M15: 45236 | N15: King/Murray/Shulski | O15: Forgot to run her through ANT and Uberball that was missed in visit one. Moved a lot, and got extremely tired by the 3rd round of go no go. See visit two time stamps for more specific information. | P15: Y | Q15: Y | R15: Y | U15: 45737 | V15: Maia | W15: Megan | X15: Could not sit still started to get really bored started distracting her brother didnt want to continue so skipped last survey and short ant and uberball and just did PAT but said yes to being friends with everyone | Y15: y | Z15: y | AC15: 45748 | AD15: Danny | AE15: Avi | AH15: Skipped GNG she was exhausted, fell asleep/wasn't paying attention during 2nd round of PAT. DTI sequence broken - DONT use dti data (Only 1st round PAT and T1 Usable) | AI15: Y | AJ15: Y | AK15: Y
A16: 116 | B16: {=IFNA(XLOOKUP(A16,'New Signups'!C:C,'New Signups'!D:D),"-")} -> Idris | C16: {=IFNA(XLOOKUP(A16,'New Signups'!C:C,'New Signups'!E:E),"-")} -> Marshall* | D16: 1003 | E16: 1 | F16: 1 | G16: 45084 | H16: Wyatt | I16: No notes; good session | J16: Y | M16: 45090 | N16: Skalaban/King | O16: good session went well | P16: Y | Q16: Y | R16: Y | U16: 45737 | V16: Aashna | X16: good session - hard to pay attention on flanker and uberball (little sister distracted him) | Y16: y | Z16: y | AC16: 45847 | AD16: Avi | AE16: Binh | AF16: Ife | AH16: Everything's unusable but DTI. PAT task wasn't working. He fell asleep during GnG | AI16: Y | AJ16: Y | AK16: Y
A17: 127 | B17: {=IFNA(XLOOKUP(A17,'New Signups'!C:C,'New Signups'!D:D),"-")} -> Morgan | C17: {=IFNA(XLOOKUP(A17,'New Signups'!C:C,'New Signups'!E:E),"-")} -> Weaver | D17: 1007 | E17: 1 | F17: 1 | G17: 45091 | H17: Murray | I17: Browser crashed after the game of dice but all data seemed to have saved when reopened the tab, continued as usual. Lost participant attention for the last two-ish minutes of short ANT but he continued to do the task. | J17: Y | M17: 45108 | N17: Tanriverdi/King | O17: Did very well, we had to let him go to the bathroom after he finished PAT, so it delayed the completion a bit (finished in 1 hr 50 mins), and we had to rerun Scout & localizer before planet GNG. | P17: Y | Q17: Y | R17: Y | U17: 45740 | V17: Danny | X17: Great Visit - Great Kid | AC17: 45743 | AD17: Avi | AE17: Danny | AH17: Good session, no notes | AI17: Y | AJ17: Y | AK17: Y
A18: 132 | B18: {=IFNA(XLOOKUP(A18,'New Signups'!C:C,'New Signups'!D:D),"-")} -> Joshua | C18: {=IFNA(XLOOKUP(A18,'New Signups'!C:C,'New Signups'!E:E),"-")} -> Gerecht | D18: 1014 | E18: 1 | F18: 1 | G18: 45131 | H18: Wyatt | I18: Game of Dice, UberBall and Short Ans. not complete | J18: Y | M18: 45145 | N18: Murray/King | O18: was fidgety and struggles with a lot of the tasks. Pat Task practice would not load. Missed a lot of the pat task trails. We did not get to DTI. | P18: Y | Q18: Y | R18: Y | U18: 45732 | V18: Avi | X18: His objective screen time data should be ignored (he said that its innaccurate and shows him being on it all night when he hasn't been) | Y18: Y | Z18: Y | AC18: 45762 | AD18: Danny | AH18: No notes- understood GNG but was just really bad at it | AI18: Y | AJ18: Y | AK18: Y
A19: 133 | B19: {=IFNA(XLOOKUP(A19,'New Signups'!C:C,'New Signups'!D:D),"-")} -> JJ (Jensen) | C19: {=IFNA(XLOOKUP(A19,'New Signups'!C:C,'New Signups'!E:E),"-")} -> Cressman | D19: 1008 | E19: 1 | F19: 1 | G19: 45090 | H19: Murray | I19: Bored after first break, got easily distracted and would tell personal anecdotes. said the games are boring - did not run peer social feedback task, was told not to run. Should do at visit two | J19: Y | M19: 45100 | N19: Tanriverdi/Foley/King | O19: Did very well, got tired toward the end but completed all tasks. Went into the scanner a little late, finished at around 2h30m. Planet GNG may have issues (more in REDCap). | P19: Y | Q19: Y | R19: Y | U19: 45737 | V19: Brooke | X19: PAT friends task slightly glitched, great visit | Y19: Y | Z19: Y | AC19: 45779 | AD19: Avi | AE19: Danny | AH19: He left the scanner after the second round of GnG. The movie was playing in the background for the whole GnG. | AI19: Y | AJ19: Y | AK19: Y
A20: 136 | B20: Holden | C20: Saalbach | D20: 1010 | E20: 1 | G20: 45103 | H20: Wyatt | I20: Bored often and got very easily distracted. Got very upset during dice when money was lost. Participant had difficulty remaining focused during tasks and surveys most during ANT. | J20: Y | M20: 45105 | N20: King/Murray | O20: He could not handle the mri. We won't be able to follow up with him. | Q20: Y | R20: Y
A21: 153 | B21: {=IFNA(XLOOKUP(A21,'New Signups'!C:C,'New Signups'!D:D),"-")} -> Idris | C21: {=IFNA(XLOOKUP(A21,'New Signups'!C:C,'New Signups'!E:E),"-")} -> Taylor | D21: 1004 | E21: 1 | F21: 1 | G21: 45113 | H21: Murray | I21: For stoplight I accidentally put in 1003 as his PID. I was able to backup the stoplight files to OneDrive. His correct stoplight files are in his folder 1004 in the stoplight folder. The output files include 1003 in the name due to my error, however I was able to differenciate based on the date of the output files. Aside from incorrect labling of files in the folder and on Toad in 841 all data is there and backed up on the OneDrive as it typically would be. 1003 is also in redcap for stoplight which needs to be changed if possible. other than that great visit, but he completed all the surveys and games in just an hour. | J21: Y | M21: 45121 | N21: King/Murray | O21: P pressed squeeze ball because it was too loud and his ears hurt. We took him out of scanner to readjust. When we did that and put him back in we got an error on the scanning computer. Tried to make adjustments to P's placement in scanner etc. Took P in and out 3 or 4 times and continued to get the same system error. Only got through PAT block one. P is willing to come back and is scheduled for the 27th of July, however it is rather far away and does not follow protocol so we are reaching out to Jason to get his approval/denial. P was very understanding and so was the mom. P did seem to be a little stressed but did not verbalize if this was in fact the case or not. (assumption he was stressed). | P21: - | Q21: - | R21: Y
A22: 155 | B22: {=IFNA(XLOOKUP(A22,'New Signups'!C:C,'New Signups'!D:D),"-")} -> Jacob | C22: {=IFNA(XLOOKUP(A22,'New Signups'!C:C,'New Signups'!E:E),"-")} -> Gibbons | D22: 1015 | E22: 1 | F22: 1 | G22: 45161 | H22: Shulski | I22: UberBall and Short Ans. not complete | J22: Y | M22: 45194 | N22: King | O22: good session, got bored during gng but did his best | P22: Y | Q22: Y | R22: Y | U22: 45739 | V22: Avi | X22: Game of Dice couldn't be run due to a lack of disk space on the 844 computer | Y22: Couldn't transfer the data because the computer was full. | Z22: Y | AC22: 45810 | AD22: Avi | AE22: Kirsten | AF22: Binh | AH22: video sound was playing in gng but otherwise all's good | AI22: Y | AJ22: Y | AK22: Y
A23: 160 | B23: Kiran | C23: Singh | D23: 1013 | E23: 1 | G23: 45114 | H23: King | I23: Great session, finished all tasks on time. great P!! | J23: Y
A24: 169 | B24: {=IFNA(XLOOKUP(A24,'New Signups'!C:C,'New Signups'!D:D),"-")} -> Magnolia (Maggie) | C24: {=IFNA(XLOOKUP(A24,'New Signups'!C:C,'New Signups'!E:E),"-")} -> Becker | D24: 1012 | E24: 1 | F24: 1 | G24: 45160 | H24: Murray | I24: Good session | J24: Y | M24: 45163 | N24: Murray/King | O24: She did great, no notes | P24: Y | Q24: Y | R24: Y | U24: 45741 | AC24: 45741
A25: 180 | B25: {=IFNA(XLOOKUP(A25,'New Signups'!C:C,'New Signups'!D:D),"-")} -> Connor | C25: {=IFNA(XLOOKUP(A25,'New Signups'!C:C,'New Signups'!E:E),"-")} -> Fitzpatrick | D25: 1016 | E25: 1 | F25: 1 | G25: 45192 | H25: King | I25: gender fluid, uses he/she pronouns | J25: Y | M25: 10/1/2023 | N25: King | O25: He did great, no notes | P25: Y | Q25: Y | R25: Y | U25: 45851 | V25: Megan | X25: No notes, good session | Y25: Y | Z25: Y | AC25: 45858 | AD25: Avi | AE25: Lina | AF25: Ife | AH25: No Notes (some internal self-tests and calibrations were skipped for PAT) | AJ25: Y | AK25: Y
A26: 339 | B26: {=IFNA(XLOOKUP(A26,'New Signups'!C:C,'New Signups'!D:D),"-")} -> Colton | C26: {=IFNA(XLOOKUP(A26,'New Signups'!C:C,'New Signups'!E:E),"-")} -> Tekimang | D26: 1021 | E26: 1 | F26: 1 | G26: 45263 | H26: Zweben | I26: good session | J26: Y | M26: 45270 | N26: Murray/Zweben | O26: Could not get through foraging. Moved A LOT with countless reminders not to move. When taking him out of the scanner his head was longer up against the cushions, and his shoulders were not touching the head coil like they should. | P26: Y | Q26: Y | R26: Y | U26: 45762 | V26: Samra | X26: No notes, good session | Y26: Y | Z26: Y | AC26: 45765 | AD26: Avi | AE26: Brooke | AH26: He had a headache and wanted to leave. Skipped GNG and DTI | AI26: Y | AJ26: Y | AK26: Y
A27: 393 | B27: {=IFNA(XLOOKUP(A27,'New Signups'!C:C,'New Signups'!D:D),"-")} -> Hai-Dinh | C27: {=IFNA(XLOOKUP(A27,'New Signups'!C:C,'New Signups'!E:E),"-")} -> Ballock | D27: 1019 | E27: 1 | F27: 1 | G27: 45248 | H27: Murray | I27: great Participant definately took the time to understand the survey and provide us with a thoughtful response.Did not like how long the surveys were, and was very concerned when the survey would "skip" parts of the survey based one of his prior answers (i.e. doesn't own a smartphone). Very inquisitive | J27: Y | M27: 45304 | N27: Murray/Zweben | O27: Good scan no issues easy kid, smart and quiet | P27: Y | Q27: Y | R27: Y | U27: 45833 | V27: Andrew | X27: no notes good session | Y27: y | Z27: y | AC27: 45854 | AD27: Avi | AE27: Kirsten | AF27: Lina | AG27: Ife | AH27: He got up before GNG; we ran the short T1 (some internal self-tests and calibrations were skipped for PAT) | AJ27: Y | AK27: Y
A28: 395 | B28: {=IFNA(XLOOKUP(A28,'New Signups'!C:C,'New Signups'!D:D),"-")} -> Amaya | C28: {=IFNA(XLOOKUP(A28,'New Signups'!C:C,'New Signups'!E:E),"-")} -> Mestre | D28: 1020 | E28: 1 | F28: 1 | G28: 45258 | H28: Murray | I28: ANT was a complete disaster, she would just click to click, missed a TON of trials, ran out of the room in the middle of the task but came right back (missed about 4 trials in her tome away from computer). Kept wanting to walk around or see her mom, but all of the servey and the games were completed | J28: Y | M28: 45272 | N28: Murray | O28: ONLY BEHAVIORAL | P28: NA | Q28: Y | R28: Y | AC28: 45777 | AD28: Avi | AE28: Jay | AH28: V2 happened before the V1 | AI28: Y | AJ28: Y | AK28: Y
A29: 507 | B29: {=IFNA(XLOOKUP(A29,'New Signups'!C:C,'New Signups'!D:D),"-")} -> Nashali | C29: {=IFNA(XLOOKUP(A29,'New Signups'!C:C,'New Signups'!E:E),"-")} -> Ortiz-Rivera | D29: 1022 | E29: 1 | F29: 1 | G29: 45318 | H29: Jay | I29: obtain screen time data in V2 | J29: Y | M29: 45092 | N29: Murray/Zweben | O29: Had to run localizer/field maps again before GNG (otherwise good scan) | P29: Y | Q29: Y | R29: Y | U29: 45970 | V29: Rae | X29: Spotlight froze when exiting the game. good session | Y29: Y | Z29: Y | AC29: 45970 | AD29: Kirsten | AE29: Megan | AF29: Rae | AG29: Avi | AH29: fell asleep - couldnt run much (just got PAT and DD alone) | AI29: y | AJ29: Y | AK29: Y
A30: 508 | B30: {=IFNA(XLOOKUP(A30,'New Signups'!C:C,'New Signups'!D:D),"-")} -> Anthony | C30: {=IFNA(XLOOKUP(A30,'New Signups'!C:C,'New Signups'!E:E),"-")} -> Ortiz-Rivera Jr | D30: 1023 | E30: 1 | F30: 1 | G30: 45318 | H30: Zweben | I30: good session, good kid | J30: Y | M30: 45319 | N30: Murray/Zweben | O30: First round of go-no-go was pressing the yellow button instead of the blue button. Used the correct button for the folowing 3 blocks. | P30: Y | Q30: Y | R30: Y | U30: 45765 | V30: Avi | W30: Aashna | X30: No notes, good session | Y30: Y | Z30: Y | AC30: 45949 | AD30: Isabel | AE30: Kirsten | AH30: Had to take participant out to readjust glasses (still had trouble reading all of the hobbies) and rerun short T1. Participant key presses registering on MATLAB, but not registering on the game screen for PAT 1 (likely unusable). Fixed for PAT round 2! Had to skip GnG for time reasons (Participant 30 minutes late) but did do DTI | AI30: Y | AJ30: Y | AK30: Y
A31: 509 | B31: {=IFNA(XLOOKUP(A31,'New Signups'!C:C,'New Signups'!D:D),"-")} -> Noemi | C31: {=IFNA(XLOOKUP(A31,'New Signups'!C:C,'New Signups'!E:E),"-")} -> Ortiz-Rivera | D31: 1024 | E31: 1 | F31: 1 | G31: 45318 | H31: Murray | I31: Good kid, did not have phoen with her to fill out that section of the survey | J31: Y | M31: 45338 | N31: Zweben/Riya | O31: GNG crashed and ould not run | P31: Y | Q31: Y | R31: Y | U31: 45765 | V31: Danny | X31: No notes, good session | Y31: Y | Z31: Y | AC31: 45935 | AD31: Kirsten | AE31: Megan | AH31: Psychopy crashed in the middle of the first gng round - skipped it and didnt dd social because it still is not working
A32: 510 | B32: {=IFNA(XLOOKUP(A32,'New Signups'!C:C,'New Signups'!D:D),"-")} -> Amina | C32: {=IFNA(XLOOKUP(A32,'New Signups'!C:C,'New Signups'!E:E),"-")} -> Ortiz-Rivera | D32: 1025 | E32: 1 | F32: 1 | G32: 45318 | H32: Murray | I32: good session, good kid | J32: Y | M32: 45338 | N32: Murray/Vince | O32: no notes good session | P32: Y | Q32: Y | R32: Y | U32: 45765 | V32: Danny | X32: No notes, good session | Y32: Y | Z32: Y | AC32: 45935 | AD32: Kirsten | AE32: Megan | AH32: started PAT 5 seconds left of first scan - did three participants and then stated second scan... took break midway of 1st gng session (did not look like she understood gng - low points even after explained twice) - cut dd social (confrmity task isnt working and time restrain) ran last field maps with movie
A33: 511 | B33: {=IFNA(XLOOKUP(A33,'New Signups'!C:C,'New Signups'!D:D),"-")} -> Keniel | C33: {=IFNA(XLOOKUP(A33,'New Signups'!C:C,'New Signups'!E:E),"-")} -> Ortiz-Rivera | D33: 1026 | E33: 1 | F33: 1 | G33: 45318 | H33: Murray | I33: good session, good kid | J33: Y | M33: 45319 | N33: Murray/Zweben | O33: Had to come out of scanner after block 2 of go-no-go to go to the bathroom | P33: Y | Q33: Y | R33: Y | U33: 45765 | V33: Aashna | X33: No notes, good session | Y33: Y | Z33: Y | AC33: 45949 | AD33: Isabel | AE33: Kirsten | AH33: Had to redo short T1 twice. First time because child needed one (1) sip of water right after full T1 and then again in the middle of PAT for bathroom. Finished run 2 of PAT with 2 minleft on scan. Didn't mention raffle for GnG. Participant didn't make responses for GoNGo2. Skipped DTI for time reasons (participants 30minutes late) | AI33: Y | AJ33: Y | AK33: Y
A34: 629 | B34: {=IFNA(XLOOKUP(A34,'New Signups'!C:C,'New Signups'!D:D),"-")} -> Alanzo | C34: {=IFNA(XLOOKUP(A34,'New Signups'!C:C,'New Signups'!E:E),"-")} -> Jones | D34: 1028 | E34: 1 | F34: 1 | G34: 45351 | H34: Riya | I34: got a little bored and impatient here and there but good session | J34: Y | U34: 45858 | V34: Aashna | X34: No Stoplight Task, afraid. | Y34: Y | Z34: Y
A35: 688 | B35: {=IFNA(XLOOKUP(A35,'New Signups'!C:C,'New Signups'!D:D),"-")} -> Ingrid | C35: {=IFNA(XLOOKUP(A35,'New Signups'!C:C,'New Signups'!E:E),"-")} -> yip | D35: 1029 | E35: 1 | F35: 1 | G35: 45368 | H35: Murray | I35: Awesome session! | J35: Y | M35: 45374 | N35: Murray/Megan | O35: great scan no issues | P35: Y | Q35: Y | R35: Y | U35: 45858 | V35: Avi | W35: Aashna | X35: No notes, good session | Y35: Y | Z35: Y | AC35: 45879 | AD35: Avi | AE35: Kirsten | AH35: She only made it through the first round of PAT. We got DTI and pulled her out | AI35: Y | AJ35: Y | AK35: Y
A36: 689 | B36: {=IFNA(XLOOKUP(A36,'New Signups'!C:C,'New Signups'!D:D),"-")} -> Ingvar | C36: {=IFNA(XLOOKUP(A36,'New Signups'!C:C,'New Signups'!E:E),"-")} -> Yip | D36: 1030 | E36: 1 | F36: 1 | G36: 45368 | H36: Danny | I36: He did great! Great kid :D | J36: Y | M36: 45374 | N36: Murray/Megan | O36: first block of go-no-go strated off a little rocky, he was a bit confused but then got the hang of it | P36: Y | Q36: Y | R36: Y | AC36: 45879 | AD36: Avi | AE36: Kirsten | AH36: He said he was dizzy and needed to take a break after the first round of GnG. We ran a short T1 and got another round and then he had to leave the scanner | AI36: Y | AJ36: Y | AK36: Y
A37: 704 | B37: {=IFNA(XLOOKUP(A37,'New Signups'!C:C,'New Signups'!D:D),"-")} -> Coyote | C37: {=IFNA(XLOOKUP(A37,'New Signups'!C:C,'New Signups'!E:E),"-")} -> Chatel | D37: 1027 | E37: 1 | F37: 1 | G37: 45350 | H37: Bowser | I37: good session, good kid | J37: Y
A38: 758 | B38: {=IFNA(XLOOKUP(A38,'New Signups'!C:C,'New Signups'!D:D),"-")} -> Tiana | C38: {=IFNA(XLOOKUP(A38,'New Signups'!C:C,'New Signups'!E:E),"-")} -> Davis | D38: 1031 | E38: 1 | F38: 1 | G38: 45383 | H38: Shulski | I38: Great job, burnt out at the end. Needs to do ShortANT | J38: Y | M38: 45384 | N38: Harry/Murray | O38: got a headache and came out of scanner in the middle of PAT block 2. Rest of scan not completed. | P38: Y | Q38: Y | R38: Y
A39: 772 | B39: {=IFNA(XLOOKUP(A39,'New Signups'!C:C,'New Signups'!D:D),"-")} -> Kennedy | C39: {=IFNA(XLOOKUP(A39,'New Signups'!C:C,'New Signups'!E:E),"-")} -> Player | D39: 1035 | E39: 1 | F39: 1 | G39: 45391 | H39: Murray | I39: need to reach out to obtain screen time data didn't bring phone to visit, so skipped the section of DES that asks for specific category use, etc. | J39: Y | M39: 45398 | N39: Harry/Murray | O39: had to take her out after PAT for a short break before starting go-no-go, | P39: Y | Q39: Y | R39: Y | U39: 45861 | V39: Andrew | X39: good session no notes | Y39: y | Z39: y | AC39: 45876 | AD39: Isabel | AE39: Camilla | AH39: Skipped DD_alone and DD_social due to technical issues (some internal self-tests and calibrations were skipped for PAT) | AI39: Y | AJ39: Y | AK39: Y
A40: 773 | B40: {=IFNA(XLOOKUP(A40,'New Signups'!C:C,'New Signups'!D:D),"-")} -> Suhaylah | C40: {=IFNA(XLOOKUP(A40,'New Signups'!C:C,'New Signups'!E:E),"-")} -> Andino | D40: 1036 | E40: 1 | F40: 1 | G40: 45392 | H40: Danny | I40: Tired and took some breaks - bit did really well. | J40: Y | M40: 45411 | N40: Harry/Murray | O40: no DTI, squeezed the squeeze ball | P40: Y | Q40: Y | R40: Y | AC40: 45862 | AD40: Megan | AE40: Binh | AH40: (some internal self-tests and calibrations were skipped for PAT) | AI40: Y | AJ40: Y | AK40: Y
A41: 774 | B41: {=IFNA(XLOOKUP(A41,'New Signups'!C:C,'New Signups'!D:D),"-")} -> Khyjair | C41: {=IFNA(XLOOKUP(A41,'New Signups'!C:C,'New Signups'!E:E),"-")} -> Tripline Reed | D41: 1032 | E41: 1 | F41: 1 | G41: 45387 | H41: Murray | I41: phone was not working so could not get phone use and screentime information | J41: Y | M41: 45388 | N41: Harry/Murray | O41: wasn't feeling very well in the scanner. Came out in the middle of T1 but went back in. We started scan over completely. After block two of go-no-go he could not do any more he was feeling worse. He did complete all of the behavioral tasks. | P41: Y | Q41: Y | R41: Y | U41: 45856 | V41: Andrew | X41: distracted but good | Y41: y | Z41: y | AC41: 45859 | AD41: Kirsten | AE41: Megan | AF41: Avi | AH41: good session (some internal self-tests and calibrations were skipped for PAT) | AI41: Y | AJ41: Y | AK41: Y
A42: 781 | B42: {=IFNA(XLOOKUP(A42,'New Signups'!C:C,'New Signups'!D:D),"-")} -> Jevar | C42: {=IFNA(XLOOKUP(A42,'New Signups'!C:C,'New Signups'!E:E),"-")} -> Gilbert | D42: 1033 | E42: 1 | G42: 45390 | H42: Shulski | I42: Had to readjust him to focus quite often, easily bored throughout visit; Struggled alot during shortant, uberball not complete | J42: Y | M42: 45391 | N42: Harry/Murray | O42: had to come out to use the bathroom after PAT block one. There were an excessive amount of go-no-go files, all are uploaded to onedrive. Go-no-go crashed at the beginning of block one, so reopened it and ran through smoothly. He fell asleep during the last blcok of go-no-go through DTI | P42: Y | Q42: Y | R42: Y
A43: 782 | B43: {=IFNA(XLOOKUP(A43,'New Signups'!C:C,'New Signups'!D:D),"-")} -> Jaiden | C43: {=IFNA(XLOOKUP(A43,'New Signups'!C:C,'New Signups'!E:E),"-")} -> Harris | D43: 1034 | E43: 1 | G43: 45390 | H43: Samra/Camilla | I43: No notes; good session | J43: Y | M43: 45391 | N43: Harry/Jay | O43: emergency squeeze ball during T1 because she was anxious about scanner noises, DIDN'T FINISH DTI (had 2 minutes left) | P43: Y | Q43: Y | R43: Y
A44: 851 | B44: {=IFNA(XLOOKUP(A44,'New Signups'!C:C,'New Signups'!D:D),"-")} -> Kiley | C44: {=IFNA(XLOOKUP(A44,'New Signups'!C:C,'New Signups'!E:E),"-")} -> Strauss | D44: 1037 | E44: 1 | F44: 1 | G44: 45414 | H44: Jay/Camilla | I44: obtain screen time data in V2; | J44: Y | M44: 45422 | N44: Danny | O44: little bit of movement during t1, did okay | P44: Y | Q44: Y | R44: Y | U44: 45897 | V44: Abby | X44: did not complete ub, sa, god due to license issue | Y44: y | Z44: y | AC44: 45910 | AD44: Kirsten | AE44: Binh | AH44: good session | AI44: Y | AJ44: Y | AK44: Y
A45: 863 | B45: {=IFNA(XLOOKUP(A45,'New Signups'!C:C,'New Signups'!D:D),"-")} -> Liam | C45: {=IFNA(XLOOKUP(A45,'New Signups'!C:C,'New Signups'!E:E),"-")} -> Williams | D45: 1041 | E45: 1 | F45: 1 | G45: 45428 | H45: Danny | I45: great kid, good session | J45: Y | M45: 45449 | N45: Danny | O45: great scan no issues | P45: Y | Q45: Y | R45: Y
A46: 876 | B46: {=IFNA(XLOOKUP(A46,'New Signups'!C:C,'New Signups'!D:D),"-")} -> Anabel | C46: {=IFNA(XLOOKUP(A46,'New Signups'!C:C,'New Signups'!E:E),"-")} -> Robinson-Posey | D46: 1051 | E46: 1 | F46: 1 | G46: 45095 | H46: Samra/Danny | I46: good session, no notes | J46: Y | M46: 45470 | N46: Danny/Avi | O46: Cried a lot had a tough time,didn't get to DTI | P46: Y | Q46: Y | R46: Y | U46: 45943 | V46: Kirsten | X46: included phone games as part of VGF; she is 12 and education survey only offered highschool and college | Y46: Y | Z46: Y | AC46: 45966 | AD46: Avi | AE46: Kirsten | AH46: Skipped DD alone
A47: 887 | B47: {=IFNA(XLOOKUP(A47,'New Signups'!C:C,'New Signups'!D:D),"-")} -> Sydney | C47: {=IFNA(XLOOKUP(A47,'New Signups'!C:C,'New Signups'!E:E),"-")} -> Hollaway | D47: 1038 | E47: 1 | F47: 1 | G47: 45419 | H47: Samra/Camilla | I47: good session | J47: Y | M47: 45426 | N47: Danny | O47: great scan no issues | P47: Y | Q47: Y | R47: Y | U47: 45893 | V47: Kirsten | X47: good session, no notes | Y47: Y | Z47: Y | AC47: 45900 | AD47: Kirsten | AE47: Megan | AH47: She was a uncomfortable in the scanner (4/3 out of 10) but she was able to complete the scan. Also, externally it was changed but internally, need to add .2 for dd alone and social files. | AI47: Y | AJ47: Y | AK47: Y
A48: 888 | B48: {=IFNA(XLOOKUP(A48,'New Signups'!C:C,'New Signups'!D:D),"-")} -> Kendall | C48: {=IFNA(XLOOKUP(A48,'New Signups'!C:C,'New Signups'!E:E),"-")} -> Hollaway | D48: 1039 | E48: 1 | F48: 1 | G48: 45419 | H48: Camilla/Samra | I48: good session. | J48: Y | M48: 45426 | N48: Danny | O48: little bit of movement during t1, did okay | P48: Y | Q48: Y | R48: Y | U48: 45894 | V48: Binh | X48: good session | Y48: Y | Z48: Y | AC48: 45901 | AD48: Kirsten | AE48: Megan | AH48: no notes, good session | AI48: y | AJ48: y
A49: 902 | B49: {=IFNA(XLOOKUP(A49,'New Signups'!C:C,'New Signups'!D:D),"-")} -> Kiara | C49: {=IFNA(XLOOKUP(A49,'New Signups'!C:C,'New Signups'!E:E),"-")} -> Rideout | D49: 1040 | E49: 1 | F49: 1 | G49: 45422 | H49: Camilia/Samra | I49: needs to bring phone next time | J49: Y
A50: 905 | B50: {=IFNA(XLOOKUP(A50,'New Signups'!C:C,'New Signups'!D:D),"-")} -> Camryn | C50: {=IFNA(XLOOKUP(A50,'New Signups'!C:C,'New Signups'!E:E),"-")} -> Grant | D50: 1046 | E50: 1 | F50: 1 | G50: 45442 | H50: Danny | I50: very young, needed a lot of breaks. But he did great! | J50: Y | M50: 45443 | N50: Danny/Harry | O50: Fell asleep midway through pat round 1 and couldn't continue | P50: Y | Q50: Y | R50: Y | U50: 45897 | V50: Maia | X50: okay session, forgot to wrote .2 in the first survey portion, inquisitive did not run because license expired for game of dice,short ant, pat task. He got tired but overall did well | Y50: Y | Z50: Y | AC50: 45567 | AD50: Avi | AE50: Shenghan | AH50: he got out before the first run of PAT, fell asleep so we skipped to DTI. AP field map wouldn't run at first so we had to copy it to run it. | AI50: Y | AJ50: Y | AK50: Y
A51: 915 | B51: Orla | C51: {=IFNA(XLOOKUP(A51,'New Signups'!C:C,'New Signups'!E:E),"-")} -> Dever | D51: 1074 | E51: 1 | F51: 1 | G51: 45542 | H51: Murray | I51: no notes, great session, great kid | J51: Y | M51: 45640 | N51: Danny/Zweben | O51: no notes good session | P51: Y | Q51: Y | R51: Y | U51: 46111 | V51: Emily | X51: good session, no notes | Y51: Y | AC51: 46112 | AD51: Isabel | AE51: Andrew | AH51: Good Session. No notes. | AI51: Y | AJ51: y | AK51: Y
A52: 923 | B52: {=IFNA(XLOOKUP(A52,'New Signups'!C:C,'New Signups'!D:D),"-")} -> Mia | C52: {=IFNA(XLOOKUP(A52,'New Signups'!C:C,'New Signups'!E:E),"-")} -> Day Hilton | D52: 1048 | E52: 1 | F52: 1 | G52: 45451 | H52: Danny Z/Danny H | I52: good session, | J52: Y | M52: 45458 | N52: Danny/Avi | O52: Had some difficulty seeing the icons in PAT, otherwise did great | P52: Y | Q52: Y | R52: Y | U52: 45922 | V52: Avi | X52: good session, I forgot to get digital receipt, so I sent it via openphone. she didn't know her addresses so I skipped urbanicity. It will come up in the survey queue when the do at-homes | Y52: Y | Z52: Y | AC52: 45939 | AD52: Avi | AE52: Megan | AH52: left due to headache. skipped GnG. | AI52: Y | AJ52: Y | AK52: Y
A53: 935 | B53: Christian | C53: Sims | D53: 1044 | E53: 1 | F53: 1 | G53: 45441 | H53: Camilla | I53: couldn't handle mock scanner | J53: Y | M53: 45445 | N53: Murray. | O53: had metal that wasn't able to be located but was setting off ferrogaurd | P53: NA | Q53: Y | R53: Y | U53: 45924 | V53: Kirsten | X53: ? | Y53: Y | Z53: Y | AC53: 45939 | AD53: Isabel | AE53: Maia | AH53: Had to take out after ddalone | AI53: Y (only localizer) | AJ53: Y | AK53: Y
A54: 940 | B54: {=IFNA(XLOOKUP(A54,'New Signups'!C:C,'New Signups'!D:D),"-")} -> sydney | C54: {=IFNA(XLOOKUP(A54,'New Signups'!C:C,'New Signups'!E:E),"-")} -> Houston | D54: 1042 | E54: 1 | F54: 1 | G54: 45440 | H54: Murray | I54: couldn't handle mock scanner | J54: Y | M54: 45447 | N54: Danny | O54: ONLY BEHAVIORAL | P54: NA | Q54: Y | R54: Y
A55: 950 | B55: {=IFNA(XLOOKUP(A55,'New Signups'!C:C,'New Signups'!D:D),"-")} -> Zuri | C55: {=IFNA(XLOOKUP(A55,'New Signups'!C:C,'New Signups'!E:E),"-")} -> Carroll-Johnson | D55: 1045 | E55: 1 | F55: 1 | G55: 45442 | H55: Murray | I55: did not have screentime setup, has her own smartphone (I phone)~ she didn't even know what to estimate/guess so did not answer those sections | J55: Y | M55: 45462 | N55: Murray/Avi | O55: had to take out of scanner for bathroom break between PAT and go-no-go, did not run DTI sequence | P55: Y | Q55: Y | R55: Y
A56: 952 | B56: {=IFNA(XLOOKUP(A56,'New Signups'!C:C,'New Signups'!D:D),"-")} -> Avery | C56: {=IFNA(XLOOKUP(A56,'New Signups'!C:C,'New Signups'!E:E),"-")} -> Ostroff | D56: 1043 | E56: 1 | F56: 1 | G56: 45440 | H56: Danny | I56: couldn't handle mock scanner | J56: Y | M56: 45450 | N56: Murray | O56: ONLY BEHAVIORAL | P56: NA | Q56: Y | R56: Y
A57: 968 | B57: {=IFNA(XLOOKUP(A57,'New Signups'!C:C,'New Signups'!D:D),"-")} -> Ailea | C57: {=IFNA(XLOOKUP(A57,'New Signups'!C:C,'New Signups'!E:E),"-")} -> Jackson | D57: 1047 | E57: 1 | F57: 1 | G57: 45443 | H57: Shulski | I57: good p, but very tired during visit (shortant v hard for her). does not have her own smartphone | J57: Y | M57: 45453 | N57: Danny/Avi | O57: Fell asleep during GNG - GNG data unsable, otherwise good scan. | P57: Y | Q57: Y | R57: Y | AC57: 46000 | AD57: Lina | AE57: Megan | AF57: Abby | AH57: reran t1 three times - first time participant was moving a ton (no volume on movie so wanted to get our attention) second time participant was moving a lot - T1 not usable after ran three times - took participant out and she did not want to continue
A58: 975 | B58: {=IFNA(XLOOKUP(A58,'New Signups'!C:C,'New Signups'!D:D),"-")} -> Caitlyn | C58: {=IFNA(XLOOKUP(A58,'New Signups'!C:C,'New Signups'!E:E),"-")} -> Moran | D58: 1050 | E58: 1 | F58: 1 | G58: 45456 | H58: Shulski, Binh | I58: good session, does not have screen time set up (ignore that session) set it up today reach out in a week to fill it in | J58: Y | M58: 45463 | N58: 2 | O58: no notes | P58: Y | Q58: Y | R58: Y | U58: 45925 | V58: Rae | X58: good session, "education" on redcap survey was skipped by participant because the options did not apply to her (she's in middle school and the options for her were high school or above) | Y58: Y | Z58: Y | AC58: 45938 | AD58: N | AE58: A | AH58: NO SCAN - Fear of MRI Machine
A59: 977 | B59: {=IFNA(XLOOKUP(A59,'New Signups'!C:C,'New Signups'!D:D),"-")} -> Si'Yor | C59: {=IFNA(XLOOKUP(A59,'New Signups'!C:C,'New Signups'!E:E),"-")} -> Rokins | D59: 1049 | E59: 1 | F59: 1 | G59: 45451 | H59: Vince | I59: good session, shortant was a little hard towards the end to stay on task | J59: Y | M59: 45467 | N59: Murray/Avi | O59: GNG block 4 started at the end of block 3 | P59: Y | Q59: Y | R59: Y
A60: 1065 | B60: {=IFNA(XLOOKUP(A60,'New Signups'!C:C,'New Signups'!D:D),"-")} -> Dominic | C60: {=IFNA(XLOOKUP(A60,'New Signups'!C:C,'New Signups'!E:E),"-")} -> Pugh | D60: 1066 | E60: 1 | F60: 1 | G60: 45495 | H60: Danny H | I60: great kid, good session | J60: Y | M60: 45495 | N60: Brooke/Murray | O60: nervous but did well | P60: Y | Q60: Y | R60: Y
A61: 1083 | B61: Jaziyah | C61: {=IFNA(XLOOKUP(A61,'New Signups'!C:C,'New Signups'!E:E),"-")} -> TAYLOR | D61: 1055 | E61: 1 | F61: 1 | G61: 45476 | H61: Murray | I61: no notes good session | J61: Y | M61: 45483 | N61: Danny/Brooke | O61: Couldn't make it to GNG and DTI, sleepy and fitgety. First T1 is SUPER blurry. Ran again, slightly better, still a lot of motion though | P61: Y | Q61: Y | R61: Y | U61: 45957 | V61: Sophie | AC61: 46169 | AD61: Avi | AE61: Andrew | AH61: DD alone had display settings issues. we had to skip it. First round of PAT: masked no go. | AJ61: y | AK61: y
A62: 1089 | B62: {=IFNA(XLOOKUP(A62,'New Signups'!C:C,'New Signups'!D:D),"-")} -> Christian | C62: {=IFNA(XLOOKUP(A62,'New Signups'!C:C,'New Signups'!E:E),"-")} -> Taylor | D62: 1052 | E62: 1 | F62: 1 | G62: 45471 | H62: Avi | I62: good session, forgot to do mock scan | J62: Y | M62: 45476 | N62: Danny/Brooke | O62: No DTI, ran out of time | P62: Y | Q62: Y | R62: Y | U62: 45957 | AC62: 46169 | AD62: Avi | AE62: Andrew | AH62: DD alone had display settings issues. we had to skip it | AJ62: y | AK62: y
A63: 1107 | B63: {=IFNA(XLOOKUP(A63,'New Signups'!C:C,'New Signups'!D:D),"-")} -> Jeremiah | C63: {=IFNA(XLOOKUP(A63,'New Signups'!C:C,'New Signups'!E:E),"-")} -> Conner | D63: 1056 | E63: 1 | G63: 45480 | H63: DannyZ | I63: No notes good session | J63: Y | M63: 45500 | N63: Murray/Megan | O63: behavioral only | P63: NA | Q63: Y | R63: Y | U63: 45965 | V63: Avi | AC63: 45965 | AD63: XX | AH63: has braces, no scan
A64: 1116 | B64: {=IFNA(XLOOKUP(A64,'New Signups'!C:C,'New Signups'!D:D),"-")} -> Zahon | C64: {=IFNA(XLOOKUP(A64,'New Signups'!C:C,'New Signups'!E:E),"-")} -> McDonald | D64: 1053 | E64: 1 | G64: 45476 | H64: Vince | I64: good session | J64: Y | M64: 45491 | N64: Murray/Avi | O64: squeezed emergency ball at beginning of t1 by accident, so we didn't have to take him out at all. had to take out to itch ear after gng block 2, localizer ran before later part of the scan | P64: Y | Q64: DD alone and DD social not working in testing room or operating room | R64: Y | U64: 45944 | V64: Ife | X64: Participant was upset and tired; parent disclosed that he has trouble reading after all the surveys were completed; QUIC-C overrode itself; he played Game of Dice six times; visit ran for nearly 3 hours | Y64: Y | Z64: Y | AC64: 45965 | AD64: Avi | AE64: Maia | AH64: Skipped dd alone and dd social because the task wasn't working. He had to take a break before PAT run 2. | AI64: Y | AJ64: Y | AK64: Y
A65: 1117 | B65: {=IFNA(XLOOKUP(A65,'New Signups'!C:C,'New Signups'!D:D),"-")} -> Zaaka | C65: {=IFNA(XLOOKUP(A65,'New Signups'!C:C,'New Signups'!E:E),"-")} -> McDonald | D65: 1054 | E65: 1 | G65: 45476 | H65: Avi | I65: good session | J65: Y | M65: 45491 | N65: Murray/Avi | O65: only got through first gng block and then couldn't do anymore | P65: Y | Q65: DD alone and DD social not working in testing room or operating room | R65: Y | U65: 45944 | V65: Maia | X65: Forgot to put .2 on first part of the surveys, Pat peers didn't run, portion of survey after break 3 refused to save(after urbanicity report), fell asleep during 2nd survey portion said he didn't get good sleep the night before | Y65: Y | Z65: Y | AC65: 45965 | AD65: Avi | AE65: Shenghan | AH65: late for 30 min. ddalone having difficulties duplicating so skipped, adjusted inflatable padding and reran localizer, PAT second run ended earlier by 25%, fell asleep in the middle of planetGoNoGo instruction. No attempt made on ddsocial bc in fear of the same problem | AI65: Y | AJ65: Y | AK65: Y
A66: 1121 | B66: {=IFNA(XLOOKUP(A66,'New Signups'!C:C,'New Signups'!D:D),"-")} -> faith | C66: {=IFNA(XLOOKUP(A66,'New Signups'!C:C,'New Signups'!E:E),"-")} -> Muhammad | D66: 1060 | E66: originally 1121 for v1.1 | F66: 1 | G66: 45489 | H66: Murray | I66: good session | J66: Y | M66: 45490 | N66: Murray | O66: Could not complete GNG rounds 3 and 4 did not complete DTI | P66: Y | Q66: Y | R66: Y | U66: 45960 | V66: Abby | X66: First survey did not save, so she had to retake it, not sure why. This made the session a little longer than usual. Needed some assistance/clarification here and there, but she is also only 10 lol. PAT was being weird and I'm not entirely sure the data for PAT saved properly. Great kid, overall good session. | Y66: y | Z66: y | AC66: 45970 | AD66: Avi | AE66: Kirsten | AF66: Megan | AH66: Midway through first Pat round wanted to be taken out... took a break and put her back in. | AI66: Y | AJ66: Y | AK66: Y
A67: 1126 | B67: {=IFNA(XLOOKUP(A67,'New Signups'!C:C,'New Signups'!D:D),"-")} -> Cynthia | C67: {=IFNA(XLOOKUP(A67,'New Signups'!C:C,'New Signups'!E:E),"-")} -> Sanchez | D67: 1061 | E67: 1 | F67: 1 | G67: 45489 | H67: DannyZ/Binh | I67: great kid, good session | J67: Y | M67: 45490 | N67: Danny | O67: no notes good session | P67: Y | Q67: Y | R67: Y
A68: 1129 | B68: {=IFNA(XLOOKUP(A68,'New Signups'!C:C,'New Signups'!D:D),"-")} -> Hendrix | C68: {=IFNA(XLOOKUP(A68,'New Signups'!C:C,'New Signups'!E:E),"-")} -> Carpenter | D68: 1058 | E68: originally 1129 for v1.1 | F68: 1 | G68: 45484 | H68: Shulski | I68: great kid, good session | J68: Y | M68: 45496 | N68: Danny/Murray | O68: reran field maps before pat, otherwise good visit | P68: Y | Q68: Y | R68: Y
A69: 1135 | B69: {=IFNA(XLOOKUP(A69,'New Signups'!C:C,'New Signups'!D:D),"-")} -> Justus | C69: {=IFNA(XLOOKUP(A69,'New Signups'!C:C,'New Signups'!E:E),"-")} -> Dixon | D69: 1059 | E69: 1 | F69: 1 | G69: 45484 | H69: DannyZ | I69: great kid, good session | J69: Y | M69: 45487 | N69: Murray | O69: lost interest in foraging task after a few trees and was not paying attention to the game even when directed to pay attention to the game. Moved during t1 making it fuzzy. During the first round of PAT he missed the beginning trials, and needed to be redirected to make selections. Missed a few trials during PAT block 2. Had to take P out after go-no-go block 2. Could not go back in scanner. No gng block 3 or 4. No DTI | P69: Y | Q69: Y | R69: Y | U69: 45958 | V69: Camilla | X69: Put session # as 1 instead of 2 for pat. Didn't complete pat peers. | Y69: y | Z69: Y | AC69: 45973 | AD69: Kirsten | AE69: Binh | AF69: Avi | AH69: he got out after GnG run 2 and got back in. we had to skip dd social | AI69: Y | AJ69: Y | AK69: Y
A70: 1146 | B70: {=IFNA(XLOOKUP(A70,'New Signups'!C:C,'New Signups'!D:D),"-")} -> Juniper | C70: {=IFNA(XLOOKUP(A70,'New Signups'!C:C,'New Signups'!E:E),"-")} -> Cates-Kozusko | D70: 1062 | E70: 1 | F70: 1 | G70: 45490 | H70: Murray | I70: great kid, good session | J70: Y | M70: 45497 | N70: Danny | O70: Couldn't do scan - noise bothered her. Stopped during T1 | P70: NA | Q70: Y | R70: Y | U70: 45968 | V70: Aashna | X70: Was getting bored but did everything | Y70: Y | Z70: Y | AC70: 45972 | AD70: Isabel | AE70: Megan | AH70: super scared... could not scan at all - Just got DD alone and Social data | AI70: N | AJ70: Y | AK70: Y
A71: 1147 | B71: Aashir | C71: Nelson | D71: 1057 | E71: 1 | F71: 1 | G71: 45483 | H71: DannyZ | I71: great kid, good session | J71: Y | M71: 45484 | N71: Danny/Avi | O71: good visit | P71: Y | Q71: Y | R71: Y | U71: 45954 | V71: Rae | X71: good session, no note | Y71: Y | Z71: Y | AC71: 45965 | AD71: Isabel | AE71: Megan | AH71: Issue with ddalone, had to skip. (GnG timing issue in round 1 | AI71: Y | AJ71: Y | AK71: Y
A72: 1180 | B72: {=IFNA(XLOOKUP(A72,'New Signups'!C:C,'New Signups'!D:D),"-")} -> Samuel | C72: {=IFNA(XLOOKUP(A72,'New Signups'!C:C,'New Signups'!E:E),"-")} | D72: 1068 | E72: 1 | F72: 1 | G72: 45511 | H72: Avi D | I72: Great kid, good session | J72: Y | M72: 45512 | N72: Harry/Murray | O72: a little antsy during gng block 2 through 4 | P72: Y | Q72: Y | R72: Y | U72: 46009 | V72: Abby | X72: quic survey repeated, otherwise good session | Y72: Y | Z72: Y | AC72: 46105 | AD72: Danny | AE72: Maia | AH72: had to go, did not do go/no go task | AJ72: Y | AK72: Y
A73: 1199 | B73: {=IFNA(XLOOKUP(A73,'New Signups'!C:C,'New Signups'!D:D),"-")} -> Valentina | C73: {=IFNA(XLOOKUP(A73,'New Signups'!C:C,'New Signups'!E:E),"-")} -> johnson | D73: 1067 | E73: 1 | F73: 1 | G73: 45499 | H73: Danny Z | I73: Great kid, good session | J73: Y | M73: 45520 | N73: Avi/Murray | O73: started PAT block 2 before block one scan was over. First block had approximately 45seconds left when block two began | P73: Y | Q73: Y | R73: Y | U73: 46052 | V73: Abby | W73: Anushka | X73: good session, couldn't transfer photo for PAT | Y73: Y | Z73: Y | AC73: 46094 | AD73: Avi | AF73: Megan | AH73: good session,anushka was there... | AI73: Y | AJ73: Y | AK73: Y
A74: 1207 | B74: {=IFNA(XLOOKUP(A74,'New Signups'!C:C,'New Signups'!D:D),"-")} -> Shiloh | C74: {=IFNA(XLOOKUP(A74,'New Signups'!C:C,'New Signups'!E:E),"-")} -> Watts | D74: 1063 | E74: 1 | F74: 1 | G74: 45494 | H74: Murray | I74: great kid, good session | J74: Y | M74: 45672 | N74: Avi/Danny | O74: Great Scan no issues | P74: Y | Q74: Y | R74: Y
A75: 1208 | B75: {=IFNA(XLOOKUP(A75,'New Signups'!C:C,'New Signups'!D:D),"-")} -> Isaiah | C75: {=IFNA(XLOOKUP(A75,'New Signups'!C:C,'New Signups'!E:E),"-")} -> Watts | D75: 1064 | E75: 1 | F75: 1 | G75: 45494 | H75: Danny Z | I75: cried for the rest of the visit after ending up in the negatives during game of dice lol, otherwise good session | J75: Y | M75: 45672 | N75: Avi/Danny | O75: Only got up to the end of pat, first t1 incomplete, use 2nd. | P75: Y | Q75: Y | R75: Y
A76: 1210 | B76: {=IFNA(XLOOKUP(A76,'New Signups'!C:C,'New Signups'!D:D),"-")} -> Ciana | C76: {=IFNA(XLOOKUP(A76,'New Signups'!C:C,'New Signups'!E:E),"-")} -> White | D76: 1065 | E76: 1 | F76: 1 | G76: 45496 | H76: Danny Z | I76: Great kid, good session | J76: Y | M76: 45502 | N76: Harry/Murray | O76: no notes | P76: Y | Q76: Y | R76: Y | U76: 45959 | V76: Binh | X76: first part of surveys were messed up so I couldn't automatically queue the surveys without deleting previous responses, participant is 11???? instead of 14???? I gave her QUIC insteaf of QUIC-C | Y76: Y | Z76: Y
A77: 1253 | B77: Joseph | C77: {=IFNA(XLOOKUP(A77,'New Signups'!C:C,'New Signups'!E:E),"-")} -> Wagner | D77: 1072 | E77: 1 | F77: 1 | G77: 45535 | H77: Danny Z | I77: Answered phone questions in regaurd to ipad | J77: Y | M77: 45633 | N77: Avi/Megan | O77: lots of movement, data probably unusable. re-ran the T1 and skipped Gn | P77: Y | Q77: Y | R77: Y
A78: 1264 | B78: Madeline | C78: {=IFNA(XLOOKUP(A78,'New Signups'!C:C,'New Signups'!E:E),"-")} -> Wagner | D78: 1073 | E78: 1 | F78: 1 | G78: 45535 | H78: Danny Z | I78: Answered phone questions in regaurd to ipad and use of parent smartphone | J78: Y | M78: 45633 | N78: Avi/Megan | O78: lots of movement, data probably unusable, re-ran T1. | P78: Y | Q78: Y | R78: Y
A79: 1356 | B79: Chaniel | C79: {=IFNA(XLOOKUP(A79,'New Signups'!C:C,'New Signups'!E:E),"-")} -> Rackley | D79: 1070 | E79: 1 | G79: 45531 | H79: Danny Z | I79: Great kid, good session | J79: Y | M79: 45551 | N79: Avi/Harry | O79: He seemed to be spamming random answers in PAT Kid squeezed the sqeeze ball in the middle of the second run og GnG. We restarted GnG from the beginning to get 2-4 GNG DIDNT SAVE. | P79: Y | Q79: Y | R79: Y
A80: 1377 | B80: Jake | C80: {=IFNA(XLOOKUP(A80,'New Signups'!C:C,'New Signups'!E:E),"-")} -> Haimes | D80: 1069 | E80: 1 | F80: 1 | G80: 45531 | H80: Danny Z | I80: Struggled a bit at times, ADHD | J80: Y | M80: 45543 | N80: Avi/Murray | O80: braces- Has a diagnosis of ASD and ADHD. Had a lot of energy but was good at staying still. Had to skip go-no-go. DD social data unsable - smamming random answers. | P80: Y | Q80: Y | R80: Y | U80: 46054 | V80: Rae | X80: skipped urbancy question | Y80: Y | Z80: Y | AC80: 46061 | AD80: Avi | AE80: Lina | AF80: Lina | AG80: Alicia | AH80: DD not working, had to skip GnG for time | AJ80: Y
A81: 1386 | B81: Jacob | C81: {=IFNA(XLOOKUP(A81,'New Signups'!C:C,'New Signups'!E:E),"-")} -> Blasucci | D81: 1078 | E81: 1 | F81: 1 | G81: 45549 | H81: Murray | I81: good session no notes | J81: Y | M81: 45563 | N81: Avi/Megan | O81: Good session no notes | P81: Y | Q81: Y | R81: Y
A82: 1393 | B82: Elias | C82: {=IFNA(XLOOKUP(A82,'New Signups'!C:C,'New Signups'!E:E),"-")} -> Waters | D82: 1071 | E82: 1 | F82: 1 | G82: 45533 | H82: Murray | I82: good session | J82: Y | M82: 45538 | N82: Avi/Murray | O82: moved a bit even when told to stay still | P82: Y | Q82: Y | R82: Y
A83: 1434 | B83: Kiss | C83: {=IFNA(XLOOKUP(A83,'New Signups'!C:C,'New Signups'!E:E),"-")} -> Jones | D83: 1075 | E83: 1 | F83: 1 | G83: 45547 | H83: Binh | I83: Participant didn't have phone with her, haven't finished PAT Peers, Short ANS, Uberball, survey PANAS-C to end | J83: Y | M83: 45558 | N83: Avi/Samra | O83: She fell asleep in the middle of PAT run 2. Then, halfway through GnG run 1 she squeezed the sqeeze ball and asked to go out. | P83: Y | Q83: Y | R83: Y
A84: 1440 | B84: Kaden | C84: {=IFNA(XLOOKUP(A84,'New Signups'!C:C,'New Signups'!E:E),"-")} -> Almodovar | D84: 1079 | E84: 1 | F84: 1 | G84: 45549 | H84: Danny | I84: did not bring phone to visit | J84: Y | M84: 45563 | N84: Avi/Megan | O84: His first T1 was abysmal. I re-ran the T1 and it was still pretty mid. We were short on time so we only did one run of GnG | P84: Y | Q84: Y | R84: Y | U84: 46041 | V84: Megan | X84: good session - did not consent to PAT photo | Y84: y | Z84: y | AC84: 46113 | AD84: Binh | AE84: Samra | AH84: Participant wanted to get out before T1, only foraging data available | AI84: X | AJ84: X
A86: 1442 | B86: Khamari | C86: {=IFNA(XLOOKUP(A86,'New Signups'!C:C,'New Signups'!E:E),"-")} -> Almodovar | D86: 1077 | E86: 1 | F86: 1 | G86: 45549 | H86: Murray | I86: did not bring phone to visit | J86: Y | M86: 45563 | N86: Avi/Megan | O86: GnG didn't save even though we were logged in on Megan's account | P86: Y | Q86: Y | R86: Y | U86: 46009 | V86: Megan | X86: Great kid and Quic repeated - only made him do it once | Y86: y | Z86: y | AC86: 46041 | AH86: Good session, no notes | AI86: Y | AJ86: Y | AK86: Y
A87: 1456 | B87: Eli | C87: Shuster-Bechelli | D87: 1098 | E87: 1 | F87: 1 | G87: 45580 | H87: Vince | I87: good session, did not have phone on him - also made clear he never had alcohol but the options did not allow for him to say he didn't (he already passed the section before I could tell him to just skip it if it doesn't have an option for none) | J87: Y | M87: 45601 | N87: Avi/Brooke/Sophie | O87: Was signed in as Danny, buy GnG still didn't save :I | P87: Y | Q87: Y | R87: Y | AH87: NO MRI !!!!!!!! - PARENT SAID CANT HANDLE IT 2/26/2026 | BA87: NO MRI !!!!!!!! - PARENT SAID CANT HANDLE IT 2/26/2026
A88: 1457 | B88: {=IFNA(XLOOKUP(A88,'New Signups'!C:C,'New Signups'!D:D),"-")} -> Oliver | C88: {=IFNA(XLOOKUP(A88,'New Signups'!C:C,'New Signups'!E:E),"-")} -> Nguyen | D88: 1080 | E88: 1 | F88: 1 | G88: 45550 | H88: Avi D | I88: no notes | J88: Y | M88: 45563 | N88: Avi/Megan | O88: Good session no notes | P88: Y | Q88: Y | R88: Y | U88: 45963 | V88: Kirsten | X88: good session no notes | Y88: Y | Z88: Y | AC88: 45970 | AH88: Good session, no notes | AI88: Y | AJ88: Y | AK88: Y
A89: 1462 | B89: {=IFNA(XLOOKUP(A89,'New Signups'!C:C,'New Signups'!D:D),"-")} -> Charlotte | C89: {=IFNA(XLOOKUP(A89,'New Signups'!C:C,'New Signups'!E:E),"-")} -> Creek | D89: 1112 | E89: 1 | F89: 1 | G89: 45603 | H89: Avi | I89: good session, no notes | J89: Y | M89: 45604 | N89: Avi/Harry | O89: She forgot which one to click on for GnG, we had to re-explain before run2 (discard run 1 | P89: Y | Q89: Y | R89: Y
A90: 1463 | B90: Skylar | C90: Sanchez | D90: 1099 | E90: 1 | F90: 1 | G90: 45584 | H90: Danny | I90: good session no notes | J90: Y | M90: 45612 | N90: Avi/Danny
A91: 1468 | B91: Lincoln | C91: Monahan | D91: 1113 | E91: 1 | F91: 1 | G91: 45604 | H91: Danny | I91: answered mtes questions for ipad | J91: Y | M91: 45604 | N91: Avi/Danny | O91: good session no notes | P91: Y | Q91: Y | R91: Y
A92: 1473 | B92: Zoey | C92: {=IFNA(XLOOKUP(A92,'New Signups'!C:C,'New Signups'!E:E),"-")} -> Castelo | D92: 1083 | E92: 1 | F92: 1 | G92: 45559 | H92: Binh | I92: no notes good session | J92: Y | M92: 45601 | N92: Danny/Avi | O92: good session | P92: Y | Q92: Y | R92: Y | U92: 46066 | V92: Anushka | X92: Good session, very fast- mom got at home survey during visit doesn't know which kid it's for? Rae set up the tasks and Anushka transfered the data. | Y92: Y | Z92: Y | AC92: 46101 | AD92: Danny | AE92: Megan | AF92: Rae | AH92: GNG went on for two rounds over the first scan -> scan finished before task | AI92: y | AJ92: y | AK92: y
A93: 1474 | B93: Javier | C93: {=IFNA(XLOOKUP(A93,'New Signups'!C:C,'New Signups'!E:E),"-")} -> Castelo | D93: 1084 | E93: 1 | F93: 1 | G93: 45559 | H93: Samra | I93: No notes; good session | J93: Y | M93: 45601 | N93: Avi/Danny | O93: We were running super overtime so we had to skip DTI, The 3rd round of GnG is fucked up, exclude it from analyses | P93: Y | Q93: Y | R93: Y | U93: 46066 | V93: Rae | W93: Alicia | X93: Good session but did not have time for Short Ant or Uberball (finished his last survey 2h in). | Y93: Y | Z93: Y | AC93: 46101 | AD93: Shenghan | AE93: Megan | AF93: Rae | AH93: GNG went on for three rounds over the end of the first scan; PAT photo had a black background; he wasnt really responding for PAT (too slow...? was responding? also he finished with 1.5 minutes for PAT and had to take him out after first round (felt really hot) -> dd social outside scanner -> dd alone and social name for PID was 2 (changed befiore transfer outside folder) | AI93: y | AJ93: y | AK93: y
A94: 1477 | B94: Eva | C94: Yakupova | D94: 1095 | E94: 1 | F94: 1 | G94: 45571 | H94: Murray | I94: good session no notes | J94: Y | M94: 45598 | N94: Danny | O94: no notes good session | P94: Y | Q94: Y | R94: Y
A95: 1484 | B95: Apolonia | C95: Tyczynska | D95: 1103 | E95: 1 | F95: 1 | G95: 45594 | H95: Samra/Kirsten | I95: good session, does not own phone | J95: Y | M95: 45629 | N95: Avi/Megan | O95: She had to leave to go to the bathroom before GnG run 3 and the scanner's isocenter function was broken so I couldn't get GnG runs 3-4 or DTI | P95: Y | Q95: Y | R95: Y | U95: 46101 | V95: Avi | X95: good session no notes | Y95: Y | Z95: Y | AC95: 46190 | AD95: Avi | AE95: Andrew | AH95: Great scan no notes - coolest 8 yr old ever | AI95: y | AJ95: y | AK95: y
A96: 1485 | B96: Kori | C96: {=IFNA(XLOOKUP(A96,'New Signups'!C:C,'New Signups'!E:E),"-")} -> Moultrie | D96: 1086 | E96: 1 | F96: 1 | G96: 45561 | H96: Vince | I96: did not bring phone to visit - struggled with shortant in the beginning of the practice and test | J96: Y | M96: 45617 | N96: Avi/Danny | O96: For foraging I accidentally put 1083 in instead of 1086 :I. Field map was fucked due to movement so we ran another one instead of DTI | P96: Y | Q96: Y | R96: Y
A97: 1489 | B97: {=IFNA(XLOOKUP(A97,'New Signups'!C:C,'New Signups'!D:D),"-")} -> Joshua | C97: {=IFNA(XLOOKUP(A97,'New Signups'!C:C,'New Signups'!E:E),"-")} -> Rubincan | D97: 1085 | E97: 1 | F97: 1 | G97: 45559 | H97: Avi | I97: No notes; good session | J97: ? | M97: 45558 | N97: Avi/Vince | O97: Sneezed during second round of PAT | P97: Y | Q97: Y | R97: Y | U97: 46090 | V97: Andrew | X97: good session no notes | Y97: y | Z97: y | AD97: Avi | AE97: Anushka | AF97: Maia | AG97: Anushka | AH97: Didn't scan, exapnder pinged for metal
A98: 1491 | B98: {=IFNA(XLOOKUP(A98,'New Signups'!C:C,'New Signups'!D:D),"-")} -> Levia | C98: {=IFNA(XLOOKUP(A98,'New Signups'!C:C,'New Signups'!E:E),"-")} -> Davis | D98: 1088 | E98: 1 | F98: 1 | G98: 45563 | H98: Avi | I98: good session no notes | J98: Y | M98: 45582 | N98: Murray/Binh | O98: good session | P98: Y | Q98: Y | R98: Y | U98: 46045 | V98: Sophie | W98: Alicia | X98: good session- need to put photo in one drive | Y98: Y | Z98: Y
A99: 1493 | B99: Mikayla | C99: Abdussamad | D99: 1100 | E99: 1 | F99: 1 | G99: 45586 | H99: Avi | I99: Good session, did not have phone with her. | J99: Y | M99: 45671 | N99: Avi/Danny | O99: Greart visit | P99: Y | Q99: Y | R99: Y
A100: 1496 | B100: Elijah | C100: Henderson | D100: 1091 | E100: 1 | F100: 1 | G100: 45563 | H100: Avi | I100: no notes good session | J100: Y | M100: 45598 | N100: Danny/Avi | O100: Good session | P100: Y | Q100: Y | R100: Y
A101: 1497 | B101: Serenity | C101: Nazario | D101: 1090 | E101: 1 | F101: 1 | G101: 45563 | H101: Murray | I101: was not engaged in any of the games, and did not wanrt to complete them. Data is likely unuable, specifically game of dice, and ANT. Non-compliant with surveys | J101: Y
A102: 1498 | B102: {=IFNA(XLOOKUP(A102,'New Signups'!C:C,'New Signups'!D:D),"-")} -> Kai | C102: {=IFNA(XLOOKUP(A102,'New Signups'!C:C,'New Signups'!E:E),"-")} -> Tran | D102: 1081 | E102: 1 | F102: 1 | G102: 45556 | H102: Avi D | I102: his mom wanted to be in the room. I let her at the start of the visit but kicked her out after stoplight. | J102: Y | M102: 45622 | N102: Danny/Avi | O102: Good Session no notes | P102: Y | Q102: Y | R102: Y | U102: 46074 | V102: Anushka
...

Sheet 2000
A1: 2-98
B2: participant dropped out of the study or stopped responding
B3: unsusable data
B4: Excused no-show/partial visit | G4: VISIT 1 | M4: VISIT 2 | U4: Wave 2 VISIT 1 | AC4: Wave 2 VISIT 2 | AM4: Wave 3 Visit 1 | AU4: Wave 3 Visit 2
B5: Completed visit
B6: No Mri Moving Forward
A7: Record ID | B7: First name | C7: Last name | D7: PID | E7: Changed in REDCap | G7: Date | H7: RAs | I7: Notes | J7: Data transferred? | M7: Date | N7: RAs | O7: Notes | P7: X-NAT data | Q7: Behavioral data | R7: Compensation? | U7: Date | V7: RA | W7: Shadow RA | X7: Notes | Y7: Data transferred? | Z7: Compensation? | AC7: Date | AD7: L3 RA | AE7: L2 RA | AF7: Shadow 1 | AG7: Shadow 2 | AH7: Notes | AI7: X-NAT data | AJ7: Behavioral data | AK7: Compensation? | AM7: Date | AN7: RA | AO7: Shadow RA | AP7: Notes | AQ7: Behavioral data | AR7: Compensation? | AU7: Date | AV7: L3 | AW7: L2 | AX7: Shadow 1 | AY7: Shadow 2 | AZ7: Notes | BA7: X-NAT data | BB7: Behavioral data | BC7: Compensation?
A8: 18 | B8: {=IFNA(XLOOKUP(A8,'New Signups'!C:C,'New Signups'!D:D),"-")} -> Amaijah | C8: {=IFNA(XLOOKUP(A8,'New Signups'!C:C,'New Signups'!E:E),"-")} -> Coates** | D8: 2001 | E8: 1 | F8: 1 | G8: 44960 | H8: Murray/Bishop | I8: No notes; good session | J8: Y | M8: 45019 | N8: Skalaban/King | O8: Name pronounced "uh-MAH-jah"; has done two Temple MRI studies before; has done the old version of Chatroom | P8: Y | Q8: Y | R8: Y
A9: 10 | B9: {=IFNA(XLOOKUP(A9,'New Signups'!C:C,'New Signups'!D:D),"-")} -> Jahvon | C9: {=IFNA(XLOOKUP(A9,'New Signups'!C:C,'New Signups'!E:E),"-")} -> Brown** | D9: 2002 | E9: 1 | G9: 44960 | H9: Wyatt/King | I9: No notes; good session | J9: Y | M9: 45021 | N9: Skalaban/King | O9: Has done two Temple MRI studies before; has done the old version of Chatroom | P9: Y | Q9: Y | R9: Y
A10: 23 | B10: {=IFNA(XLOOKUP(A10,'New Signups'!C:C,'New Signups'!D:D),"-")} -> Aidan | C10: Peterson | D10: 2003 | E10: 1 | F10: 1 | G10: 44966 | H10: King | I10: No notes; good session | J10: Y | M10: 44995 | N10: Skalaban/King | O10: Is also a RISE participant, in second year. Chatroom wasn't working so we do not have scan data for that | P10: Y | Q10: y | R10: Y | U10: 45666 | V10: Danny | X10: good session, no notes | Y10: Y | Z10: Y | AC10: 45666 | AD10: Danny | AE10: Avi | AH10: No Notes | AI10: Y | AJ10: Y | AK10: Y
A11: 22 | B11: Jason | C11: Mckenzie | D11: 2004 | E11: 1 | G11: 44975 | H11: King | I11: Easily distracted, but made an effort | J11: Y | M11: 45017 | N11: Skalaban/King | O11: Non-compliant; had to come out of MRI multiple times, would not participate. Pulled out of scanner after Chatroom task | P11: Y | Q11: Y | R11: Y | U11: 45875
A12: 13 | B12: {=IFNA(XLOOKUP(A12,'New Signups'!C:C,'New Signups'!D:D),"-")} -> Elliott | C12: {=IFNA(XLOOKUP(A12,'New Signups'!C:C,'New Signups'!E:E),"-")} -> Clair | D12: 2005 | E12: 1 | F12: 1 | G12: 44977 | H12: King | I12: No notes; good session | J12: Y | M12: 45014 | N12: Skalaban/King | O12: P did not receive feedback during Chatroom, was confused during Go No Go | P12: Y | Q12: Y | R12: Y | U12: 45643 | V12: Avi | X12: good session, no notes | Y12: Y | Z12: Y | AC12: 45657 | AD12: Danny | AE12: Avi | AH12: No notes | AI12: Y | AJ12: Y | AK12: Y
A13: 48 | B13: {=IFNA(XLOOKUP(A13,'New Signups'!C:C,'New Signups'!D:D),"-")} -> Vrishab | C13: {=IFNA(XLOOKUP(A13,'New Signups'!C:C,'New Signups'!E:E),"-")} -> Kaushik | D13: 2006 | E13: 1 | F13: 1 | G13: 45037 | H13: Murray | I13: No notes; good session | J13: Y | M13: 45049 | N13: Skalaban/King | O13: Vrishab got confused with the break screens and told us he had surpassed break 1 and 2 by accident. So, we did the stoplight and game of dice tasks a bit too early. Otherwise, all went smoothly and he was good at following directions | P13: Y | Q13: Y | R13: Y | U13: 45675 | V13: Danny | X13: good session, no notes | Y13: Y | Z13: Y | AC13: 45682 | AD13: Danny | AE13: Avi | AH13: No notes | AI13: Y | AJ13: Y | AK13: Y
A14: 117 | B14: {=IFNA(XLOOKUP(A14,'New Signups'!C:C,'New Signups'!D:D),"-")} -> Hajr | C14: {=IFNA(XLOOKUP(A14,'New Signups'!C:C,'New Signups'!E:E),"-")} -> Davis* | D14: 2007 | E14: 1 | F14: 1 | G14: 45085 | H14: Murray | I14: did not do peer run social feedback because we were not ready to run it should do at visit two | J14: Y | M14: 45091 | N14: Skalaban/King | O14: Participant moved a lot during the functional scans, especially last run of PAT. The alignment was not placed well, and some parts of the cerebellum was cut. | P14: Y | Q14: Y | R14: Y
A15: 126 | B15: Ben | C15: Braus | D15: 2008 | E15: 1 | G15: 45092 | H15: Murray | I15: Participant flew through the survey, did it so fast but was definately reading it and answering accordingly. Even gave info in the boxes we provide, but still concerning how fast he completed the visit. Browser closed after the RPI survey but data was saved (so it appears in red cap) and got it back up and running smoothely. Participant has had MRI's in the past with us, was frustrated he had to do the mock scan. | J15: Y
A16: 170 | B16: {=IFNA(XLOOKUP(A16,'New Signups'!C:C,'New Signups'!D:D),"-")} -> Jude | C16: {=IFNA(XLOOKUP(A16,'New Signups'!C:C,'New Signups'!E:E),"-")} -> Becker | D16: 2009 | E16: 1 | F16: 1 | G16: 45160 | H16: King | I16: Good session, attentive, didn't need any breaks | J16: Y | M16: 45277 | N16: Murray/Jay | O16: good scan no issues | P16: Y | Q16: Y | U16: 45828 | V16: Binh | W16: Rae | X16: good session, no notes | Y16: Y | Z16: Y | AC16: 45849 | AD16: Megan | AE16: Avi
A17: 432 | B17: {=IFNA(XLOOKUP(A17,'New Signups'!C:C,'New Signups'!D:D),"-")} -> Athen | C17: {=IFNA(XLOOKUP(A17,'New Signups'!C:C,'New Signups'!E:E),"-")} -> Schaper | D17: 2010 | E17: 1 | F17: 1 | G17: 45297 | H17: Murray | I17: Settings on phone waas not showing the full report (could not access the weekly report or categories) so we used the daily average report for the weekly report questions and she took her best guess at the categories she thinks she uses most. Also could not access the number of pickups and notifactions. Had an 'older' version of the iphone. Great participant! Apologized fo not having all the phone information because she "didn't want to scew our data'. | J17: Y | M17: 45304 | N17: Murray/Zweben | O17: squeezed the ear pillow inflation part throughout the entirety of the scan. | P17: Y | Q17: Y | R17: Y
A18: 520 | B18: {=IFNA(XLOOKUP(A18,'New Signups'!C:C,'New Signups'!D:D),"-")} -> Nayeli | C18: {=IFNA(XLOOKUP(A18,'New Signups'!C:C,'New Signups'!E:E),"-")} -> Padilla | D18: 2011 | E18: 1 | F18: 1 | G18: 45297 | H18: Murray | I18: good session, no notes | J18: Y | M18: 45305 | N18: Murray/Zweben | O18: good scan no issues | P18: Y | Q18: Y | R18: Y | U18: 45829 | V18: Binh | W18: Rae | X18: good session, no notes | Y18: Y | Z18: Y | AC18: 45866 | AD18: Kirsten | AE18: Andrew | AH18: Used wave 1 PAT data (some internal self-tests and calibrations were skipped for PAT) | AI18: Y | AJ18: Y | AK18: Y
A19: 527 | B19: {=IFNA(XLOOKUP(A19,'New Signups'!C:C,'New Signups'!D:D),"-")} -> Rika | C19: {=IFNA(XLOOKUP(A19,'New Signups'!C:C,'New Signups'!E:E),"-")} -> Iijima | D19: 2012 | E19: 1 | F19: 1 | G19: 45311 | H19: Murray | I19: good session, no notes | J19: Y | M19: 45332 | N19: Murray/Vince | O19: good scan no issues | P19: Y | Q19: Y | R19: Y | U19: 45827 | V19: Megan | X19: good session, no notes | Y19: y | Z19: Y | AC19: 45858 | AD19: Avi | AE19: Lina | AF19: Ife | AH19: No Notes (some internal self-tests and calibrations were skipped for PAT) | AJ19: Y | AK19: Y
A20: 529 | B20: {=IFNA(XLOOKUP(A20,'New Signups'!C:C,'New Signups'!D:D),"-")} -> Tina | C20: {=IFNA(XLOOKUP(A20,'New Signups'!C:C,'New Signups'!E:E),"-")} -> Zheng | D20: 2013 | E20: 1 | F20: 1 | G20: 45323 | H20: Vince | I20: good session, no notes | J20: Y | M20: 45333 | N20: Murray/Vince | O20: good scan no issues, DD alone accidentally said she was 14 instead of 15 | P20: Y | Q20: Y | R20: Y | U20: 45857 | V20: Binh | X20: did not remember all addresses for urban youth questionnaire | AC20: 45862 | AD20: Megan | AE20: Andrew | AH20: (some internal self-tests and calibrations were skipped for PAT) | AI20: Y | AJ20: Y | AK20: Y
A21: 549 | B21: {=IFNA(XLOOKUP(A21,'New Signups'!C:C,'New Signups'!D:D),"-")} -> Ronald "Mackie" | C21: {=IFNA(XLOOKUP(A21,'New Signups'!C:C,'New Signups'!E:E),"-")} -> DenBroeder | D21: 2014 | E21: 1 | F21: 1 | G21: 45332 | H21: Vince | I21: good session, no notes | J21: Y | M21: 45346 | N21: Danny/Murray | O21: good scan no issues | P21: Y | Q21: Y | R21: Y | U21: 45882 | V21: Kirsten | X21: good session, no notes | Y21: Y | Z21: Y
A22: 632 | B22: {=IFNA(XLOOKUP(A22,'New Signups'!C:C,'New Signups'!D:D),"-")} -> Demani | C22: {=IFNA(XLOOKUP(A22,'New Signups'!C:C,'New Signups'!E:E),"-")} -> Bowen | D22: 2015 | E22: 1 | F22: 1 | G22: 45344 | H22: Shah | I22: good session, no notes | J22: Y | M22: 45369 | N22: Danny/Murray/Avi | O22: good scan | P22: Y | Q22: Y | R22: Y
A23: 679 | B23: {=IFNA(XLOOKUP(A23,'New Signups'!C:C,'New Signups'!D:D),"-")} -> Chelsea | C23: {=IFNA(XLOOKUP(A23,'New Signups'!C:C,'New Signups'!E:E),"-")} -> Painter | D23: 2016 | E23: 1 | F23: 1 | G23: 45347 | H23: Danny | I23: good session, no notes | J23: Y | M23: 45375 | N23: Danny/Hawk | O23: had to do DTI before GNG (made sure to do fieldmaps again) | P23: Y | Q23: Y | R23: Y | U23: 45845 | V23: Andrew | X23: didnt run PAT, license issue rest of session was good | Y23: y | Z23: y | AC23: 45863 | AD23: Kirsten | AE23: Andrew | AF23: Isabel | AH23: wave one pat used (no wave 2 v1 data for pat) other than that no notes good session (some internal self-tests and calibrations were skipped for PAT) | AI23: Y | AJ23: y | AK23: y
A24: 626 | B24: {=IFNA(XLOOKUP(A24,'New Signups'!C:C,'New Signups'!D:D),"-")} -> Eden | C24: {=IFNA(XLOOKUP(A24,'New Signups'!C:C,'New Signups'!E:E),"-")} -> Jones | D24: 2017 | E24: 1 | F24: 1 | G24: 45351 | H24: Murray | I24: good session, no notes | J24: Y | M24: 45357 | N24: Danny/Murray | O24: Planet gono go would shut down immediately after putting in the participant information. Game does not open/crashes. | P24: Y | Q24: Y | R24: Y
A25: 701 | B25: {=IFNA(XLOOKUP(A25,'New Signups'!C:C,'New Signups'!D:D),"-")} -> Karma | C25: {=IFNA(XLOOKUP(A25,'New Signups'!C:C,'New Signups'!E:E),"-")} -> Davis | D25: 2018 | E25: 1 | F25: 1 | G25: 45360 | H25: Danny | I25: good session, no notes | J25: Y | M25: 45375 | N25: Danny/Hawk | O25: good scan no issues | P25: Y | Q25: Y | R25: Y | AC25: 45874 | AD25: Isabel | AE25: Avi | AH25: GnG crashed in first round (1stripe instead of 1striped), but ran smoothly afterwards. | AI25: Y | AJ25: Y | AK25: Y
A26: 685 | B26: {=IFNA(XLOOKUP(A26,'New Signups'!C:C,'New Signups'!D:D),"-")} -> Catherine | C26: {=IFNA(XLOOKUP(A26,'New Signups'!C:C,'New Signups'!E:E),"-")} -> McKevitt | D26: 2019 | E26: 1 | F26: 1 | G26: 45361 | H26: Murray | I26: good session, no notes | J26: Y | M26: 45375 | N26: Danny/Hawk | O26: good scan no issues | P26: Y | Q26: Y | R26: Y | U26: 45866 | V26: Kirsten | X26: No note good session | AC26: 46118 | AD26: Megan | AE26: Camilla | AF26: Shenghan | AH26: Has Dexcom... cant scan it is ferros | AI26: N | AJ26: Y | AK26: Y
A27: 738 | B27: {=IFNA(XLOOKUP(A27,'New Signups'!C:C,'New Signups'!D:D),"-")} -> Myesha | C27: {=IFNA(XLOOKUP(A27,'New Signups'!C:C,'New Signups'!E:E),"-")} -> Gardner | D27: 2020 | E27: 1 | F27: 1 | G27: 45379 | H27: Vince | I27: good session, no notes | J27: Y | M27: 45385 | N27: Murray/Vince | O27: good scan no issues | P27: Y | Q27: Y | R27: Y | U27: 45854 | V27: Megan | X27: good session | Y27: y | Z27: y | AC27: 45859 | AD27: Kirsten | AE27: Megan | AH27: no notes (some internal self-tests and calibrations were skipped for PAT) | AI27: y | AJ27: y | AK27: y
A28: 658 | B28: {=IFNA(XLOOKUP(A28,'New Signups'!C:C,'New Signups'!D:D),"-")} -> Thomas | C28: {=IFNA(XLOOKUP(A28,'New Signups'!C:C,'New Signups'!E:E),"-")} -> Hylan | D28: 2022 | E28: 1 | F28: 1 | G28: 45380 | H28: Jay | I28: No screen time data | J28: Y | M28: 45385 | N28: Murray/Vince | O28: good scan no issues | U28: 45869 | V28: Binh | X28: good session | Y28: Y | Z28: Y | AC28: 45887 | AD28: Avi | AE28: Binh | AH28: good session | AI28: Y | AJ28: Y | AK28: Y
A29: 759 | B29: {=IFNA(XLOOKUP(A29,'New Signups'!C:C,'New Signups'!D:D),"-")} -> Jaidah | C29: {=IFNA(XLOOKUP(A29,'New Signups'!C:C,'New Signups'!E:E),"-")} -> Minnick | D29: 2023 | E29: 1 | F29: 1 | G29: 45383 | H29: Neil | I29: good session, couldn't handle scanner. | J29: Y | M29: 45384 | N29: Danny | O29: (behavioral only) good session no notes | P29: NA | Q29: Y | R29: Y
A30: 779 | B30: {=IFNA(XLOOKUP(A30,'New Signups'!C:C,'New Signups'!D:D),"-")} -> Emira | C30: {=IFNA(XLOOKUP(A30,'New Signups'!C:C,'New Signups'!E:E),"-")} -> Cheeks | D30: 2024 | E30: 1 | F30: 1 | G30: 45385 | H30: Shah | I30: good session, no notes | J30: Y | M30: 45395 | N30: Danny/Hawk | O30: Ran GnG, DTI , then PAT | P30: Y | Q30: Y | R30: Y | U30: 45867 | V30: Andrew | X30: good session no notes | Y30: y | Z30: y | AC30: 45877 | AD30: Kirsten | AE30: Lina | AH30: Have braces. Computer displays were messed up; we cut DDalone, DDsocial & GNG round 3+4; (GNG round 2 imaging data can not be collected due to a technical problem) (some internal self-tests and calibrations were skipped for PAT) | AI30: Y | AJ30: Y
A31: 787 | B31: {=IFNA(XLOOKUP(A31,'New Signups'!C:C,'New Signups'!D:D),"-")} -> Yusuf | C31: {=IFNA(XLOOKUP(A31,'New Signups'!C:C,'New Signups'!E:E),"-")} -> Devlin | D31: 2025 | E31: 1 | G31: 45390 | H31: Shah | I31: good session, no notes | J31: Y | M31: 45427 | N31: Danny/Avi | O31: GNG didn't save behavioral data | P31: Y | Q31: Y | R31: Y
A32: 807 | B32: {=IFNA(XLOOKUP(A32,'New Signups'!C:C,'New Signups'!D:D),"-")} -> Sayir | C32: {=IFNA(XLOOKUP(A32,'New Signups'!C:C,'New Signups'!E:E),"-")} -> Taylor | D32: 2026 | E32: 1 | F32: 1 | G32: 45394 | H32: Danny | I32: Has a phone but it is mostly broken - put NA for the screen time section | J32: Y | M32: 4/15/2024 | N32: Danny/Avi | O32: good scan no issues | P32: Y | Q32: Y | R32: Y | U32: 45863 | V32: Megan | X32: good session | AC32: 45901 | AD32: Kirsten | AE32: Avi | AH32: misnamed in XNAT; missed the 'P' | AJ32: Y | AK32: Y
A33: 793 | B33: {=IFNA(XLOOKUP(A33,'New Signups'!C:C,'New Signups'!D:D),"-")} -> Zahmyah | C33: {=IFNA(XLOOKUP(A33,'New Signups'!C:C,'New Signups'!E:E),"-")} -> Gresham | D33: 2027 | E33: 1 | F33: 1 | G33: 45394 | H33: Shah | I33: good session, no notes | J33: Y | M33: 45403 | N33: Danny/Kenzie | O33: good scan no issues | P33: Y | Q33: Y | R33: Y | U33: 45852 | V33: Andrew | X33: listened to music, good playlist good session, no notes | Y33: Y | Z33: y | AC33: 45875 | AD33: Avi | AE33: Binh | AF33: Kirsten | AH33: A lot of movement on the T1, Avi told her to be more still for the functional runs, Had to use Wave 1 PAT image (some internal self-tests and calibrations were skipped for PAT) | AI33: Y | AJ33: Y | AK33: Y
A34: 795 | B34: {=IFNA(XLOOKUP(A34,'New Signups'!C:C,'New Signups'!D:D),"-")} -> Zayden | C34: {=IFNA(XLOOKUP(A34,'New Signups'!C:C,'New Signups'!E:E),"-")} -> Gresham | D34: 2028 | E34: 1 | F34: 1 | G34: 45394 | H34: Kenzie | I34: No screen time data | J34: Y | M34: 45401 | N34: Murray/Brooke | O34: good scan no issues | P34: Y | Q34: Y | R34: Y | U34: 45852 | V34: Andrew | X34: good session no notes a little antsy really wanted to know what headphones were in 841 | Z34: y | AC34: 45888 | AD34: Isabel | AE34: Binh | AH34: Task ended with 2 minutes 30 seconds left on the scanner for PAT. | AI34: Y | AJ34: Y | AK34: Y
A35: 819 | B35: {=IFNA(XLOOKUP(A35,'New Signups'!C:C,'New Signups'!D:D),"-")} -> Ishmael | C35: {=IFNA(XLOOKUP(A35,'New Signups'!C:C,'New Signups'!E:E),"-")} -> Savadogo | D35: 2029 | E35: 1 | F35: 1 | G35: 45401 | H35: Kenzie/Murray | I35: session was good (was the mom that gave ash a little trouble on the phone right before visit) | J35: Y | M35: 45403 | N35: Danny/Kenzie | O35: good scan no issues | P35: Y | Q35: Y | R35: Y | U35: 45868 | V35: Ife | X35: Didin't complete urbanicity because he felt uncomfortable, skipped through the shortant rounds, and was generally unenthusiastic | Y35: Y | Z35: Y | AC35: 45890 | AD35: Avi | AE35: Isabel | AH35: PAT wasn't working, but we accidentally ran the PAT scan while playing the first round of GnG. We ended up getting all 4 rounds of GnG just fine, but there's PAT mri data that isn't real. | AI35: y | AJ35: y | AK35: y
A36: 821 | B36: {=IFNA(XLOOKUP(A36,'New Signups'!C:C,'New Signups'!D:D),"-")} -> Nakayla | C36: {=IFNA(XLOOKUP(A36,'New Signups'!C:C,'New Signups'!E:E),"-")} -> Perry | D36: 2030 | E36: 1 | F36: 1 | G36: 45403 | H36: Kenzie | I36: Session was good, had trouble finding building and were a bit annoyed | J36: Y | M36: 45410 | N36: Murray/Jay | O36: put in the wrong birth year (I entered 2013 but should have been 2010 | P36: Y | Q36: Y | R36: Y
A37: 843 | B37: {=IFNA(XLOOKUP(A37,'New Signups'!C:C,'New Signups'!D:D),"-")} -> Thomas | C37: {=IFNA(XLOOKUP(A37,'New Signups'!C:C,'New Signups'!E:E),"-")} -> Cirino | D37: 2031 | E37: 1 | F37: 1 | G37: 45412 | H37: Brooke | I37: good session, no notes | J37: Y | M37: 45485 | N37: Brooke/Murray | O37: no notes | P37: Y | Q37: Y | R37: Y
A38: 884 | B38: {=IFNA(XLOOKUP(A38,'New Signups'!C:C,'New Signups'!D:D),"-")} -> Micah | C38: {=IFNA(XLOOKUP(A38,'New Signups'!C:C,'New Signups'!E:E),"-")} -> Hollaway | D38: 2032 | E38: 1 | F38: 1 | G38: 5/7/2024 | H38: Danny | I38: good session, really attentive. Data not collected for PAT | J38: Y | M38: 45427 | N38: Lena/Avi | O38: good scan no issues | P38: Y | Q38: Y | R38: Y | U38: 45895 | V38: Binh | X38: good session | Y38: Y | Z38: Y | AC38: 45898 | AD38: Kirsten | AE38: Megan | AH38: No notes, good session | AI38: y | AJ38: y | AK38: y
A39: 867 | B39: {=IFNA(XLOOKUP(A39,'New Signups'!C:C,'New Signups'!D:D),"-")} -> Wren | C39: {=IFNA(XLOOKUP(A39,'New Signups'!C:C,'New Signups'!E:E),"-")} -> RuiFang Palombaro Lanza | D39: 2033 | E39: 1 | F39: 1 | G39: 45421 | H39: Danny | I39: good session | J39: Y | M39: 45432 | N39: Avi/Danny | O39: good scan no issues | P39: Y | Q39: Y | R39: Y | U39: 45904 | V39: Avi | W39: Binh | X39: Wrong PID for Game of Dice and Stoplight, Avi will fix it | Y39: Y | Z39: Y | AC39: 45923 | AD39: Avi | AE39: Isabel | AH39: TUBRIC computers updated, resulting in PAT and DDsocial not working; skipped. Foraging done after scan. | AI39: Y | AJ39: Y | AK39: Y
A40: 816 | B40: {=IFNA(XLOOKUP(A40,'New Signups'!C:C,'New Signups'!D:D),"-")} -> Najee | C40: {=IFNA(XLOOKUP(A40,'New Signups'!C:C,'New Signups'!E:E),"-")} -> Israel | D40: 2034 | E40: 1 | F40: 1 | G40: 45432 | H40: Avi | I40: good session, no notes | J40: Y | M40: 45435 | N40: Avi/Brooke | O40: good scan no issues | P40: Y | Q40: Y | R40: Y
A41: 869 | B41: {=IFNA(XLOOKUP(A41,'New Signups'!C:C,'New Signups'!D:D),"-")} -> Sherie | C41: {=IFNA(XLOOKUP(A41,'New Signups'!C:C,'New Signups'!E:E),"-")} -> Clark | D41: 2035 | E41: 1 | F41: 1 | G41: 45432 | H41: Avi | I41: good session, no notes | J41: Y | M41: 45439 | N41: Avi/Brooke | O41: Sneezed during beginning scans- Reran t1 fieldmaps | P41: Y | Q41: Y | R41: Y | U41: 45993 | V41: Sophie | X41: good session | Y41: Y | Z41: Y | AC41: 46035 | AD41: Avi | AE41: Megan | AF41: Andrew | AH41: a little claustrophobic at first but great session! Super still | AI41: y | AJ41: y | AK41: y
A42: 924 | B42: {=IFNA(XLOOKUP(A42,'New Signups'!C:C,'New Signups'!D:D),"-")} -> Yismeily | C42: {=IFNA(XLOOKUP(A42,'New Signups'!C:C,'New Signups'!E:E),"-")} -> Mezquita | D42: 2036 | E42: 1 | F42: 1 | G42: 5/22/2024 | H42: Murray | I42: good session no notes | J42: Y | M42: 45436 | N42: Harry/Murray | O42: no notes good scan | P42: Y | Q42: Y | R42: Y
A43: 912 | B43: {=IFNA(XLOOKUP(A43,'New Signups'!C:C,'New Signups'!D:D),"-")} -> Saige | C43: {=IFNA(XLOOKUP(A43,'New Signups'!C:C,'New Signups'!E:E),"-")} -> Williams | D43: 2037 | E43: 1 | F43: 1 | G43: 45449 | H43: Sheila/Camilla | I43: good session, no notes | J43: Y
A44: 761 | B44: {=IFNA(XLOOKUP(A44,'New Signups'!C:C,'New Signups'!D:D),"-")} -> Aniyah | C44: {=IFNA(XLOOKUP(A44,'New Signups'!C:C,'New Signups'!E:E),"-")} -> Reese | D44: 2038 | E44: 1 | F44: 1 | G44: 45480 | H44: Danny/Avi | I44: good session, no notes | J44: Y | M44: 45453 | N44: Danny/Avi | O44: no notes good scan | P44: Y | Q44: Y | R44: Y
A45: 963 | B45: {=IFNA(XLOOKUP(A45,'New Signups'!C:C,'New Signups'!D:D),"-")} -> Enrique | C45: {=IFNA(XLOOKUP(A45,'New Signups'!C:C,'New Signups'!E:E),"-")} -> Hernandez | D45: 2039 | E45: 1 | F45: 1 | G45: 45453 | H45: Samra/Shelia | I45: good session, no notes | J45: Y | M45: 45460 | N45: Brooke/Avi | O45: a bit figidy (images are blury in initial images), reran first round of pat, fourth round of gonogo got started late everything else ran smooth | P45: Y | Q45: Y | R45: Y | U45: 45968 | V45: Sophie | X45: Missing a ton of data... Not complete at all | Y45: Y | Z45: Y | AC45: 46009 | AD45: Megan | AE45: Abby | AH45: Great kid, session messed up - did not have a updated licenses for PAT so could not run | AI45: y | AJ45: y | AK45: y
A46: 981 | B46: {=IFNA(XLOOKUP(A46,'New Signups'!C:C,'New Signups'!D:D),"-")} -> Eliza | C46: {=IFNA(XLOOKUP(A46,'New Signups'!C:C,'New Signups'!E:E),"-")} -> Scott | D46: 2040 | E46: 1 | F46: 1 | G46: 45455 | H46: Danny/Avi | I46: good session, no notes | J46: Y | M46: 45457 | N46: Avi/Vince | O46: no notes | P46: Y | Q46: Y | R46: Y | U46: 45943 | V46: Kirsten | X46: avg notifications of '1' in DES is not accurate | Y46: Y | Z46: Y | AC46: 45968 | AD46: Kirsten | AE46: Binh | AH46: Good session | AI46: Y | AJ46: Y | AK46: Y
A47: 983 | B47: {=IFNA(XLOOKUP(A47,'New Signups'!C:C,'New Signups'!D:D),"-")} -> Jordan | C47: {=IFNA(XLOOKUP(A47,'New Signups'!C:C,'New Signups'!E:E),"-")} -> Coates Ahzai | D47: 2041 | E47: 1 | F47: 1 | G47: 45456 | H47: Danny | I47: great participant | J47: Y | M47: 45460 | N47: Avi/Sheila | O47: GoNoGo behavioral data didn't save | P47: Y | Q47: no GNG | R47: Y
A48: 1056 | B48: {=IFNA(XLOOKUP(A48,'New Signups'!C:C,'New Signups'!D:D),"-")} -> Julian | C48: {=IFNA(XLOOKUP(A48,'New Signups'!C:C,'New Signups'!E:E),"-")} -> Hoffman | D48: 2042 | E48: 1 | F48: 1 | G48: 45461 | H48: Danny/Binh | I48: good participant | J48: Y | M48: 45468 | N48: Avi/Murray | O48: no notes | P48: Y | Q48: Y | R48: Y
A49: 1053 | B49: {=IFNA(XLOOKUP(A49,'New Signups'!C:C,'New Signups'!D:D),"-")} -> Gianna | C49: {=IFNA(XLOOKUP(A49,'New Signups'!C:C,'New Signups'!E:E),"-")} -> Jones Smith | D49: 2043 | E49: 1 | F49: 1 | G49: 45464 | H49: Avi | I49: Participant was uncomfortable with taking the PAT photo and left mid visit. | J49: Y | M49: 45478 | N49: Avi/Megan/Sheila/Danny | O49: Ran DD alone with subid 1053 and ran foraging with 2053. We skipped PAT because she didn't consent to having her picture taken
A50: 1072 | B50: {=IFNA(XLOOKUP(A50,'New Signups'!C:C,'New Signups'!D:D),"-")} -> Manny | C50: {=IFNA(XLOOKUP(A50,'New Signups'!C:C,'New Signups'!E:E),"-")} -> Dachs | D50: 2044 | E50: originally v1.1 1072 | F50: 1 | G50: 45468 | H50: Binh/Murray | I50: no notes | J50: Y | M50: 45471 | N50: Danny/Avi | O50: T1 was initially set without being aligned. We ran t1 again to re-align but alignment box didn't apear. Re ran localizer and filedmaps in between PAT rounds. 3rd round of GNG started 30 seconds before scanner. | P50: Y | Q50: Y | R50: Y
A51: 1093 | B51: Dirk | C51: Spaeth | D51: 2045 | E51: 1 | F51: 1 | G51: 45476 | H51: Shulski | I51: fantastic p, computer crashed on pat, so we had to redo it | J51: Y | M51: 45482 | N51: Danny/Brooke | O51: Pat didn't work, no pat | P51: Y | Q51: Y | R51: Y | U51: 45979 | V51: Avi | Y51: Y | Z51: Y | AC51: 46042
A52: 1078 | B52: {=IFNA(XLOOKUP(A52,'New Signups'!C:C,'New Signups'!D:D),"-")} -> Dominic | C52: {=IFNA(XLOOKUP(A52,'New Signups'!C:C,'New Signups'!E:E),"-")} -> Fuhs | D52: 2046 | E52: 1 | F52: 1 | G52: 45476 | H52: Danny | I52: great participant | J52: Y | M52: 45478 | N52: Danny/Avi | O52: missing the first few trials of the second run of GNG. Had to skip PAT because it wasn't registering the button box inputs (eben though the box was lighting up on press) | P52: Y | Q52: Y | R52: Y | U52: 45841 | V52: Avi | X52: Couldn't run PAT because MATLAB wasn't launching after the Windows 11 update | Y52: Y | Z52: Y | AC52: 45860 | AD52: Avi | AE52: ? | AH52: (some internal self-tests and calibrations were skipped for PAT) | AI52: Y | AJ52: Y | AK52: Y
A53: 1109 | B53: {=IFNA(XLOOKUP(A53,'New Signups'!C:C,'New Signups'!D:D),"-")} -> Jahbril | C53: {=IFNA(XLOOKUP(A53,'New Signups'!C:C,'New Signups'!E:E),"-")} -> Jenkins | D53: 2047 | E53: 1 | F53: 1 | G53: 45480 | H53: Danny H | I53: great participant | J53: Y | M53: 45500 | N53: Murray/Megan | O53: no notes good scan | P53: Y | Q53: Y | R53: Y | U53: 46006 | V53: Kirsten | X53: Good session no notes | Y53: Y | Z53: y | AC53: 46010 | AD53: Megan | AE53: Abby | AH53: abby started GNG run three before run 2's scan was done... apparently she was too excited... | AI53: Y | AJ53: Y | AK53: Y
A54: 1110 | B54: {=IFNA(XLOOKUP(A54,'New Signups'!C:C,'New Signups'!D:D),"-")} -> Arman Jonathan (AJ) | C54: {=IFNA(XLOOKUP(A54,'New Signups'!C:C,'New Signups'!E:E),"-")} -> Froggatt | D54: 2048 | E54: 1 | F54: 1 | G54: 45481 | H54: Danny /Sheila | I54: great participant | J54: Y | M54: 45483 | N54: Danny/Brooke | O54: ASLEEP during first GNG round. Otherwise good P | P54: Y | Q54: Y | R54: Y | U54: 45963 | V54: Kirsten | X54: couldn't remeber the street name for one of his previous addresses in urbanicity survey | Y54: Y | AC54: 45980 | AD54: Kirsten | AE54: Megan | AH54: ? | AI54: Y | AJ54: y | AK54: y
A55: 1165 | B55: {=IFNA(XLOOKUP(A55,'New Signups'!C:C,'New Signups'!D:D),"-")} -> Juhlai | C55: {=IFNA(XLOOKUP(A55,'New Signups'!C:C,'New Signups'!E:E),"-")} -> Dixon | D55: 2049 | E55: 1 | F55: 1 | G55: 45484 | H55: Danny | I55: Screen time not turned on, we turned it on. Otherwise good P | J55: Y | M55: 45490 | N55: Danny | O55: Good scan | P55: Y | Q55: Y | R55: Y | U55: 45958 | V55: Maia | X55: Put PID as sibling for stoplight(1059.2). v2 receipt in incorrect redcap spot- please see v2 receipt in v1 . | Y55: y | Z55: y | AC55: 45972 | AD55: Isabel | AE55: Megan | AH55: Perfect! | AI55: Y | AJ55: Y | AK55: Y
A56: 1194 | B56: {=IFNA(XLOOKUP(A56,'New Signups'!C:C,'New Signups'!D:D),"-")} -> Noah | C56: {=IFNA(XLOOKUP(A56,'New Signups'!C:C,'New Signups'!E:E),"-")} -> Watts | D56: 2050 | E56: 1 | F56: 1 | G56: 45486 | H56: Murray | I56: great participant | J56: Y | M56: 45494 | N56: Murray/Avi | O56: reran t1, first one was too blurry from head movement | P56: Y | Q56: no GNG | R56: Y | U56: 46027 | V56: Avi | X56: Good session no notes | Y56: Y | Z56: Y | AC56: 46094 | AD56: Lina | AE56: Megan | AF56: Rae | AH56: had to rerun planetgonogo, nice kid
A57: 1076 | B57: {=IFNA(XLOOKUP(A57,'New Signups'!C:C,'New Signups'!D:D),"-")} -> Judah | C57: {=IFNA(XLOOKUP(A57,'New Signups'!C:C,'New Signups'!E:E),"-")} -> Watts | D57: 2051 | E57: 1 | F57: 1 | G57: 45486 | H57: Danny | I57: great participant | J57: Y | M57: 45494 | N57: Avi | O57: no notes good session | P57: Y | Q57: no GNG | R57: Y | U57: 46027 | V57: Avi | X57: Good session no notes | Y57: Y | Z57: Y | AH57: (run short ant)
A58: 1211 | B58: {=IFNA(XLOOKUP(A58,'New Signups'!C:C,'New Signups'!D:D),"-")} -> Sye | C58: Myrkse | D58: 2052 | E58: 1 | F58: 1 | G58: 45492 | H58: Sheila | I58: On the SnapChat question she checks it less then she answered (5-10 times instead). | J58: Y | M58: 45492 | N58: Danny/Murray | O58: No Notes, good session | P58: Y | Q58: Y | R58: Y | U58: 45964 | V58: Andrew | X58: couldnt run short ant will run on v2 | Y58: y | AC58: 45978 | AD58: Isabel | AE58: Kirsten | AH58: Started PAT 2 during the last 20 seconds of PAT 1. Skipped PAT 2 for time. | AI58: Y | AJ58: Y | AK58: Y
A59: 1203 | B59: {=IFNA(XLOOKUP(A59,'New Signups'!C:C,'New Signups'!D:D),"-")} -> Charle | C59: {=IFNA(XLOOKUP(A59,'New Signups'!C:C,'New Signups'!E:E),"-")} -> Jones | D59: 2053 | E59: 1 | F59: 1 | G59: 45492 | H59: Murray | I59: no notes grreat session- owe $2.00 | J59: Y | M59: 45506 | N59: Harry/ Brooke | O59: Ran 2135 for foraging | P59: Y | Q59: Y | R59: Y
A60: 1205 | B60: {=IFNA(XLOOKUP(A60,'New Signups'!C:C,'New Signups'!D:D),"-")} -> azeeza | C60: Edwards | D60: 2054 | E60: 1 | F60: 1 | G60: 45493 | H60: Danny | I60: good session no notes | J60: Y | M60: 45507 | N60: Avi and Megan | O60: GoNoGo behavioral data didn't save | P60: Y | Q60: Y | R60: Y
A61: 1088 | B61: {=IFNA(XLOOKUP(A61,'New Signups'!C:C,'New Signups'!D:D),"-")} -> Gilpatrick | C61: Yaacov | D61: 2055 | E61: 1 | F61: 1 | G61: 45495 | H61: Sheila | I61: good participant | J61: Y | M61: 45611 | N61: Avi/Danny | O61: Good visit no notes | P61: Y | Q61: Y | R61: Y | U61: 46101 | V61: Avi | X61: no notes | Y61: y | Z61: y | AC61: 46192 | AD61: Andrew | AE61: Anushka | AH61: GOOD SESSION NO NOTES | AI61: y | AJ61: y | AK61: y
A62: 1224 | B62: {=IFNA(XLOOKUP(A62,'New Signups'!C:C,'New Signups'!D:D),"-")} -> Camila | C62: Inés Franquie | D62: 2056 | E62: 1 | F62: 1 | G62: 45498 | H62: Danny | I62: good participant | J62: Y | M62: 45519 | N62: Avi/Murray | O62: put 2057 when registering for foraging- but all other tasks are good | P62: Y | Q62: Y | R62: Y
A63: 1201 | B63: {=IFNA(XLOOKUP(A63,'New Signups'!C:C,'New Signups'!D:D),"-")} -> Elijah | C63: Bowen | D63: 2057 | E63: 1 | F63: 1 | G63: 45502 | H63: Danny H | I63: visit took 3 hours long, data might be skewed due to user input | J63: Y | M63: 8/23/2024 | N63: Danny/Harrry | O63: ^ used 2056 for foraging. missed about 2 of every 3 in the second pat round but got the others. Otherwise good scan | P63: Y | Q63: Y | R63: Y
A64: 1261 | B64: {=IFNA(XLOOKUP(A64,'New Signups'!C:C,'New Signups'!D:D),"-")} -> Caron | C64: Blache | D64: 2058 | E64: 1 | F64: 1 | G64: 45503 | H64: Danny Z | I64: good participant, screen time off | J64: Y | M64: 45511 | N64: Danny/Brooke | O64: reran field maps before PAT. Reran localizer, field maps, and T1 before GNG. SECOND T1 is BETTER! NO DTI | P64: Y | Q64: Y | R64: Y
A65: 1141 | B65: {=IFNA(XLOOKUP(A65,'New Signups'!C:C,'New Signups'!D:D),"-")} -> Mia | C65: Haugen | D65: 2059 | E65: 1 | F65: 1 | G65: 45503 | H65: Binh | I65: good participant, Danny took the picture because Ipads were dead | J65: Y | M65: 45523 | N65: Murray/Harry | O65: no notes good scan | P65: Y | Q65: Y | R65: Y | U65: 46043 | V65: Sophie | X65: Good session no notes | Y65: Y | Z65: Y | AC65: 46124 | AD65: Avi | AE65: Anushka | AF65: Rae | AH65: No notes | AI65: Y | AJ65: Y | AK65: Y
A66: 1171 | B66: {=IFNA(XLOOKUP(A66,'New Signups'!C:C,'New Signups'!D:D),"-")} -> Chloe | C66: Rackley | D66: 2060 | E66: 1 | F66: 1 | G66: 45509 | H66: Sheila | I66: good participant | J66: Y | M66: 45531 | N66: Avi/Megan | O66: No pat - ran out of time | P66: Y | Q66: Y | R66: Y
A67: 1172 | B67: Kamryn | C67: Rackley | D67: 2061 | E67: 1 | G67: 45509 | H67: Danny H | I67: good participant | J67: Y | M67: 45531 | N67: Murray | O67: Had to rerun T1, did not do DTI due to time constraints. Was a 'wiggly' participant. | P67: Y | Q67: Y | R67: Y
A68: 1280 | B68: {=IFNA(XLOOKUP(A68,'New Signups'!C:C,'New Signups'!D:D),"-")} -> Owen | C68: Ganley | D68: 2062 | E68: 1 | F68: 1 | G68: 45510 | H68: Samra | I68: good session; no notes | J68: Y | M68: 45524 | N68: Danny/Harry | O68: no notes good session | P68: Y | Q68: Y | R68: Y | U68: 45996 | V68: Andrew | X68: good session no notes | Y68: y | Z68: y | AC68: 46045 | AD68: Lina | AE68: Megan | AF68: Abby | AG68: Anushka | AH68: RAN TWICE) scan one-> only ran DD alone and computer & L3 computer was not working - scan two-> Reran DD alone for the second scan - Abby started early for pat before scan was finished :( | AI68: Y | AJ68: Y | AK68: Y
A69: 1256 | B69: {=IFNA(XLOOKUP(A69,'New Signups'!C:C,'New Signups'!D:D),"-")} -> Emily | C69: Franque | D69: 2064 | E69: 1 | F69: 1 | G69: 45517 | H69: Sheila | I69: good session | J69: Y | M69: 45519 | N69: Murray | O69: no notes good session | P69: Y | Q69: Y | R69: Y
A70: 1346 | B70: Samurai | C70: Saputra | D70: 2065 | E70: 1 | F70: 1 | G70: 45517 | H70: Avi | I70: good session | J70: Y | M70: 45519 | N70: Avi/Danny H | O70: Couldn't fit in the MRI | P70: N | Q70: Y | R70: Y
A71: 1247 | B71: Valentina | C71: Franquie | D71: 2066 | E71: 1 | F71: 1 | G71: 45519 | H71: Avi | I71: good session no notes | J71: Y | M71: 45540 | N71: Murray/Megan | O71: no notes good session | P71: Y | Q71: Y | R71: Y
A72: 1122 | B72: Maria | C72: Montgomery | D72: 2067 | E72: originally v1.1 1122 | F72: 1 | G72: 45521 | H72: Murray | I72: good session no notes | J72: Y | M72: 45521 | N72: Murray | O72: Ran go no go before PAT | P72: Y | Q72: Y | R72: Y
A73: 1345 | B73: Gloriannah | C73: Black | D73: 2068 | E73: 1 | F73: 1 | G73: 45524 | H73: Binh | I73: good session no notes | J73: Y | M73: 8/21/2024 | N73: Avi/Danny/Harry | O73: no notes | P73: Y | Q73: Y | R73: Y
A74: 1376 | B74: Julian | C74: Lloret | D74: 2069 | E74: 1 | F74: 1 | G74: 45531 | H74: Murray | I74: Was in trouble and didn't have phone, so the DES section where phone is needed is not accurate data | J74: Y | M74: 45543 | N74: Avi/Murray | O74: braces, and moved the entire scan (severe ADHD -professional- diagnosis) data is likely not useable | P74: Y | Q74: Y | R74: Y | U74: 46054 | V74: Abby | X74: Got distracted when checking screentimes and stopped to scroll on his phone every now and then (during shortant was super disinterested and texting people), took a while to let me know he had reached a breakpoint each time, PAT photo not transferred to one drive bc it was signed out | Y74: Y | Z74: Y | AC74: 46061 | AD74: Avi | AE74: Megan | AF74: Kiara | AG74: Rae | AH74: DD not working. Slice number accidentally adjusted on bounding box screen. | AK74: Y
A75: 1398 | B75: Nina | C75: Chen | D75: 2070 | E75: 1 | F75: 1 | G75: 45531 | H75: Samra | I75: good session: no notes | J75: Y | M75: 45540 | N75: Murray/Megan | O75: braces | P75: Y | Q75: Y | R75: Y
A76: 1394 | B76: Sariyah | C76: Blackwell | D76: 2071 | E76: 1 | F76: 1 | G76: 45533 | H76: Murray | I76: good session: no notes | J76: Y | M76: 45538 | N76: Murray/Avi | O76: no notes | P76: Y | Q76: Y | R76: Y
A77: 1395 | B77: Shawn | C77: Blackwell | D77: 2072 | E77: 1 | F77: 1 | G77: 45533 | H77: Murray | I77: good session: no notes | J77: Y | M77: 45566 | N77: Murray/Avi | O77: no notes good session | P77: Y | Q77: Y | R77: Y
A78: 1388 | B78: Gracie | C78: Giron | D78: 2073 | E78: 1 | F78: 1 | G78: 45538 | H78: Murray | I78: good session: no notes | J78: Y | M78: 45544 | N78: Avi/Titiksha | O78: no notes | P78: Y | Q78: Y | R78: Y
A79: 1383 | B79: Khashia | C79: Griffin Smith | D79: 2074 | E79: 1 | F79: 1 | G79: 45539 | H79: Samra/Titiksha | I79: good session, no notes | J79: Y | M79: 45547 | N79: Danny/Titiksha | O79: good session (smelled a bit like weed - pottentially high, but seemed normal) | P79: Y | Q79: Y | R79: Y | U79: 46008 | V79: Kirsten | X79: Good session no notes | Y79: y | Z79: y | AC79: 46008
A80: 1428 | B80: Amira | C80: Norcott | D80: 2075 | E80: 1 | F80: 1 | G80: 45544 | H80: Samra | I80: good session; no notes | J80: Y | M80: 45551 | N80: Danny/Harry/Avi | O80: was clicking through dd alone and social super quickly- don't think he was really doing the task. GNG - FELL ASLEEP - DATA UNUSABLE. | P80: Y | Q80: Y | R80: Y | U80: 46055 | V80: Aashna | X80: Good session, kept going on phone during short ant though | Y80: Y | Z80: Nope, mistake on my part, would have to be paid online, cash was not given, receipt signed though | AC80: 46066 | AD80: Danny | AE80: Megan | AF80: Andrew | AH80: Put 17 not 19 for age for DD Alone / GNG crashes with 2 minutes left of last round
A81: 1390 | B81: Zachary | C81: Rubenstein | D81: 2076 | E81: 1 | F81: 1 | G81: 45549 | H81: Danny | I81: good session, no notes | J81: Y | M81: 45550 | N81: Hawk/Murray | O81: was clicking through dd alone and social super quickly- don't think he was really doing the task. | P81: Y | Q81: Y | R81: Y
A82: 1403 | B82: Irvin | C82: Hawkins | D82: 2077 | E82: 1 | F82: 1 | G82: 45549 | H82: Murray | I82: good session, no notes | J82: Y | M82: 45552 | N82: Danny/Avi | O82: He came 25 minutes late and there was a scan right behind us. The T1 was so messed up we had to re-do it after PAT. USE THE 2nd T1 All we got from the MRI was PAT, and the T1 - AD | P82: Y | Q82: Y | R82: Y | U82: 46162 | V82: Anushka | X82: came 40 mins late, texted receipt to parent because he came alone | Y82: Y | Z82: Y | AC82: 46184 | AD82: Avi | AE82: Anushka | AH82: His first T1 was blurry so we took another one | AI82: Y | AJ82: Y | AK82: Y
A83: 1366 | B83: {=IFNA(XLOOKUP(A83,'New Signups'!C:C,'New Signups'!D:D),"-")} -> Sarain | C83: {=IFNA(XLOOKUP(B83,'New Signups'!D:D,'New Signups'!E:E),"-")} -> Ceesay | D83: 2078 | E83: 1 | F83: 1 | G83: 45550 | H83: Avi | I83: good session, no notes | J83: Y | M83: 45550 | N83: Hawk/Murray | O83: no notes good session | P83: Y | Q83: Y | R83: Y | U83: 46062 | V83: Emily | W83: Andrew | X83: good session no notes | Y83: y | Z83: y | AD83: Shenghan | AE83: Lina | AH83: task computer misbehaving throughout Pat misbehaving: run 1 participant noticing when they press button 1 button 2 response was received, run 2 frequently not giving feedback despite the participant pressing the button repeatedly and responding. GonoGo: participant asked padding adjustment, reran localized before go-no-go And in run 2 the computer just forced out gonogo so partial run 2 and no run 3 and 4 ddsocial I adjusted the eprime experimental screen number to 1
A84: 1369 | B84: Vandalyn | C84: Marrow | D84: 2079 | E84: 1 | F84: 1 | G84: 45550 | H84: Murray | I84: good session, no notes | J84: Y | M84: 45585 | N84: Avi/Danny | O84: DTI before GnG. One round of GnG before DTI that is unusable | P84: Y | Q84: Y | R84: Y
A85: 1528 | B85: Dibanhi | C85: Ronzon Santamaria | D85: 2080 | E85: 1 | F85: 1 | G85: 45554 | H85: Binh | I85: Didn't have access to phone, put NA and No phone | J85: Y | M85: 45597 | N85: Danny/Avi/Sophie | O85: good esssion | P85: Y | Q85: Y | R85: Y
A86: 1453 | B86: Lillian | C86: Sacksith | D86: 2081 | E86: 1 | F86: 1 | G86: 45554 | H86: Samra | I86: good session; no notes | J86: Y | M86: 45580 | N86: Avi, Jamie (she had her headphones on full volume in the corner of the control room) | O86: GnG didn't save | P86: Y | Q86: Y | R86: Y | U86: 46059 | V86: Abby | W86: Anushka | X86: good session, no notes | Y86: Y | Z86: Y | AC86: 46093 | AD86: Avi | AE86: Abby | AH86: Good session no notes | AI86: Y | AJ86: Y | AK86: Y
A87: 1549 | B87: {=IFNA(XLOOKUP(A87,'New Signups'!C:C,'New Signups'!D:D),"-")} -> Marshall | C87: {=IFNA(XLOOKUP(B87,'New Signups'!D:D,'New Signups'!E:E),"-")} -> Toomey | D87: 2082 | E87: 1 | G87: 45559 | H87: Avi | I87: good session; no notes | J87: Y | M87: 45559 | N87: Avi, Titiksha | O87: He thought he was supposed to use the 3 key for PAT, so the first run is probably invalid | P87: Y | Q87: Y | R87: Y
A88: 1444 | B88: Jada | C88: Hudson | D88: 2083 | E88: 1 | F88: 1 | G88: 45558 | H88: Samra | I88: good session; no notes | J88: Y | M88: 45632 | N88: Danny/Avi | O88: Only T1 and DTI, GNG unusable. Kept falling asleep. | P88: Y | Q88: Y | R88: Y
A89: 1448 | B89: Declan | C89: Wilson | D89: 2084 | E89: 1 | F89: 1 | G89: 45560 | H89: Samra | I89: good session; no notes | J89: Y | M89: 45619 | N89: Danny/Avi | O89: no notes good session | P89: Y | Q89: Y | R89: Y | U89: 46113 | V89: Camilla | X89: good session, no notes | Y89: y | Z89: y | AC89: 46115 | AD89: Megan | AE89: Samra | AH89: PGNG Round 3 - scan ended three rounds before task ended // Skipped PAT (would not work, wrong participant's wave 1 data save)
A90: 1539 | B90: {=IFNA(XLOOKUP(A90,'New Signups'!C:C,'New Signups'!D:D),"-")} -> lexie | C90: {=IFNA(XLOOKUP(B90,'New Signups'!D:D,'New Signups'!E:E),"-")} -> rubincan | D90: 2085 | E90: 1 | F90: 1 | G90: 45560 | H90: Avi | I90: good session | J90: Y | M90: 45609 | N90: Avi/Megan | O90: GnG didn't save | P90: Y | Q90: Y | R90: Y | U90: 46090 | V90: Anushka | X90: good session no notes | Y90: Y | Z90: Y | AC90: 46149 | AD90: Avi | AE90: Anushka | AF90: Maia | AG90: Anushka | AH90: no notes, great scan | AI90: y | AJ90: y | AK90: y
A91: 1537 | B91: Oliver | C91: Mason | D91: 2086 | E91: 1 | F91: 1 | G91: 45562 | H91: Danny | I91: good session, no notes | J91: Y | M91: 45668 | N91: Danny/Avi | O91: GNG before PAT -- DONT USE FIRST ROUND OF GNG - didn't understand rules yet!! | P91: Y | Q91: Y | R91: Y
A92: 1531 | B92: Laylah | C92: Young | D92: 2087 | E92: 1 | F92: 1 | G92: 45563 | H92: Murray | I92: good session, no notes | J92: Y | M92: 45703 | N92: Avi/Megan | O92: wrong PID used in forgaing (1124) and skipped PAT | P92: Y | Q92: Y | R92: Y | U92: 46187 | V92: Rae | X92: participant did not complete uberball because she needed leave by 1p | Y92: Y | Z92: Y
A93: 1850 | B93: Niyale | C93: Byuard | D93: 2088 | E93: 1 | F93: 1 | G93: 45701 | H93: Danny | I93: no PAT, skipped QUIC, skipped game of dice, ant, uberball. P and mom were very skeptical and difficult, but we got stoplight and most self report data | J93: Y | M93: 45708 | N93: Avi/Megan | O93: Started PGNG late for the 3rd session, Skipped GNG part 4 (squeeze ball) and No PAT (did not have a photo)
A94: 1495 | B94: {=IFNA(XLOOKUP(A94,'New Signups'!C:C,'New Signups'!D:D),"-")} -> Jamel | C94: {=IFNA(XLOOKUP(B94,'New Signups'!D:D,'New Signups'!E:E),"-")} -> Maldonado | D94: 2089 | E94: 1 | F94: 1 | G94: 45563 | H94: Danny | I94: No screen time data (didn't bring phone) | J94: Y | M94: 45592 | N94: Danny/Avi | O94: no notes good session | P94: Y | Q94: Y | R94: Y
A95: 1546 | B95: Rylan | C95: Mumma | D95: 2090 | E95: 1 | F95: 1 | G95: 45565 | H95: Murray | I95: has dyslexia, took a little longer to work through the surveys | J95: Y | M95: 45615 | N95: Danny/Megan | O95: no notes good session | P95: Y | Q95: Y | R95: Y | U95: 46078 | V95: Emily | X95: participant did not complete surveys from PANAS-C to BREAK 3 - Have him complete these surveys in the testing room before v2! | Y95: Y | Z95: Y | AC95: 46100 | AD95: Megan | AE95: Andrew | AF95: Kiara | AH95: no bounding box??? | AJ95: y | AK95: y
A96: 1545 | B96: Everett | C96: Mumma | D96: 2091 | E96: 1 | F96: 1 | G96: 45565 | H96: Samra | I96: no notes good session | J96: Y | M96: 45615 | N96: Danny/Megan | O96: GNG BEFORE PAT. Also - Don't use very first run of PAt (only ran it for 2 seconds) then reran fielmaps and pat! | P96: Y | Q96: Y | R96: Y | U96: 46078 | V96: Binh | X96: good session no notes | Y96: Y | Z96: Y | AC96: 46100 | AD96: Megan | AE96: Andrew | AF96: Kiara | AH96: pgng crashed at the third set | AI96: y | AJ96: y | AK96: y
A97: 1558 | B97: Kyiah | C97: Andrews | D97: 2092 | E97: 1 | F97: 1 | G97: 45570 | H97: Murray | I97: no notes good session | J97: Y | M97: 45660 | N97: Danny/Shenghan | O97: First run of PAT restarted, using 2nd 2 rounds - otherwise great scan | P97: Y | Q97: Y | R97: Y
A98: 1494 | B98: Daniellah | C98: Torres | D98: 2093 | E98: 1 | F98: 1 | G98: 45566 | H98: Binh | I98: no notes good session | J98: Y | M98: 45600 | N98: Avi/Danny/Kirsten | O98: had to cut DTI for time | P98: Y | Q98: Y | R98: Y
A99: 1478 | B99: Michelle | C99: Yakupova | D99: 2094 | E99: 1 | F99: 1 | G99: 45571 | H99: Murray | I99: good session no notes | J99: Y | M99: 45598 | N99: Danny/Murray | O99: no notes good session | P99: Y | Q99: Y | R99: Y
A100: 1571 | B100: {=IFNA(XLOOKUP(A100,'New Signups'!C:C,'New Signups'!D:D),"-")} -> Tristan | C100: {=IFNA(XLOOKUP(B100,'New Signups'!D:D,'New Signups'!E:E),"-")} -> Labor | D100: 2095 | E100: 1 | F100: 1 | G100: 45575 | H100: Avi | I100: good session no notes | J100: Y | M100: 45617 | N100: Vince/Avi/Samra | O100: Cut everything except dti due to needing to adjust head coil + being late | P100: Y | Q100: Y | R100: Y | U100: 46083 | V100: Samra | X100: good session, no notes | Y100: Y | Z100: Y | AC100: 46101 | AD100: Shenghan | AE100: Samra | AH100: pat1 stuck and has to be restarted after practice moved somewhat during pat run 2; Otherwise great participant and smooth session | AI100: y
...

Sheet Factors
B2: To remove researchers from this sheet, delete their names from the Scheduling Eligibility tab
C4: Scan | E4: Scan shadow | G4: V1
C5: L3 | D5: L2 | E5: L3 | F5: L2 | G5: V1 | H5: V1 Shadow
B6: =if('Scheduling Eligibility'!C4=0,"",'Scheduling Eligibility'!C4) -> Anushka | D6: 1 | E6: 1 | G6: 1
B7: =if('Scheduling Eligibility'!C5=0,"",'Scheduling Eligibility'!C5) -> Avi | C7: 1 | D7: 1 | G7: 1
B8: =if('Scheduling Eligibility'!C6=0,"",'Scheduling Eligibility'!C6) -> Megan | C8: 1 | D8: 1 | G8: 1
B9: =if('Scheduling Eligibility'!C7=0,"",'Scheduling Eligibility'!C7) -> Abby | D9: 1 | G9: 1
B10: =if('Scheduling Eligibility'!C8=0,"",'Scheduling Eligibility'!C8) -> Andrew | C10: 1 | D10: 1 | G10: 1
B11: =if('Scheduling Eligibility'!C9=0,"",'Scheduling Eligibility'!C9) -> Kiara | F11: 1 | H11: 1
B12: =if('Scheduling Eligibility'!C10=0,"",'Scheduling Eligibility'!C10) -> Danny | C12: 100
B13: =if('Scheduling Eligibility'!C11=0,"",'Scheduling Eligibility'!C11) -> Alicia | F13: 1 | G13: 1
B14: =if('Scheduling Eligibility'!C12=0,"",'Scheduling Eligibility'!C12) -> Camilla | D14: 1 | E14: 100 | G14: 1
B15: =if('Scheduling Eligibility'!C13=0,"",'Scheduling Eligibility'!C13) -> Maia | D15: 1 | G15: 1
B16: =if('Scheduling Eligibility'!C14=0,"",'Scheduling Eligibility'!C14) -> Aashna | F16: 1 | G16: 1
B17: =if('Scheduling Eligibility'!C15=0,"",'Scheduling Eligibility'!C15) -> Isabel | C17: 1 | D17: 1
B18: =if('Scheduling Eligibility'!C16=0,"",'Scheduling Eligibility'!C16) -> Lina | C18: 1
B19: =if('Scheduling Eligibility'!C17=0,"",'Scheduling Eligibility'!C17) -> Shenghan | C19: 100 | F19: 1
B20: =if('Scheduling Eligibility'!C18=0,"",'Scheduling Eligibility'!C18) -> Rae | F20: 1 | G20: 1
B21: =if('Scheduling Eligibility'!C19=0,"",'Scheduling Eligibility'!C19) -> Sophie | E21: 1 | F21: 1 | G21: 1
B22: =if('Scheduling Eligibility'!C20=0,"",'Scheduling Eligibility'!C20) -> Emily | F22: 1 | G22: 1
B23: =if('Scheduling Eligibility'!C21=0,"",'Scheduling Eligibility'!C21) -> Samra
B24: =if('Scheduling Eligibility'!C22=0,"",'Scheduling Eligibility'!C22) -> Natalie
B26: =if('Scheduling Eligibility'!C24=0,"",'Scheduling Eligibility'!C24)
B27: =if('Scheduling Eligibility'!C25=0,"",'Scheduling Eligibility'!C25)
B28: =if('Scheduling Eligibility'!C26=0,"",'Scheduling Eligibility'!C26)
B29: =if('Scheduling Eligibility'!C27=0,"",'Scheduling Eligibility'!C27)
B30: =if('Scheduling Eligibility'!C28=0,"",'Scheduling Eligibility'!C28)
B31: =if('Scheduling Eligibility'!C29=0,"",'Scheduling Eligibility'!C29)
B32: =if('Scheduling Eligibility'!C30=0,"",'Scheduling Eligibility'!C30)
B33: =if('Scheduling Eligibility'!C31=0,"",'Scheduling Eligibility'!C31)
B34: =if('Scheduling Eligibility'!C32=0,"",'Scheduling Eligibility'!C32)
B35: =if('Scheduling Eligibility'!C33=0,"",'Scheduling Eligibility'!C33)
... B42: =if('Scheduling Eligibility'!C40=0,"",'Scheduling Eligibility'!C40)

Sheet Scheduling Code
A2: Decimal | B2: Researcher | C2: L3 | D2: L2 | E2: L3 | F2: L2 | G2: V1 | H2: V1 Shadow | I2: Screeners | J2: Screeners Shadow | N2: L3 | O2: L2 | P2: L3 | Q2: L2 | R2: V1 | S2: V1 Shadow | T2: Screeners | U2: Screeners Shadow
A3: 0.01 | B3: =if('Scheduling Eligibility'!C4=0,"",'Scheduling Eligibility'!C4) -> Anushka | C3: =$A3+iferror(100*Factors!C6/(1+'Scheduling Eligibility'!$D4),100+Factors!C6) -> 0.01 | D3: =$A3+iferror(100*Factors!D6/(1+'Scheduling Eligibility'!$D4),100+Factors!D6) -> 6.26 | E3: =$A3+iferror(100*Factors!E6/(1+'Scheduling Eligibility'!$D4),100+Factors!E6) -> 6.26 | F3: =$A3+iferror(100*Factors!F6/(1+'Scheduling Eligibility'!$D4),100+Factors!F6) -> 0.01 | G3: =$A3+iferror(100*Factors!G6/(1+'Scheduling Eligibility'!$D4),100+Factors!G6) -> 6.26 | H3: =$A3+iferror(100*Factors!H6/(1+'Scheduling Eligibility'!$D4),100+Factors!H6) -> 0.01 | I3: =$A3+iferror(100*#REF!/(1+'Scheduling Eligibility'!$E4),100+#REF!) -> #REF! | J3: =$A3+iferror(100*#REF!/(1+'Scheduling Eligibility'!$E4),100+#REF!) -> #REF! | N3: =xlookup(large(C:C,1),C:C,$B:$B) -> Shenghan | O3: =xlookup(large(D:D,1),D:D,$B:$B) -> Isabel | P3: =xlookup(large(E:E,1),E:E,$B:$B) -> Camilla | Q3: =xlookup(large(F:F,1),F:F,$B:$B) -> Aashna | R3: =xlookup(large(G:G,1),G:G,$B:$B) -> Aashna | S3: =xlookup(large(H:H,1),H:H,$B:$B) -> Kiara | T3: =xlookup(large(I:I,1),I:I,$B:$B) -> #REF! | U3: =xlookup(large(J:J,1),J:J,$B:$B) -> #REF!
A4: 0.02 | B4: =if('Scheduling Eligibility'!C5=0,"",'Scheduling Eligibility'!C5) -> Avi | C4: =$A4+iferror(100*Factors!C7/(1+'Scheduling Eligibility'!$D5),100+Factors!C7) -> 4.7819048 | D4: =$A4+iferror(100*Factors!D7/(1+'Scheduling Eligibility'!$D5),100+Factors!D7) -> 4.7819048 | E4: =$A4+iferror(100*Factors!E7/(1+'Scheduling Eligibility'!$D5),100+Factors!E7) -> 0.02 | F4: =$A4+iferror(100*Factors!F7/(1+'Scheduling Eligibility'!$D5),100+Factors!F7) -> 0.02 | G4: =$A4+iferror(100*Factors!G7/(1+'Scheduling Eligibility'!$D5),100+Factors!G7) -> 4.7819048 | H4: =$A4+iferror(100*Factors!H7/(1+'Scheduling Eligibility'!$D5),100+Factors!H7) -> 0.02 | I4: =$A4+iferror(100*#REF!/(1+'Scheduling Eligibility'!$E5),100+#REF!) -> #REF! | J4: =$A4+iferror(100*#REF!/(1+'Scheduling Eligibility'!$E5),100+#REF!) -> #REF! | N4: =xlookup(large(C:C,2),C:C,$B:$B) -> Danny | O4: =xlookup(large(D:D,2),D:D,$B:$B) -> Maia | P4: =xlookup(large(E:E,2),E:E,$B:$B) -> Sophie | Q4: =xlookup(large(F:F,2),F:F,$B:$B) -> Shenghan | R4: =xlookup(large(G:G,2),G:G,$B:$B) -> Alicia | S4: =xlookup(large(H:H,2),H:H,$B:$B) -> x | T4: =xlookup(large(I:I,2),I:I,$B:$B) -> #REF! | U4: =xlookup(large(J:J,2),J:J,$B:$B) -> #REF!
A5: 0.03 | B5: =if('Scheduling Eligibility'!C6=0,"",'Scheduling Eligibility'!C6) -> Megan | C5: =$A5+iferror(100*Factors!C8/(1+'Scheduling Eligibility'!$D6),100+Factors!C8) -> 5.5855556 | D5: =$A5+iferror(100*Factors!D8/(1+'Scheduling Eligibility'!$D6),100+Factors!D8) -> 5.5855556 | E5: =$A5+iferror(100*Factors!E8/(1+'Scheduling Eligibility'!$D6),100+Factors!E8) -> 0.03 | F5: =$A5+iferror(100*Factors!F8/(1+'Scheduling Eligibility'!$D6),100+Factors!F8) -> 0.03 | G5: =$A5+iferror(100*Factors!G8/(1+'Scheduling Eligibility'!$D6),100+Factors!G8) -> 5.5855556 | H5: =$A5+iferror(100*Factors!H8/(1+'Scheduling Eligibility'!$D6),100+Factors!H8) -> 0.03 | I5: =$A5+iferror(100*#REF!/(1+'Scheduling Eligibility'!$E6),100+#REF!) -> #REF! | J5: =$A5+iferror(100*#REF!/(1+'Scheduling Eligibility'!$E6),100+#REF!) -> #REF! | N5: =xlookup(large(C:C,3),C:C,$B:$B) -> Lina | O5: =xlookup(large(D:D,3),D:D,$B:$B) -> Camilla | P5: =xlookup(large(E:E,3),E:E,$B:$B) -> Anushka | Q5: =xlookup(large(F:F,3),F:F,$B:$B) -> Alicia | R5: =xlookup(large(G:G,3),G:G,$B:$B) -> Emily | S5: =xlookup(large(H:H,3),H:H,$B:$B) -> x | T5: =xlookup(large(I:I,3),I:I,$B:$B) -> #REF! | U5: =xlookup(large(J:J,3),J:J,$B:$B) -> #REF!
A6: 0.04 | B6: =if('Scheduling Eligibility'!C7=0,"",'Scheduling Eligibility'!C7) -> Abby | C6: =$A6+iferror(100*Factors!C9/(1+'Scheduling Eligibility'!$D7),100+Factors!C9) -> 0.04 | D6: =$A6+iferror(100*Factors!D9/(1+'Scheduling Eligibility'!$D7),100+Factors!D9) -> 11.151111 | E6: =$A6+iferror(100*Factors!E9/(1+'Scheduling Eligibility'!$D7),100+Factors!E9) -> 0.04 | F6: =$A6+iferror(100*Factors!F9/(1+'Scheduling Eligibility'!$D7),100+Factors!F9) -> 0.04 | G6: =$A6+iferror(100*Factors!G9/(1+'Scheduling Eligibility'!$D7),100+Factors!G9) -> 11.151111 | H6: =$A6+iferror(100*Factors!H9/(1+'Scheduling Eligibility'!$D7),100+Factors!H9) -> 0.04 | I6: =$A6+iferror(100*#REF!/(1+'Scheduling Eligibility'!$E7),100+#REF!) -> #REF! | J6: =$A6+iferror(100*#REF!/(1+'Scheduling Eligibility'!$E7),100+#REF!) -> #REF! | N6: =xlookup(large(C:C,4),C:C,$B:$B) -> Isabel | O6: =xlookup(large(D:D,4),D:D,$B:$B) -> Abby | P6: =xlookup(large(E:E,4),E:E,$B:$B) -> x | Q6: =xlookup(large(F:F,4),F:F,$B:$B) -> Emily | R6: =xlookup(large(G:G,4),G:G,$B:$B) -> Sophie | S6: =xlookup(large(H:H,4),H:H,$B:$B) -> x | T6: =xlookup(large(I:I,4),I:I,$B:$B) -> #REF! | U6: =xlookup(large(J:J,4),J:J,$B:$B) -> #REF!
A7: 0.05 | B7: =if('Scheduling Eligibility'!C8=0,"",'Scheduling Eligibility'!C8) -> Andrew | C7: =$A7+iferror(100*Factors!C10/(1+'Scheduling Eligibility'!$D8),100+Factors!C10) -> 5.6055556 | D7: =$A7+iferror(100*Factors!D10/(1+'Scheduling Eligibility'!$D8),100+Factors!D10) -> 5.6055556 | E7: =$A7+iferror(100*Factors!E10/(1+'Scheduling Eligibility'!$D8),100+Factors!E10) -> 0.05 | F7: =$A7+iferror(100*Factors!F10/(1+'Scheduling Eligibility'!$D8),100+Factors!F10) -> 0.05 | G7: =$A7+iferror(100*Factors!G10/(1+'Scheduling Eligibility'!$D8),100+Factors!G10) -> 5.6055556 | H7: =$A7+iferror(100*Factors!H10/(1+'Scheduling Eligibility'!$D8),100+Factors!H10) -> 0.05 | I7: =$A7+iferror(100*#REF!/(1+'Scheduling Eligibility'!$E8),100+#REF!) -> #REF! | J7: =$A7+iferror(100*#REF!/(1+'Scheduling Eligibility'!$E8),100+#REF!) -> #REF! | N7: =xlookup(large(C:C,5),C:C,$B:$B) -> Andrew | O7: =xlookup(large(D:D,5),D:D,$B:$B) -> Anushka | P7: =xlookup(large(E:E,5),E:E,$B:$B) -> x | Q7: =xlookup(large(F:F,5),F:F,$B:$B) -> Kiara | R7: =xlookup(large(G:G,5),G:G,$B:$B) -> Rae | S7: =xlookup(large(H:H,5),H:H,$B:$B) -> x | T7: =xlookup(large(I:I,5),I:I,$B:$B) -> #REF! | U7: =xlookup(large(J:J,5),J:J,$B:$B) -> #REF!
